Workbook
Name _3t21pjvpxv31: Task2!$A$6
Name Days: [1]DataValidation!$V$2:$V$20
Name Dy: OFFSET([1]Offset!$A$1,0,0,COUNTA([1]Offset!$A:$A),COUNTA([1]Offset!$1:$1))
Name DynamicRange: OFFSET([1]Offset!$A$1,0,0,COUNTA([1]Offset!$A:$A),COUNTA([1]Offset!$1:$1))
Name DynamicTable: OFFSET([2]PivotTable1.2!$A$1,0,0,COUNTA([2]PivotTable1.2!$A:$A),COUNTA([2]PivotTable1.2!$1:$1))
Name HR_Header: #REF!
Name MonthlyIncome: [3]NamedRange!$O$3:$O$1472
Name MonthlyRate: [3]NamedRange!$P$3:$P$1472
Name NativeTimeline_Order_Date: #N/A
Name OrdId: [4]VLookUp!$A$1:$A$4577
Name Quantity: [4]MathsFunctions!$D$3:$D$22
Name Slicer_Delivery_Status: #N/A
Name Slicer_Payment_Method: #N/A
Name Slicer_Region: #N/A

Sheet AmazonSales
A1: Order ID | B1: Order Date | C1: Delivery Date | D1: Cancel Date | E1: Customer ID | F1: Product ID | G1: Region | H1: Sale Price/Unit | I1: Quantity | J1: Total Amount | K1: Payment Method | L1: Delivery Status | M1: Fulfillment Partner
A2: ORD0001 | B2: 12/31/2023 | D2: 1/2/2024 | E2: CUST021 | F2: PROD012 | G2: North | H2: 44 | I2: 1 | J2: 44 | K2: Apple Pay | L2: Cancelled | M2: DHL
A3: ORD0002 | B3: 2/22/2023 | C3: 2/24/2023 | E3: CUST029 | F3: PROD018 | G3: East | H3: 96 | I3: 4 | J3: 384 | K3: Credit Card | L3: Delivered | M3: DHL
A4: ORD0003 | B4: 10/11/2023 | E4: CUST021 | F4: PROD013 | G4: South | H4: 194 | I4: 4 | J4: 776 | K4: Credit Card | L4: In Transit | M4: USPS
A5: ORD0004 | B5: 5/5/2023 | D5: 5/11/2023 | E5: CUST044 | F5: PROD013 | G5: North | H5: 196 | I5: 3 | J5: 588 | K5: PayPal | L5: Cancelled | M5: UPS
A6: ORD0005 | B6: 2/2/2023 | C6: 2/5/2023 | E6: CUST027 | F6: PROD010 | G6: North | H6: 59 | I6: 1 | J6: 59 | K6: PayPal | L6: Delivered | M6: Amazon Logistics
A7: ORD0006 | B7: 11/1/2023 | D7: 11/2/2023 | E7: CUST009 | F7: PROD010 | G7: North | H7: 58 | I7: 4 | J7: 232 | K7: Amazon Pay | L7: Cancelled | M7: DHL
A8: ORD0007 | B8: 8/14/2023 | D8: 8/18/2023 | E8: CUST042 | F8: PROD020 | G8: Central | H8: 105 | I8: 3 | J8: 315 | K8: Debit Card | L8: Cancelled | M8: DHL
A9: ORD0008 | B9: 4/1/2023 | D9: 4/6/2023 | E9: CUST019 | F9: PROD021 | G9: West | H9: 37 | I9: 5 | J9: 185 | K9: PayPal | L9: Cancelled | M9: DHL
A10: ORD0009 | B10: 7/21/2023 | E10: CUST013 | F10: PROD019 | G10: Central | H10: 44 | I10: 2 | J10: 88 | K10: Credit Card | L10: In Transit | M10: Amazon Logistics
A11: ORD0010 | B11: 12/29/2023 | E11: CUST019 | F11: PROD003 | G11: South | H11: 141 | I11: 4 | J11: 564 | K11: Debit Card | L11: In Transit | M11: DHL
A12: ORD0011 | B12: 5/4/2023 | D12: 5/8/2023 | E12: CUST046 | F12: PROD014 | G12: South | H12: 249 | I12: 1 | J12: 249 | K12: Amazon Pay | L12: Cancelled | M12: USPS
A13: ORD0012 | B13: 7/25/2023 | E13: CUST045 | F13: PROD014 | G13: Central | H13: 247 | I13: 3 | J13: 741 | K13: Amazon Pay | L13: In Transit | M13: FedEx
A14: ORD0013 | B14: 2/25/2023 | D14: 2/28/2023 | E14: CUST023 | F14: PROD006 | G14: Central | H14: 96 | I14: 1 | J14: 96 | K14: Apple Pay | L14: Cancelled | M14: Amazon Logistics
A15: ORD0014 | B15: 2/24/2023 | D15: 2/25/2023 | E15: CUST033 | F15: PROD017 | G15: West | H15: 74 | I15: 5 | J15: 370 | K15: Apple Pay | L15: Cancelled | M15: Amazon Logistics
A16: ORD0015 | B16: 8/26/2023 | D16: 9/2/2023 | E16: CUST033 | F16: PROD005 | G16: South | H16: 27 | I16: 1 | J16: 27 | K16: Credit Card | L16: Cancelled | M16: Amazon Logistics
A17: ORD0016 | B17: 2/13/2023 | E17: CUST047 | F17: PROD005 | G17: South | H17: 27 | I17: 3 | J17: 81 | K17: Debit Card | L17: In Transit | M17: Amazon Logistics
A18: ORD0017 | B18: 6/28/2023 | C18: 7/1/2023 | E18: CUST045 | F18: PROD015 | G18: East | H18: 21 | I18: 3 | J18: 63 | K18: Credit Card | L18: Delivered | M18: DHL
A19: ORD0018 | B19: 11/28/2023 | E19: CUST011 | F19: PROD008 | G19: West | H19: 70 | I19: 5 | J19: 350 | K19: PayPal | L19: In Transit | M19: Amazon Logistics
A20: ORD0019 | B20: 8/25/2023 | E20: CUST041 | F20: PROD006 | G20: South | H20: 94 | I20: 4 | J20: 376 | K20: Credit Card | L20: In Transit | M20: USPS
A21: ORD0020 | B21: 4/12/2023 | E21: CUST025 | F21: PROD001 | G21: North | H21: 813 | I21: 2 | J21: 1626 | K21: Credit Card | L21: In Transit | M21: FedEx
A22: ORD0021 | B22: 10/2/2023 | E22: CUST013 | F22: PROD015 | G22: Central | H22: 21 | I22: 4 | J22: 84 | K22: PayPal | L22: In Transit | M22: Amazon Logistics
A23: ORD0022 | B23: 11/9/2023 | E23: CUST023 | F23: PROD012 | G23: West | H23: 46 | I23: 5 | J23: 230 | K23: PayPal | L23: In Transit | M23: USPS
A24: ORD0023 | B24: 2/13/2023 | D24: 2/14/2023 | E24: CUST016 | F24: PROD010 | G24: West | H24: 58 | I24: 3 | J24: 174 | K24: Amazon Pay | L24: Cancelled | M24: Amazon Logistics
A25: ORD0024 | B25: 11/2/2023 | C25: 11/5/2023 | E25: CUST028 | F25: PROD006 | G25: West | H25: 96 | I25: 5 | J25: 480 | K25: Amazon Pay | L25: Delivered | M25: Amazon Logistics
A26: ORD0025 | B26: 5/28/2023 | C26: 5/30/2023 | E26: CUST040 | F26: PROD002 | G26: South | H26: 43 | I26: 1 | J26: 43 | K26: Debit Card | L26: Delivered | M26: Amazon Logistics
A27: ORD0026 | B27: 10/15/2023 | C27: 10/21/2023 | E27: CUST027 | F27: PROD022 | G27: South | H27: 64 | I27: 4 | J27: 256 | K27: Debit Card | L27: Delivered | M27: USPS
A28: ORD0027 | B28: 1/16/2023 | E28: CUST018 | F28: PROD008 | G28: South | H28: 70 | I28: 2 | J28: 140 | K28: Amazon Pay | L28: In Transit | M28: Amazon Logistics
A29: ORD0028 | B29: 10/9/2023 | E29: CUST018 | F29: PROD018 | G29: Central | H29: 97 | I29: 3 | J29: 291 | K29: Credit Card | L29: In Transit | M29: Amazon Logistics
A30: ORD0029 | B30: 10/7/2023 | D30: 10/10/2023 | E30: CUST007 | F30: PROD021 | G30: East | H30: 37 | I30: 3 | J30: 111 | K30: Apple Pay | L30: Cancelled | M30: DHL
A31: ORD0030 | B31: 2/14/2023 | E31: CUST008 | F31: PROD008 | G31: North | H31: 69 | I31: 5 | J31: 345 | K31: Amazon Pay | L31: In Transit | M31: Amazon Logistics
A32: ORD0031 | B32: 3/26/2023 | E32: CUST014 | F32: PROD002 | G32: North | H32: 42 | I32: 5 | J32: 210 | K32: Amazon Pay | L32: In Transit | M32: UPS
A33: ORD0032 | B33: 6/15/2023 | D33: 6/22/2023 | E33: CUST037 | F33: PROD009 | G33: East | H33: 11 | I33: 5 | J33: 55 | K33: Debit Card | L33: Cancelled | M33: FedEx
A34: ORD0033 | B34: 5/22/2023 | C34: 5/23/2023 | E34: CUST016 | F34: PROD005 | G34: South | H34: 27 | I34: 2 | J34: 54 | K34: Apple Pay | L34: Delivered | M34: USPS
A35: ORD0034 | B35: 11/20/2023 | E35: CUST025 | F35: PROD015 | G35: South | H35: 21 | I35: 1 | J35: 21 | K35: Amazon Pay | L35: In Transit | M35: DHL
A36: ORD0035 | B36: 12/22/2023 | C36: 12/26/2023 | E36: CUST032 | F36: PROD011 | G36: South | H36: 172 | I36: 1 | J36: 172 | K36: PayPal | L36: Delivered | M36: USPS
A37: ORD0036 | B37: 7/23/2023 | E37: CUST014 | F37: PROD016 | G37: North | H37: 212 | I37: 3 | J37: 636 | K37: Amazon Pay | L37: In Transit | M37: UPS
A38: ORD0037 | B38: 10/17/2023 | C38: 10/22/2023 | E38: CUST044 | F38: PROD002 | G38: East | H38: 41 | I38: 4 | J38: 164 | K38: Credit Card | L38: Delivered | M38: Amazon Logistics
A39: ORD0038 | B39: 8/22/2023 | D39: 8/24/2023 | E39: CUST028 | F39: PROD007 | G39: North | H39: 32 | I39: 2 | J39: 64 | K39: Debit Card | L39: Cancelled | M39: FedEx
A40: ORD0039 | B40: 12/2/2023 | E40: CUST024 | F40: PROD022 | G40: East | H40: 66 | I40: 2 | J40: 132 | K40: Apple Pay | L40: In Transit | M40: DHL
A41: ORD0040 | B41: 12/25/2023 | E41: CUST006 | F41: PROD004 | G41: East | H41: 62 | I41: 4 | J41: 248 | K41: Debit Card | L41: In Transit | M41: UPS
A42: ORD0041 | B42: 9/23/2023 | C42: 9/30/2023 | E42: CUST001 | F42: PROD011 | G42: West | H42: 173 | I42: 4 | J42: 692 | K42: Apple Pay | L42: Delivered | M42: UPS
A43: ORD0042 | B43: 7/16/2023 | C43: 7/18/2023 | E43: CUST007 | F43: PROD004 | G43: West | H43: 63 | I43: 3 | J43: 189 | K43: Apple Pay | L43: Delivered | M43: UPS
A44: ORD0043 | B44: 2/5/2023 | D44: 2/11/2023 | E44: CUST040 | F44: PROD021 | G44: West | H44: 36 | I44: 3 | J44: 108 | K44: Debit Card | L44: Cancelled | M44: USPS
A45: ORD0044 | B45: 12/18/2023 | D45: 12/23/2023 | E45: CUST006 | F45: PROD004 | G45: Central | H45: 62 | I45: 1 | J45: 62 | K45: Apple Pay | L45: Cancelled | M45: Amazon Logistics
A46: ORD0045 | B46: 6/11/2023 | D46: 6/14/2023 | E46: CUST042 | F46: PROD003 | G46: Central | H46: 137 | I46: 5 | J46: 685 | K46: Amazon Pay | L46: Cancelled | M46: FedEx
A47: ORD0046 | B47: 12/4/2023 | C47: 12/8/2023 | E47: CUST039 | F47: PROD017 | G47: North | H47: 73 | I47: 4 | J47: 292 | K47: Credit Card | L47: Delivered | M47: Amazon Logistics
A48: ORD0047 | B48: 7/17/2023 | C48: 7/19/2023 | E48: CUST041 | F48: PROD020 | G48: North | H48: 104 | I48: 1 | J48: 104 | K48: PayPal | L48: Delivered | M48: Amazon Logistics
A49: ORD0048 | B49: 10/19/2023 | C49: 10/24/2023 | E49: CUST044 | F49: PROD006 | G49: East | H49: 97 | I49: 1 | J49: 97 | K49: Amazon Pay | L49: Delivered | M49: FedEx
A50: ORD0049 | B50: 5/15/2023 | E50: CUST026 | F50: PROD017 | G50: South | H50: 73 | I50: 5 | J50: 365 | K50: Apple Pay | L50: In Transit | M50: Amazon Logistics
A51: ORD0050 | B51: 2/12/2023 | C51: 2/19/2023 | E51: CUST040 | F51: PROD005 | G51: East | H51: 27 | I51: 3 | J51: 81 | K51: Amazon Pay | L51: Delivered | M51: UPS
A52: ORD0051 | B52: 10/2/2023 | E52: CUST041 | F52: PROD021 | G52: North | H52: 37 | I52: 1 | J52: 37 | K52: Apple Pay | L52: In Transit | M52: UPS
A53: ORD0052 | B53: 1/30/2023 | C53: 2/1/2023 | E53: CUST008 | F53: PROD015 | G53: North | H53: 22 | I53: 1 | J53: 22 | K53: Debit Card | L53: Delivered | M53: FedEx
A54: ORD0053 | B54: 12/29/2023 | C54: 1/1/2024 | E54: CUST011 | F54: PROD016 | G54: Central | H54: 218 | I54: 5 | J54: 1090 | K54: PayPal | L54: Delivered | M54: DHL
A55: ORD0054 | B55: 3/6/2023 | D55: 3/13/2023 | E55: CUST018 | F55: PROD004 | G55: North | H55: 64 | I55: 1 | J55: 64 | K55: Apple Pay | L55: Cancelled | M55: USPS
A56: ORD0055 | B56: 2/2/2023 | C56: 2/6/2023 | E56: CUST037 | F56: PROD021 | G56: Central | H56: 36 | I56: 4 | J56: 144 | K56: PayPal | L56: Delivered | M56: Amazon Logistics
A57: ORD0056 | B57: 10/18/2023 | C57: 10/21/2023 | E57: CUST017 | F57: PROD004 | G57: West | H57: 65 | I57: 1 | J57: 65 | K57: Amazon Pay | L57: Delivered | M57: FedEx
A58: ORD0057 | B58: 1/7/2023 | C58: 1/9/2023 | E58: CUST025 | F58: PROD005 | G58: Central | H58: 26 | I58: 1 | J58: 26 | K58: Apple Pay | L58: Delivered | M58: DHL
A59: ORD0058 | B59: 5/8/2023 | E59: CUST021 | F59: PROD009 | G59: North | H59: 11 | I59: 5 | J59: 55 | K59: Credit Card | L59: In Transit | M59: FedEx
A60: ORD0059 | B60: 4/2/2023 | D60: 4/5/2023 | E60: CUST003 | F60: PROD013 | G60: North | H60: 195 | I60: 4 | J60: 780 | K60: PayPal | L60: Cancelled | M60: FedEx
A61: ORD0060 | B61: 10/11/2023 | D61: 10/12/2023 | E61: CUST019 | F61: PROD019 | G61: West | H61: 44 | I61: 5 | J61: 220 | K61: Apple Pay | L61: Cancelled | M61: USPS
A62: ORD0061 | B62: 9/10/2023 | E62: CUST035 | F62: PROD008 | G62: East | H62: 69 | I62: 4 | J62: 276 | K62: Debit Card | L62: In Transit | M62: DHL
A63: ORD0062 | B63: 11/22/2023 | C63: 11/29/2023 | E63: CUST022 | F63: PROD001 | G63: North | H63: 815 | I63: 4 | J63: 3260 | K63: Credit Card | L63: Delivered | M63: USPS
A64: ORD0063 | B64: 5/2/2023 | E64: CUST004 | F64: PROD005 | G64: East | H64: 27 | I64: 1 | J64: 27 | K64: Debit Card | L64: In Transit | M64: Amazon Logistics
A65: ORD0064 | B65: 12/25/2023 | C65: 12/29/2023 | E65: CUST048 | F65: PROD003 | G65: West | H65: 139 | I65: 5 | J65: 695 | K65: Apple Pay | L65: Delivered | M65: USPS
A66: ORD0065 | B66: 10/18/2023 | D66: 10/20/2023 | E66: CUST009 | F66: PROD008 | G66: South | H66: 69 | I66: 3 | J66: 207 | K66: PayPal | L66: Cancelled | M66: Amazon Logistics
A67: ORD0066 | B67: 5/20/2023 | D67: 5/21/2023 | E67: CUST009 | F67: PROD019 | G67: West | H67: 42 | I67: 1 | J67: 42 | K67: Apple Pay | L67: Cancelled | M67: DHL
A68: ORD0067 | B68: 7/28/2023 | C68: 7/30/2023 | E68: CUST050 | F68: PROD007 | G68: North | H68: 31 | I68: 4 | J68: 124 | K68: Credit Card | L68: Delivered | M68: UPS
A69: ORD0068 | B69: 12/18/2023 | E69: CUST045 | F69: PROD020 | G69: West | H69: 104 | I69: 3 | J69: 312 | K69: Credit Card | L69: In Transit | M69: UPS
A70: ORD0069 | B70: 7/2/2023 | D70: 7/7/2023 | E70: CUST044 | F70: PROD010 | G70: East | H70: 58 | I70: 2 | J70: 116 | K70: Apple Pay | L70: Cancelled | M70: USPS
A71: ORD0070 | B71: 10/9/2023 | D71: 10/10/2023 | E71: CUST009 | F71: PROD004 | G71: West | H71: 62 | I71: 2 | J71: 124 | K71: Debit Card | L71: Cancelled | M71: DHL
A72: ORD0071 | B72: 12/18/2023 | C72: 12/25/2023 | E72: CUST006 | F72: PROD019 | G72: East | H72: 43 | I72: 1 | J72: 43 | K72: Credit Card | L72: Delivered | M72: Amazon Logistics
A73: ORD0072 | B73: 3/7/2023 | E73: CUST022 | F73: PROD004 | G73: East | H73: 62 | I73: 4 | J73: 248 | K73: Debit Card | L73: In Transit | M73: Amazon Logistics
A74: ORD0073 | B74: 7/22/2023 | D74: 7/25/2023 | E74: CUST028 | F74: PROD006 | G74: North | H74: 95 | I74: 2 | J74: 190 | K74: PayPal | L74: Cancelled | M74: UPS
A75: ORD0074 | B75: 1/18/2023 | C75: 1/24/2023 | E75: CUST016 | F75: PROD021 | G75: Central | H75: 36 | I75: 4 | J75: 144 | K75: Apple Pay | L75: Delivered | M75: FedEx
A76: ORD0075 | B76: 5/24/2023 | E76: CUST042 | F76: PROD017 | G76: East | H76: 73 | I76: 5 | J76: 365 | K76: Apple Pay | L76: In Transit | M76: DHL
A77: ORD0076 | B77: 9/3/2023 | C77: 9/9/2023 | E77: CUST023 | F77: PROD019 | G77: North | H77: 43 | I77: 4 | J77: 172 | K77: Debit Card | L77: Delivered | M77: DHL
A78: ORD0077 | B78: 11/2/2023 | C78: 11/4/2023 | E78: CUST004 | F78: PROD016 | G78: West | H78: 214 | I78: 5 | J78: 1070 | K78: Debit Card | L78: Delivered | M78: UPS
A79: ORD0078 | B79: 12/3/2023 | D79: 12/6/2023 | E79: CUST048 | F79: PROD002 | G79: Central | H79: 42 | I79: 2 | J79: 84 | K79: Apple Pay | L79: Cancelled | M79: UPS
A80: ORD0079 | B80: 4/1/2023 | E80: CUST048 | F80: PROD012 | G80: North | H80: 46 | I80: 1 | J80: 46 | K80: Amazon Pay | L80: In Transit | M80: UPS
A81: ORD0080 | B81: 10/16/2023 | C81: 10/19/2023 | E81: CUST032 | F81: PROD018 | G81: East | H81: 95 | I81: 4 | J81: 380 | K81: Credit Card | L81: Delivered | M81: UPS
A82: ORD0081 | B82: 11/5/2023 | E82: CUST001 | F82: PROD011 | G82: West | H82: 174 | I82: 2 | J82: 348 | K82: PayPal | L82: In Transit | M82: UPS
A83: ORD0082 | B83: 6/15/2023 | D83: 6/18/2023 | E83: CUST046 | F83: PROD005 | G83: North | H83: 27 | I83: 5 | J83: 135 | K83: Credit Card | L83: Cancelled | M83: Amazon Logistics
A84: ORD0083 | B84: 10/28/2023 | C84: 10/30/2023 | E84: CUST021 | F84: PROD005 | G84: South | H84: 27 | I84: 4 | J84: 108 | K84: PayPal | L84: Delivered | M84: USPS
A85: ORD0084 | B85: 12/22/2023 | E85: CUST015 | F85: PROD022 | G85: South | H85: 65 | I85: 2 | J85: 130 | K85: PayPal | L85: In Transit | M85: DHL
A86: ORD0085 | B86: 3/7/2023 | E86: CUST045 | F86: PROD019 | G86: East | H86: 43 | I86: 5 | J86: 215 | K86: Debit Card | L86: In Transit | M86: DHL
A87: ORD0086 | B87: 11/10/2023 | E87: CUST007 | F87: PROD016 | G87: West | H87: 210 | I87: 1 | J87: 210 | K87: PayPal | L87: In Transit | M87: UPS
A88: ORD0087 | B88: 11/22/2023 | E88: CUST043 | F88: PROD021 | G88: South | H88: 37 | I88: 3 | J88: 111 | K88: Credit Card | L88: In Transit | M88: UPS
A89: ORD0088 | B89: 5/8/2023 | E89: CUST007 | F89: PROD001 | G89: South | H89: 788 | I89: 4 | J89: 3152 | K89: Debit Card | L89: In Transit | M89: Amazon Logistics
A90: ORD0089 | B90: 7/13/2023 | E90: CUST007 | F90: PROD016 | G90: West | H90: 217 | I90: 5 | J90: 1085 | K90: Debit Card | L90: In Transit | M90: FedEx
A91: ORD0090 | B91: 1/18/2023 | E91: CUST007 | F91: PROD003 | G91: West | H91: 138 | I91: 4 | J91: 552 | K91: Credit Card | L91: In Transit | M91: FedEx
A92: ORD0091 | B92: 6/23/2023 | C92: 6/29/2023 | E92: CUST031 | F92: PROD001 | G92: Central | H92: 803 | I92: 2 | J92: 1606 | K92: Apple Pay | L92: Delivered | M92: FedEx
A93: ORD0092 | B93: 2/21/2023 | D93: 2/25/2023 | E93: CUST013 | F93: PROD014 | G93: North | H93: 248 | I93: 5 | J93: 1240 | K93: PayPal | L93: Cancelled | M93: UPS
A94: ORD0093 | B94: 2/19/2023 | C94: 2/21/2023 | E94: CUST036 | F94: PROD016 | G94: East | H94: 210 | I94: 3 | J94: 630 | K94: Apple Pay | L94: Delivered | M94: DHL
A95: ORD0094 | B95: 12/5/2023 | D95: 12/12/2023 | E95: CUST013 | F95: PROD004 | G95: North | H95: 62 | I95: 2 | J95: 124 | K95: Credit Card | L95: Cancelled | M95: FedEx
A96: ORD0095 | B96: 6/7/2023 | D96: 6/12/2023 | E96: CUST043 | F96: PROD009 | G96: South | H96: 11 | I96: 5 | J96: 55 | K96: Debit Card | L96: Cancelled | M96: Amazon Logistics
A97: ORD0096 | B97: 7/9/2023 | C97: 7/12/2023 | E97: CUST017 | F97: PROD015 | G97: North | H97: 21 | I97: 2 | J97: 42 | K97: Amazon Pay | L97: Delivered | M97: UPS
A98: ORD0097 | B98: 12/23/2023 | C98: 12/26/2023 | E98: CUST023 | F98: PROD018 | G98: West | H98: 95 | I98: 5 | J98: 475 | K98: Amazon Pay | L98: Delivered | M98: Amazon Logistics
A99: ORD0098 | B99: 9/25/2023 | C99: 9/30/2023 | E99: CUST044 | F99: PROD016 | G99: South | H99: 215 | I99: 2 | J99: 430 | K99: PayPal | L99: Delivered | M99: Amazon Logistics
A100: ORD0099 | B100: 1/18/2023 | D100: 1/24/2023 | E100: CUST034 | F100: PROD019 | G100: West | H100: 43 | I100: 5 | J100: 215 | K100: Credit Card | L100: Cancelled | M100: UPS
...

Sheet ProductMaster
A1: Product ID | B1: Product Name | C1: Category | D1: Cost Price | E1: Description
A2: PROD001 | B2: Smartphone | C2: Electronics | D2: 749 | E2: Latest model with 5G, dual SIM, and OLED display
A3: PROD002 | B3: Action Figure | C3: Toys | D3: 39 | E3: Collectible superhero action figure for ages 8+
A4: PROD003 | B4: Cookware Set | C4: Home | D4: 129 | E4: Non-stick 5-piece cookware set for daily use
A5: PROD004 | B5: Leg Set | C5: Toys | D5: 59 | E5: 300-piece creative building block toy set
A6: PROD005 | B6: T-Shirt | C6: Fashion | D6: 25 | E6: Cotton t-shirt, available in multiple colors
A7: PROD006 | B7: Shoes | C7: Fashion | D7: 89 | E7: Casual wear shoes for men and women
A8: PROD007 | B8: Puzzle | C8: Toys | D8: 29 | E8: 1000-piece jigsaw puzzle
A9: PROD008 | B9: Textbook | C9: Books | D9: 65 | E9: University-level textbook on computer science
A10: PROD009 | B10: Magazine | C10: Books | D10: 10 | E10: Monthly lifestyle magazine
A11: PROD010 | B11: Jeans | C11: Fashion | D11: 55 | E11: Slim fit denim jeans with stretch
A12: PROD011 | B12: Headphones | C12: Electronics | D12: 159 | E12: Wireless noise-cancelling over-ear headphones
A13: PROD012 | B13: Lamp | C13: Home | D13: 42 | E13: LED desk lamp with dimmable light
... A23: PROD022 | B23: Backpack | C23: Fashion | D23: 60 | E23: Waterproof backpack with laptop compartment
A24: Total | B24: =SUBTOTAL(103,Product_table[Product Name]) -> 22 | E24: =SUBTOTAL(103,Product_table[Description]) -> 22

Sheet RegionGoals
A1: Region | B1: Sales Target
A2: Central | B2: 97500
A3: East | B3: 50500
A4: North | B4: 105000
A5: South | B5: 91500
A6: West | B6: 90750

Sheet CustomerMaster
A1: Customer ID | B1: Customer Name | C1: Customer Type | D1: City | E1: State
A2: CUST001 | B2: James Miller | C2: Business | D2: New York | E2: New York
A3: CUST002 | B3: Emily Johnson | C3: Prime | D3: Seattle | E3: Washington
A4: CUST003 | B4: Ethan Davis | C4: Prime | D4: Austin | E4: Texas
A5: CUST004 | B5: Noah Wilson | C5: Prime | D5: San Francisco | E5: California
A6: CUST005 | B6: Olivia Martinez | C6: Prime | D6: Seattle | E6: Washington
A7: CUST006 | B7: Ava Robinson | C7: Prime | D7: Chicago | E7: Illinois
A8: CUST007 | B8: Liam Walker | C8: Prime | D8: San Francisco | E8: California
A9: CUST008 | B9: Harper Young | C9: Business | D9: Dallas | E9: Texas
A10: CUST009 | B10: Jackson Allen | C10: Business | D10: Seattle | E10: Washington
A11: CUST010 | B11: Charlotte Harris | C11: Prime | D11: Chicago | E11: Illinois
A12: CUST011 | B12: Mason Hall | C12: Business | D12: Miami | E12: Florida
... A50: CUST049 | B50: Hazel Gray | C50: Business | D50: Chicago | E50: Illinois

Sheet Task1
A1: Order count | B1: Order ID | C1: Order Date | D1: Delivery Date | E1: Cancel Date | F1: Customer ID | G1: Product ID | H1: Product Category | I1: Product Name | J1: Region | K1: Sale Price/Unit | L1: Quantity | M1: Total Amount | N1: Payment Method | O1: Delivery Status | P1: Fulfillment Partner | Q1: Order Status | R1: Delivery Time | S1: Cancelled | T1: Delivered | U1: Delivered sales Amount | V1: Delivery performance | W1: Fast delivery
A2: 1 | B2: ORD0001 | C2: 45291 | E2: 45323 | F2: CUST021 | G2: PROD012 | H2: =_xlfn.XLOOKUP(AmazonSales[[#This Row],[Product ID]],Product_table[Product ID],Product_table[Category]) -> Home | I2: =_xlfn.XLOOKUP(AmazonSales[[#This Row],[Product ID]],Product_table[Product ID],Product_table[Product Name]) -> Lamp | J2: North | K2: 44 | L2: 1 | M2: 44 | N2: Apple Pay | O2: Cancelled | P2: DHL | Q2: =IF(AND(E2<>"", O2="Cancelled"), "Cancelled", "Active") -> Cancelled | S2: =IF(AmazonSales[[#This Row],[Order Status]]="Cancelled",1,0) -> 1 | T2: =IF(AmazonSales[[#This Row],[Delivery Status]]="Delivered",1,0) -> 0 | U2: =IF(AmazonSales[[#This Row],[Delivery Status]]="Delivered",AmazonSales[[#This Row],[Total Amount]],0) -> 0 | V2: {=_xlfn.IFS(AND(AmazonSales[[#This Row],[Delivery Time]]=""),"",AND(AmazonSales[[#This Row],[Delivery Time]]<=2),"Fast",AND(AmazonSales[[#This Row],[Delivery Time]]>2),"Slow")} | W2: =IF(AmazonSales[[#This Row],[Delivery performance]]="Fast",1,0) -> 0
A3: 1 | B3: ORD0002 | C3: 44979 | D3: 44981 | F3: CUST029 | G3: PROD018 | H3: =_xlfn.XLOOKUP(AmazonSales[[#This Row],[Product ID]],Product_table[Product ID],Product_table[Category]) -> Toys | I3: =_xlfn.XLOOKUP(AmazonSales[[#This Row],[Product ID]],Product_table[Product ID],Product_table[Product Name]) -> Doll House | J3: East | K3: 96 | L3: 4 | M3: 384 | N3: Credit Card | O3: Delivered | P3: DHL | Q3: =IF(AND(E3<>"", O3="Cancelled"), "Cancelled", "Active") -> Active | R3: =DATEDIF(AmazonSales[[#This Row],[Order Date]],AmazonSales[[#This Row],[Delivery Date]],"d") -> 2 | S3: =IF(AmazonSales[[#This Row],[Order Status]]="Cancelled",1,0) -> 0 | T3: =IF(AmazonSales[[#This Row],[Delivery Status]]="Delivered",1,0) -> 1 | U3: =IF(AmazonSales[[#This Row],[Delivery Status]]="Delivered",AmazonSales[[#This Row],[Total Amount]],0) -> 384 | V3: {=_xlfn.IFS(AND(AmazonSales[[#This Row],[Delivery Time]]=""),"",AND(AmazonSales[[#This Row],[Delivery Time]]<=2),"Fast",AND(AmazonSales[[#This Row],[Delivery Time]]>2),"Slow")} -> Fast | W3: =IF(AmazonSales[[#This Row],[Delivery performance]]="Fast",1,0) -> 1
A4: 1 | B4: ORD0003 | C4: 45240 | F4: CUST021 | G4: PROD013 | H4: =_xlfn.XLOOKUP(AmazonSales[[#This Row],[Product ID]],Product_table[Product ID],Product_table[Category]) -> Home | I4: =_xlfn.XLOOKUP(AmazonSales[[#This Row],[Product ID]],Product_table[Product ID],Product_table[Product Name]) -> Vacuum Cleaner | J4: South | K4: 194 | L4: 4 | M4: 776 | N4: Credit Card | O4: In Transit | P4: USPS | Q4: =IF(AND(E4<>"", O4="Cancelled"), "Cancelled", "Active") -> Active | S4: =IF(AmazonSales[[#This Row],[Order Status]]="Cancelled",1,0) -> 0 | T4: =IF(AmazonSales[[#This Row],[Delivery Status]]="Delivered",1,0) -> 0 | U4: =IF(AmazonSales[[#This Row],[Delivery Status]]="Delivered",AmazonSales[[#This Row],[Total Amount]],0) -> 0 | V4: {=_xlfn.IFS(AND(AmazonSales[[#This Row],[Delivery Time]]=""),"",AND(AmazonSales[[#This Row],[Delivery Time]]<=2),"Fast",AND(AmazonSales[[#This Row],[Delivery Time]]>2),"Slow")} | W4: =IF(AmazonSales[[#This Row],[Delivery performance]]="Fast",1,0) -> 0
A5: 1 | B5: ORD0004 | C5: 45051 | E5: 45235 | F5: CUST044 | G5: PROD013 | H5: =_xlfn.XLOOKUP(AmazonSales[[#This Row],[Product ID]],Product_table[Product ID],Product_table[Category]) -> Home | I5: =_xlfn.XLOOKUP(AmazonSales[[#This Row],[Product ID]],Product_table[Product ID],Product_table[Product Name]) -> Vacuum Cleaner | J5: North | K5: 196 | L5: 3 | M5: 588 | N5: PayPal | O5: Cancelled | P5: UPS | Q5: =IF(AND(E5<>"", O5="Cancelled"), "Cancelled", "Active") -> Cancelled | S5: =IF(AmazonSales[[#This Row],[Order Status]]="Cancelled",1,0) -> 1 | T5: =IF(AmazonSales[[#This Row],[Delivery Status]]="Delivered",1,0) -> 0 | U5: =IF(AmazonSales[[#This Row],[Delivery Status]]="Delivered",AmazonSales[[#This Row],[Total Amount]],0) -> 0 | V5: {=_xlfn.IFS(AND(AmazonSales[[#This Row],[Delivery Time]]=""),"",AND(AmazonSales[[#This Row],[Delivery Time]]<=2),"Fast",AND(AmazonSales[[#This Row],[Delivery Time]]>2),"Slow")} | W5: =IF(AmazonSales[[#This Row],[Delivery performance]]="Fast",1,0) -> 0
A6: 1 | B6: ORD0005 | C6: 44959 | D6: 44962 | F6: CUST027 | G6: PROD010 | H6: =_xlfn.XLOOKUP(AmazonSales[[#This Row],[Product ID]],Product_table[Product ID],Product_table[Category]) -> Fashion | I6: =_xlfn.XLOOKUP(AmazonSales[[#This Row],[Product ID]],Product_table[Product ID],Product_table[Product Name]) -> Jeans | J6: North | K6: 59 | L6: 1 | M6: 59 | N6: PayPal | O6: Delivered | P6: Amazon Logistics | Q6: =IF(AND(E6<>"", O6="Cancelled"), "Cancelled", "Active") -> Active | R6: =DATEDIF(AmazonSales[[#This Row],[Order Date]],AmazonSales[[#This Row],[Delivery Date]],"d") -> 3 | S6: =IF(AmazonSales[[#This Row],[Order Status]]="Cancelled",1,0) -> 0 | T6: =IF(AmazonSales[[#This Row],[Delivery Status]]="Delivered",1,0) -> 1 | U6: =IF(AmazonSales[[#This Row],[Delivery Status]]="Delivered",AmazonSales[[#This Row],[Total Amount]],0) -> 59 | V6: {=_xlfn.IFS(AND(AmazonSales[[#This Row],[Delivery Time]]=""),"",AND(AmazonSales[[#This Row],[Delivery Time]]<=2),"Fast",AND(AmazonSales[[#This Row],[Delivery Time]]>2),"Slow")} -> Slow | W6: =IF(AmazonSales[[#This Row],[Delivery performance]]="Fast",1,0) -> 0
A7: 1 | B7: ORD0006 | C7: 44937 | E7: 44968 | F7: CUST009 | G7: PROD010 | H7: =_xlfn.XLOOKUP(AmazonSales[[#This Row],[Product ID]],Product_table[Product ID],Product_table[Category]) -> Fashion | I7: =_xlfn.XLOOKUP(AmazonSales[[#This Row],[Product ID]],Product_table[Product ID],Product_table[Product Name]) -> Jeans | J7: North | K7: 58 | L7: 4 | M7: 232 | N7: Amazon Pay | O7: Cancelled | P7: DHL | Q7: =IF(AND(E7<>"", O7="Cancelled"), "Cancelled", "Active") -> Cancelled | S7: =IF(AmazonSales[[#This Row],[Order Status]]="Cancelled",1,0) -> 1 | T7: =IF(AmazonSales[[#This Row],[Delivery Status]]="Delivered",1,0) -> 0 | U7: =IF(AmazonSales[[#This Row],[Delivery Status]]="Delivered",AmazonSales[[#This Row],[Total Amount]],0) -> 0 | V7: {=_xlfn.IFS(AND(AmazonSales[[#This Row],[Delivery Time]]=""),"",AND(AmazonSales[[#This Row],[Delivery Time]]<=2),"Fast",AND(AmazonSales[[#This Row],[Delivery Time]]>2),"Slow")} | W7: =IF(AmazonSales[[#This Row],[Delivery performance]]="Fast",1,0) -> 0
A8: 1 | B8: ORD0007 | C8: 45152 | E8: 45156 | F8: CUST042 | G8: PROD020 | H8: =_xlfn.XLOOKUP(AmazonSales[[#This Row],[Product ID]],Product_table[Product ID],Product_table[Category]) -> Electronics | I8: =_xlfn.XLOOKUP(AmazonSales[[#This Row],[Product ID]],Product_table[Product ID],Product_table[Product Name]) -> Bluetooth Speaker | J8: Central | K8: 105 | L8: 3 | M8: 315 | N8: Debit Card | O8: Cancelled | P8: DHL | Q8: =IF(AND(E8<>"", O8="Cancelled"), "Cancelled", "Active") -> Cancelled | S8: =IF(AmazonSales[[#This Row],[Order Status]]="Cancelled",1,0) -> 1 | T8: =IF(AmazonSales[[#This Row],[Delivery Status]]="Delivered",1,0) -> 0 | U8: =IF(AmazonSales[[#This Row],[Delivery Status]]="Delivered",AmazonSales[[#This Row],[Total Amount]],0) -> 0 | V8: {=_xlfn.IFS(AND(AmazonSales[[#This Row],[Delivery Time]]=""),"",AND(AmazonSales[[#This Row],[Delivery Time]]<=2),"Fast",AND(AmazonSales[[#This Row],[Delivery Time]]>2),"Slow")} | W8: =IF(AmazonSales[[#This Row],[Delivery performance]]="Fast",1,0) -> 0
A9: 1 | B9: ORD0008 | C9: 44930 | E9: 45081 | F9: CUST019 | G9: PROD021 | H9: =_xlfn.XLOOKUP(AmazonSales[[#This Row],[Product ID]],Product_table[Product ID],Product_table[Category]) -> Home | I9: =_xlfn.XLOOKUP(AmazonSales[[#This Row],[Product ID]],Product_table[Product ID],Product_table[Product Name]) -> Wall Clock | J9: West | K9: 37 | L9: 5 | M9: 185 | N9: PayPal | O9: Cancelled | P9: DHL | Q9: =IF(AND(E9<>"", O9="Cancelled"), "Cancelled", "Active") -> Cancelled | S9: =IF(AmazonSales[[#This Row],[Order Status]]="Cancelled",1,0) -> 1 | T9: =IF(AmazonSales[[#This Row],[Delivery Status]]="Delivered",1,0) -> 0 | U9: =IF(AmazonSales[[#This Row],[Delivery Status]]="Delivered",AmazonSales[[#This Row],[Total Amount]],0) -> 0 | V9: {=_xlfn.IFS(AND(AmazonSales[[#This Row],[Delivery Time]]=""),"",AND(AmazonSales[[#This Row],[Delivery Time]]<=2),"Fast",AND(AmazonSales[[#This Row],[Delivery Time]]>2),"Slow")} | W9: =IF(AmazonSales[[#This Row],[Delivery performance]]="Fast",1,0) -> 0
A10: 1 | B10: ORD0009 | C10: 45128 | F10: CUST013 | G10: PROD019 | H10: =_xlfn.XLOOKUP(AmazonSales[[#This Row],[Product ID]],Product_table[Product ID],Product_table[Category]) -> Fashion | I10: =_xlfn.XLOOKUP(AmazonSales[[#This Row],[Product ID]],Product_table[Product ID],Product_table[Product Name]) -> Formal Shirt | J10: Central | K10: 44 | L10: 2 | M10: 88 | N10: Credit Card | O10: In Transit | P10: Amazon Logistics | Q10: =IF(AND(E10<>"", O10="Cancelled"), "Cancelled", "Active") -> Active | S10: =IF(AmazonSales[[#This Row],[Order Status]]="Cancelled",1,0) -> 0 | T10: =IF(AmazonSales[[#This Row],[Delivery Status]]="Delivered",1,0) -> 0 | U10: =IF(AmazonSales[[#This Row],[Delivery Status]]="Delivered",AmazonSales[[#This Row],[Total Amount]],0) -> 0 | V10: {=_xlfn.IFS(AND(AmazonSales[[#This Row],[Delivery Time]]=""),"",AND(AmazonSales[[#This Row],[Delivery Time]]<=2),"Fast",AND(AmazonSales[[#This Row],[Delivery Time]]>2),"Slow")} | W10: =IF(AmazonSales[[#This Row],[Delivery performance]]="Fast",1,0) -> 0
A11: 1 | B11: ORD0010 | C11: 45289 | F11: CUST019 | G11: PROD003 | H11: =_xlfn.XLOOKUP(AmazonSales[[#This Row],[Product ID]],Product_table[Product ID],Product_table[Category]) -> Home | I11: =_xlfn.XLOOKUP(AmazonSales[[#This Row],[Product ID]],Product_table[Product ID],Product_table[Product Name]) -> Cookware Set | J11: South | K11: 141 | L11: 4 | M11: 564 | N11: Debit Card | O11: In Transit | P11: DHL | Q11: =IF(AND(E11<>"", O11="Cancelled"), "Cancelled", "Active") -> Active | S11: =IF(AmazonSales[[#This Row],[Order Status]]="Cancelled",1,0) -> 0 | T11: =IF(AmazonSales[[#This Row],[Delivery Status]]="Delivered",1,0) -> 0 | U11: =IF(AmazonSales[[#This Row],[Delivery Status]]="Delivered",AmazonSales[[#This Row],[Total Amount]],0) -> 0 | V11: {=_xlfn.IFS(AND(AmazonSales[[#This Row],[Delivery Time]]=""),"",AND(AmazonSales[[#This Row],[Delivery Time]]<=2),"Fast",AND(AmazonSales[[#This Row],[Delivery Time]]>2),"Slow")} | W11: =IF(AmazonSales[[#This Row],[Delivery performance]]="Fast",1,0) -> 0
A12: 1 | B12: ORD0011 | C12: 45021 | E12: 45143 | F12: CUST046 | G12: PROD014 | H12: =_xlfn.XLOOKUP(AmazonSales[[#This Row],[Product ID]],Product_table[Product ID],Product_table[Category]) -> Electronics | I12: =_xlfn.XLOOKUP(AmazonSales[[#This Row],[Product ID]],Product_table[Product ID],Product_table[Product Name]) -> Smartwatch | J12: South | K12: 249 | L12: 1 | M12: 249 | N12: Amazon Pay | O12: Cancelled | P12: USPS | Q12: =IF(AND(E12<>"", O12="Cancelled"), "Cancelled", "Active") -> Cancelled | S12: =IF(AmazonSales[[#This Row],[Order Status]]="Cancelled",1,0) -> 1 | T12: =IF(AmazonSales[[#This Row],[Delivery Status]]="Delivered",1,0) -> 0 | U12: =IF(AmazonSales[[#This Row],[Delivery Status]]="Delivered",AmazonSales[[#This Row],[Total Amount]],0) -> 0 | V12: {=_xlfn.IFS(AND(AmazonSales[[#This Row],[Delivery Time]]=""),"",AND(AmazonSales[[#This Row],[Delivery Time]]<=2),"Fast",AND(AmazonSales[[#This Row],[Delivery Time]]>2),"Slow")} | W12: =IF(AmazonSales[[#This Row],[Delivery performance]]="Fast",1,0) -> 0
A13: 1 | B13: ORD0012 | C13: 45132 | F13: CUST045 | G13: PROD014 | H13: =_xlfn.XLOOKUP(AmazonSales[[#This Row],[Product ID]],Product_table[Product ID],Product_table[Category]) -> Electronics | I13: =_xlfn.XLOOKUP(AmazonSales[[#This Row],[Product ID]],Product_table[Product ID],Product_table[Product Name]) -> Smartwatch | J13: Central | K13: 247 | L13: 3 | M13: 741 | N13: Amazon Pay | O13: In Transit | P13: FedEx | Q13: =IF(AND(E13<>"", O13="Cancelled"), "Cancelled", "Active") -> Active | S13: =IF(AmazonSales[[#This Row],[Order Status]]="Cancelled",1,0) -> 0 | T13: =IF(AmazonSales[[#This Row],[Delivery Status]]="Delivered",1,0) -> 0 | U13: =IF(AmazonSales[[#This Row],[Delivery Status]]="Delivered",AmazonSales[[#This Row],[Total Amount]],0) -> 0 | V13: {=_xlfn.IFS(AND(AmazonSales[[#This Row],[Delivery Time]]=""),"",AND(AmazonSales[[#This Row],[Delivery Time]]<=2),"Fast",AND(AmazonSales[[#This Row],[Delivery Time]]>2),"Slow")} | W13: =IF(AmazonSales[[#This Row],[Delivery performance]]="Fast",1,0) -> 0
A14: 1 | B14: ORD0013 | C14: 44982 | E14: 44985 | F14: CUST023 | G14: PROD006 | H14: =_xlfn.XLOOKUP(AmazonSales[[#This Row],[Product ID]],Product_table[Product ID],Product_table[Category]) -> Fashion | I14: =_xlfn.XLOOKUP(AmazonSales[[#This Row],[Product ID]],Product_table[Product ID],Product_table[Product Name]) -> Shoes | J14: Central | K14: 96 | L14: 1 | M14: 96 | N14: Apple Pay | O14: Cancelled | P14: Amazon Logistics | Q14: =IF(AND(E14<>"", O14="Cancelled"), "Cancelled", "Active") -> Cancelled | S14: =IF(AmazonSales[[#This Row],[Order Status]]="Cancelled",1,0) -> 1 | T14: =IF(AmazonSales[[#This Row],[Delivery Status]]="Delivered",1,0) -> 0 | U14: =IF(AmazonSales[[#This Row],[Delivery Status]]="Delivered",AmazonSales[[#This Row],[Total Amount]],0) -> 0 | V14: {=_xlfn.IFS(AND(AmazonSales[[#This Row],[Delivery Time]]=""),"",AND(AmazonSales[[#This Row],[Delivery Time]]<=2),"Fast",AND(AmazonSales[[#This Row],[Delivery Time]]>2),"Slow")} | W14: =IF(AmazonSales[[#This Row],[Delivery performance]]="Fast",1,0) -> 0
A15: 1 | B15: ORD0014 | C15: 44981 | E15: 44982 | F15: CUST033 | G15: PROD017 | H15: =_xlfn.XLOOKUP(AmazonSales[[#This Row],[Product ID]],Product_table[Product ID],Product_table[Category]) -> Electronics | I15: =_xlfn.XLOOKUP(AmazonSales[[#This Row],[Product ID]],Product_table[Product ID],Product_table[Product Name]) -> Gaming Mouse | J15: West | K15: 74 | L15: 5 | M15: 370 | N15: Apple Pay | O15: Cancelled | P15: Amazon Logistics | Q15: =IF(AND(E15<>"", O15="Cancelled"), "Cancelled", "Active") -> Cancelled | S15: =IF(AmazonSales[[#This Row],[Order Status]]="Cancelled",1,0) -> 1 | T15: =IF(AmazonSales[[#This Row],[Delivery Status]]="Delivered",1,0) -> 0 | U15: =IF(AmazonSales[[#This Row],[Delivery Status]]="Delivered",AmazonSales[[#This Row],[Total Amount]],0) -> 0 | V15: {=_xlfn.IFS(AND(AmazonSales[[#This Row],[Delivery Time]]=""),"",AND(AmazonSales[[#This Row],[Delivery Time]]<=2),"Fast",AND(AmazonSales[[#This Row],[Delivery Time]]>2),"Slow")} | W15: =IF(AmazonSales[[#This Row],[Delivery performance]]="Fast",1,0) -> 0
A16: 1 | B16: ORD0015 | C16: 45164 | E16: 45171 | F16: CUST033 | G16: PROD005 | H16: =_xlfn.XLOOKUP(AmazonSales[[#This Row],[Product ID]],Product_table[Product ID],Product_table[Category]) -> Fashion | I16: =_xlfn.XLOOKUP(AmazonSales[[#This Row],[Product ID]],Product_table[Product ID],Product_table[Product Name]) -> T-Shirt | J16: South | K16: 27 | L16: 1 | M16: 27 | N16: Credit Card | O16: Cancelled | P16: Amazon Logistics | Q16: =IF(AND(E16<>"", O16="Cancelled"), "Cancelled", "Active") -> Cancelled | S16: =IF(AmazonSales[[#This Row],[Order Status]]="Cancelled",1,0) -> 1 | T16: =IF(AmazonSales[[#This Row],[Delivery Status]]="Delivered",1,0) -> 0 | U16: =IF(AmazonSales[[#This Row],[Delivery Status]]="Delivered",AmazonSales[[#This Row],[Total Amount]],0) -> 0 | V16: {=_xlfn.IFS(AND(AmazonSales[[#This Row],[Delivery Time]]=""),"",AND(AmazonSales[[#This Row],[Delivery Time]]<=2),"Fast",AND(AmazonSales[[#This Row],[Delivery Time]]>2),"Slow")} | W16: =IF(AmazonSales[[#This Row],[Delivery performance]]="Fast",1,0) -> 0
A17: 1 | B17: ORD0016 | C17: 44970 | F17: CUST047 | G17: PROD005 | H17: =_xlfn.XLOOKUP(AmazonSales[[#This Row],[Product ID]],Product_table[Product ID],Product_table[Category]) -> Fashion | I17: =_xlfn.XLOOKUP(AmazonSales[[#This Row],[Product ID]],Product_table[Product ID],Product_table[Product Name]) -> T-Shirt | J17: South | K17: 27 | L17: 3 | M17: 81 | N17: Debit Card | O17: In Transit | P17: Amazon Logistics | Q17: =IF(AND(E17<>"", O17="Cancelled"), "Cancelled", "Active") -> Active | S17: =IF(AmazonSales[[#This Row],[Order Status]]="Cancelled",1,0) -> 0 | T17: =IF(AmazonSales[[#This Row],[Delivery Status]]="Delivered",1,0) -> 0 | U17: =IF(AmazonSales[[#This Row],[Delivery Status]]="Delivered",AmazonSales[[#This Row],[Total Amount]],0) -> 0 | V17: {=_xlfn.IFS(AND(AmazonSales[[#This Row],[Delivery Time]]=""),"",AND(AmazonSales[[#This Row],[Delivery Time]]<=2),"Fast",AND(AmazonSales[[#This Row],[Delivery Time]]>2),"Slow")} | W17: =IF(AmazonSales[[#This Row],[Delivery performance]]="Fast",1,0) -> 0
A18: 1 | B18: ORD0017 | C18: 45105 | D18: 45108 | F18: CUST045 | G18: PROD015 | H18: =_xlfn.XLOOKUP(AmazonSales[[#This Row],[Product ID]],Product_table[Product ID],Product_table[Category]) -> Books | I18: =_xlfn.XLOOKUP(AmazonSales[[#This Row],[Product ID]],Product_table[Product ID],Product_table[Product Name]) -> Novel | J18: East | K18: 21 | L18: 3 | M18: 63 | N18: Credit Card | O18: Delivered | P18: DHL | Q18: =IF(AND(E18<>"", O18="Cancelled"), "Cancelled", "Active") -> Active | R18: =DATEDIF(AmazonSales[[#This Row],[Order Date]],AmazonSales[[#This Row],[Delivery Date]],"d") -> 3 | S18: =IF(AmazonSales[[#This Row],[Order Status]]="Cancelled",1,0) -> 0 | T18: =IF(AmazonSales[[#This Row],[Delivery Status]]="Delivered",1,0) -> 1 | U18: =IF(AmazonSales[[#This Row],[Delivery Status]]="Delivered",AmazonSales[[#This Row],[Total Amount]],0) -> 63 | V18: {=_xlfn.IFS(AND(AmazonSales[[#This Row],[Delivery Time]]=""),"",AND(AmazonSales[[#This Row],[Delivery Time]]<=2),"Fast",AND(AmazonSales[[#This Row],[Delivery Time]]>2),"Slow")} -> Slow | W18: =IF(AmazonSales[[#This Row],[Delivery performance]]="Fast",1,0) -> 0
A19: 1 | B19: ORD0018 | C19: 45258 | F19: CUST011 | G19: PROD008 | H19: =_xlfn.XLOOKUP(AmazonSales[[#This Row],[Product ID]],Product_table[Product ID],Product_table[Category]) -> Books | I19: =_xlfn.XLOOKUP(AmazonSales[[#This Row],[Product ID]],Product_table[Product ID],Product_table[Product Name]) -> Textbook | J19: West | K19: 70 | L19: 5 | M19: 350 | N19: PayPal | O19: In Transit | P19: Amazon Logistics | Q19: =IF(AND(E19<>"", O19="Cancelled"), "Cancelled", "Active") -> Active | S19: =IF(AmazonSales[[#This Row],[Order Status]]="Cancelled",1,0) -> 0 | T19: =IF(AmazonSales[[#This Row],[Delivery Status]]="Delivered",1,0) -> 0 | U19: =IF(AmazonSales[[#This Row],[Delivery Status]]="Delivered",AmazonSales[[#This Row],[Total Amount]],0) -> 0 | V19: {=_xlfn.IFS(AND(AmazonSales[[#This Row],[Delivery Time]]=""),"",AND(AmazonSales[[#This Row],[Delivery Time]]<=2),"Fast",AND(AmazonSales[[#This Row],[Delivery Time]]>2),"Slow")} | W19: =IF(AmazonSales[[#This Row],[Delivery performance]]="Fast",1,0) -> 0
A20: 1 | B20: ORD0019 | C20: 45163 | F20: CUST041 | G20: PROD006 | H20: =_xlfn.XLOOKUP(AmazonSales[[#This Row],[Product ID]],Product_table[Product ID],Product_table[Category]) -> Fashion | I20: =_xlfn.XLOOKUP(AmazonSales[[#This Row],[Product ID]],Product_table[Product ID],Product_table[Product Name]) -> Shoes | J20: South | K20: 94 | L20: 4 | M20: 376 | N20: Credit Card | O20: In Transit | P20: USPS | Q20: =IF(AND(E20<>"", O20="Cancelled"), "Cancelled", "Active") -> Active | S20: =IF(AmazonSales[[#This Row],[Order Status]]="Cancelled",1,0) -> 0 | T20: =IF(AmazonSales[[#This Row],[Delivery Status]]="Delivered",1,0) -> 0 | U20: =IF(AmazonSales[[#This Row],[Delivery Status]]="Delivered",AmazonSales[[#This Row],[Total Amount]],0) -> 0 | V20: {=_xlfn.IFS(AND(AmazonSales[[#This Row],[Delivery Time]]=""),"",AND(AmazonSales[[#This Row],[Delivery Time]]<=2),"Fast",AND(AmazonSales[[#This Row],[Delivery Time]]>2),"Slow")} | W20: =IF(AmazonSales[[#This Row],[Delivery performance]]="Fast",1,0) -> 0
A21: 1 | B21: ORD0020 | C21: 45264 | F21: CUST025 | G21: PROD001 | H21: =_xlfn.XLOOKUP(AmazonSales[[#This Row],[Product ID]],Product_table[Product ID],Product_table[Category]) -> Electronics | I21: =_xlfn.XLOOKUP(AmazonSales[[#This Row],[Product ID]],Product_table[Product ID],Product_table[Product Name]) -> Smartphone | J21: North | K21: 813 | L21: 2 | M21: 1626 | N21: Credit Card | O21: In Transit | P21: FedEx | Q21: =IF(AND(E21<>"", O21="Cancelled"), "Cancelled", "Active") -> Active | S21: =IF(AmazonSales[[#This Row],[Order Status]]="Cancelled",1,0) -> 0 | T21: =IF(AmazonSales[[#This Row],[Delivery Status]]="Delivered",1,0) -> 0 | U21: =IF(AmazonSales[[#This Row],[Delivery Status]]="Delivered",AmazonSales[[#This Row],[Total Amount]],0) -> 0 | V21: {=_xlfn.IFS(AND(AmazonSales[[#This Row],[Delivery Time]]=""),"",AND(AmazonSales[[#This Row],[Delivery Time]]<=2),"Fast",AND(AmazonSales[[#This Row],[Delivery Time]]>2),"Slow")} | W21: =IF(AmazonSales[[#This Row],[Delivery performance]]="Fast",1,0) -> 0
A22: 1 | B22: ORD0021 | C22: 44967 | F22: CUST013 | G22: PROD015 | H22: =_xlfn.XLOOKUP(AmazonSales[[#This Row],[Product ID]],Product_table[Product ID],Product_table[Category]) -> Books | I22: =_xlfn.XLOOKUP(AmazonSales[[#This Row],[Product ID]],Product_table[Product ID],Product_table[Product Name]) -> Novel | J22: Central | K22: 21 | L22: 4 | M22: 84 | N22: PayPal | O22: In Transit | P22: Amazon Logistics | Q22: =IF(AND(E22<>"", O22="Cancelled"), "Cancelled", "Active") -> Active | S22: =IF(AmazonSales[[#This Row],[Order Status]]="Cancelled",1,0) -> 0 | T22: =IF(AmazonSales[[#This Row],[Delivery Status]]="Delivered",1,0) -> 0 | U22: =IF(AmazonSales[[#This Row],[Delivery Status]]="Delivered",AmazonSales[[#This Row],[Total Amount]],0) -> 0 | V22: {=_xlfn.IFS(AND(AmazonSales[[#This Row],[Delivery Time]]=""),"",AND(AmazonSales[[#This Row],[Delivery Time]]<=2),"Fast",AND(AmazonSales[[#This Row],[Delivery Time]]>2),"Slow")} | W22: =IF(AmazonSales[[#This Row],[Delivery performance]]="Fast",1,0) -> 0
A23: 1 | B23: ORD0022 | C23: 45180 | F23: CUST023 | G23: PROD012 | H23: =_xlfn.XLOOKUP(AmazonSales[[#This Row],[Product ID]],Product_table[Product ID],Product_table[Category]) -> Home | I23: =_xlfn.XLOOKUP(AmazonSales[[#This Row],[Product ID]],Product_table[Product ID],Product_table[Product Name]) -> Lamp | J23: West | K23: 46 | L23: 5 | M23: 230 | N23: PayPal | O23: In Transit | P23: USPS | Q23: =IF(AND(E23<>"", O23="Cancelled"), "Cancelled", "Active") -> Active | S23: =IF(AmazonSales[[#This Row],[Order Status]]="Cancelled",1,0) -> 0 | T23: =IF(AmazonSales[[#This Row],[Delivery Status]]="Delivered",1,0) -> 0 | U23: =IF(AmazonSales[[#This Row],[Delivery Status]]="Delivered",AmazonSales[[#This Row],[Total Amount]],0) -> 0 | V23: {=_xlfn.IFS(AND(AmazonSales[[#This Row],[Delivery Time]]=""),"",AND(AmazonSales[[#This Row],[Delivery Time]]<=2),"Fast",AND(AmazonSales[[#This Row],[Delivery Time]]>2),"Slow")} | W23: =IF(AmazonSales[[#This Row],[Delivery performance]]="Fast",1,0) -> 0
A24: 1 | B24: ORD0023 | C24: 44970 | E24: 44971 | F24: CUST016 | G24: PROD010 | H24: =_xlfn.XLOOKUP(AmazonSales[[#This Row],[Product ID]],Product_table[Product ID],Product_table[Category]) -> Fashion | I24: =_xlfn.XLOOKUP(AmazonSales[[#This Row],[Product ID]],Product_table[Product ID],Product_table[Product Name]) -> Jeans | J24: West | K24: 58 | L24: 3 | M24: 174 | N24: Amazon Pay | O24: Cancelled | P24: Amazon Logistics | Q24: =IF(AND(E24<>"", O24="Cancelled"), "Cancelled", "Active") -> Cancelled | S24: =IF(AmazonSales[[#This Row],[Order Status]]="Cancelled",1,0) -> 1 | T24: =IF(AmazonSales[[#This Row],[Delivery Status]]="Delivered",1,0) -> 0 | U24: =IF(AmazonSales[[#This Row],[Delivery Status]]="Delivered",AmazonSales[[#This Row],[Total Amount]],0) -> 0 | V24: {=_xlfn.IFS(AND(AmazonSales[[#This Row],[Delivery Time]]=""),"",AND(AmazonSales[[#This Row],[Delivery Time]]<=2),"Fast",AND(AmazonSales[[#This Row],[Delivery Time]]>2),"Slow")} | W24: =IF(AmazonSales[[#This Row],[Delivery performance]]="Fast",1,0) -> 0
A25: 1 | B25: ORD0024 | C25: 45232 | D25: 45235 | F25: CUST028 | G25: PROD006 | H25: =_xlfn.XLOOKUP(AmazonSales[[#This Row],[Product ID]],Product_table[Product ID],Product_table[Category]) -> Fashion | I25: =_xlfn.XLOOKUP(AmazonSales[[#This Row],[Product ID]],Product_table[Product ID],Product_table[Product Name]) -> Shoes | J25: West | K25: 96 | L25: 5 | M25: 480 | N25: Amazon Pay | O25: Delivered | P25: Amazon Logistics | Q25: =IF(AND(E25<>"", O25="Cancelled"), "Cancelled", "Active") -> Active | R25: =DATEDIF(AmazonSales[[#This Row],[Order Date]],AmazonSales[[#This Row],[Delivery Date]],"d") -> 3 | S25: =IF(AmazonSales[[#This Row],[Order Status]]="Cancelled",1,0) -> 0 | T25: =IF(AmazonSales[[#This Row],[Delivery Status]]="Delivered",1,0) -> 1 | U25: =IF(AmazonSales[[#This Row],[Delivery Status]]="Delivered",AmazonSales[[#This Row],[Total Amount]],0) -> 480 | V25: {=_xlfn.IFS(AND(AmazonSales[[#This Row],[Delivery Time]]=""),"",AND(AmazonSales[[#This Row],[Delivery Time]]<=2),"Fast",AND(AmazonSales[[#This Row],[Delivery Time]]>2),"Slow")} -> Slow | W25: =IF(AmazonSales[[#This Row],[Delivery performance]]="Fast",1,0) -> 0
A26: 1 | B26: ORD0025 | C26: 45074 | D26: 45076 | F26: CUST040 | G26: PROD002 | H26: =_xlfn.XLOOKUP(AmazonSales[[#This Row],[Product ID]],Product_table[Product ID],Product_table[Category]) -> Toys | I26: =_xlfn.XLOOKUP(AmazonSales[[#This Row],[Product ID]],Product_table[Product ID],Product_table[Product Name]) -> Action Figure | J26: South | K26: 43 | L26: 1 | M26: 43 | N26: Debit Card | O26: Delivered | P26: Amazon Logistics | Q26: =IF(AND(E26<>"", O26="Cancelled"), "Cancelled", "Active") -> Active | R26: =DATEDIF(AmazonSales[[#This Row],[Order Date]],AmazonSales[[#This Row],[Delivery Date]],"d") -> 2 | S26: =IF(AmazonSales[[#This Row],[Order Status]]="Cancelled",1,0) -> 0 | T26: =IF(AmazonSales[[#This Row],[Delivery Status]]="Delivered",1,0) -> 1 | U26: =IF(AmazonSales[[#This Row],[Delivery Status]]="Delivered",AmazonSales[[#This Row],[Total Amount]],0) -> 43 | V26: {=_xlfn.IFS(AND(AmazonSales[[#This Row],[Delivery Time]]=""),"",AND(AmazonSales[[#This Row],[Delivery Time]]<=2),"Fast",AND(AmazonSales[[#This Row],[Delivery Time]]>2),"Slow")} -> Fast | W26: =IF(AmazonSales[[#This Row],[Delivery performance]]="Fast",1,0) -> 1
A27: 1 | B27: ORD0026 | C27: 45214 | D27: 45220 | F27: CUST027 | G27: PROD022 | H27: =_xlfn.XLOOKUP(AmazonSales[[#This Row],[Product ID]],Product_table[Product ID],Product_table[Category]) -> Fashion | I27: =_xlfn.XLOOKUP(AmazonSales[[#This Row],[Product ID]],Product_table[Product ID],Product_table[Product Name]) -> Backpack | J27: South | K27: 64 | L27: 4 | M27: 256 | N27: Debit Card | O27: Delivered | P27: USPS | Q27: =IF(AND(E27<>"", O27="Cancelled"), "Cancelled", "Active") -> Active | R27: =DATEDIF(AmazonSales[[#This Row],[Order Date]],AmazonSales[[#This Row],[Delivery Date]],"d") -> 6 | S27: =IF(AmazonSales[[#This Row],[Order Status]]="Cancelled",1,0) -> 0 | T27: =IF(AmazonSales[[#This Row],[Delivery Status]]="Delivered",1,0) -> 1 | U27: =IF(AmazonSales[[#This Row],[Delivery Status]]="Delivered",AmazonSales[[#This Row],[Total Amount]],0) -> 256 | V27: {=_xlfn.IFS(AND(AmazonSales[[#This Row],[Delivery Time]]=""),"",AND(AmazonSales[[#This Row],[Delivery Time]]<=2),"Fast",AND(AmazonSales[[#This Row],[Delivery Time]]>2),"Slow")} -> Slow | W27: =IF(AmazonSales[[#This Row],[Delivery performance]]="Fast",1,0) -> 0
A28: 1 | B28: ORD0027 | C28: 44942 | F28: CUST018 | G28: PROD008 | H28: =_xlfn.XLOOKUP(AmazonSales[[#This Row],[Product ID]],Product_table[Product ID],Product_table[Category]) -> Books | I28: =_xlfn.XLOOKUP(AmazonSales[[#This Row],[Product ID]],Product_table[Product ID],Product_table[Product Name]) -> Textbook | J28: South | K28: 70 | L28: 2 | M28: 140 | N28: Amazon Pay | O28: In Transit | P28: Amazon Logistics | Q28: =IF(AND(E28<>"", O28="Cancelled"), "Cancelled", "Active") -> Active | S28: =IF(AmazonSales[[#This Row],[Order Status]]="Cancelled",1,0) -> 0 | T28: =IF(AmazonSales[[#This Row],[Delivery Status]]="Delivered",1,0) -> 0 | U28: =IF(AmazonSales[[#This Row],[Delivery Status]]="Delivered",AmazonSales[[#This Row],[Total Amount]],0) -> 0 | V28: {=_xlfn.IFS(AND(AmazonSales[[#This Row],[Delivery Time]]=""),"",AND(AmazonSales[[#This Row],[Delivery Time]]<=2),"Fast",AND(AmazonSales[[#This Row],[Delivery Time]]>2),"Slow")} | W28: =IF(AmazonSales[[#This Row],[Delivery performance]]="Fast",1,0) -> 0
A29: 1 | B29: ORD0028 | C29: 45179 | F29: CUST018 | G29: PROD018 | H29: =_xlfn.XLOOKUP(AmazonSales[[#This Row],[Product ID]],Product_table[Product ID],Product_table[Category]) -> Toys | I29: =_xlfn.XLOOKUP(AmazonSales[[#This Row],[Product ID]],Product_table[Product ID],Product_table[Product Name]) -> Doll House | J29: Central | K29: 97 | L29: 3 | M29: 291 | N29: Credit Card | O29: In Transit | P29: Amazon Logistics | Q29: =IF(AND(E29<>"", O29="Cancelled"), "Cancelled", "Active") -> Active | S29: =IF(AmazonSales[[#This Row],[Order Status]]="Cancelled",1,0) -> 0 | T29: =IF(AmazonSales[[#This Row],[Delivery Status]]="Delivered",1,0) -> 0 | U29: =IF(AmazonSales[[#This Row],[Delivery Status]]="Delivered",AmazonSales[[#This Row],[Total Amount]],0) -> 0 | V29: {=_xlfn.IFS(AND(AmazonSales[[#This Row],[Delivery Time]]=""),"",AND(AmazonSales[[#This Row],[Delivery Time]]<=2),"Fast",AND(AmazonSales[[#This Row],[Delivery Time]]>2),"Slow")} | W29: =IF(AmazonSales[[#This Row],[Delivery performance]]="Fast",1,0) -> 0
A30: 1 | B30: ORD0029 | C30: 45117 | E30: 45209 | F30: CUST007 | G30: PROD021 | H30: =_xlfn.XLOOKUP(AmazonSales[[#This Row],[Product ID]],Product_table[Product ID],Product_table[Category]) -> Home | I30: =_xlfn.XLOOKUP(AmazonSales[[#This Row],[Product ID]],Product_table[Product ID],Product_table[Product Name]) -> Wall Clock | J30: East | K30: 37 | L30: 3 | M30: 111 | N30: Apple Pay | O30: Cancelled | P30: DHL | Q30: =IF(AND(E30<>"", O30="Cancelled"), "Cancelled", "Active") -> Cancelled | S30: =IF(AmazonSales[[#This Row],[Order Status]]="Cancelled",1,0) -> 1 | T30: =IF(AmazonSales[[#This Row],[Delivery Status]]="Delivered",1,0) -> 0 | U30: =IF(AmazonSales[[#This Row],[Delivery Status]]="Delivered",AmazonSales[[#This Row],[Total Amount]],0) -> 0 | V30: {=_xlfn.IFS(AND(AmazonSales[[#This Row],[Delivery Time]]=""),"",AND(AmazonSales[[#This Row],[Delivery Time]]<=2),"Fast",AND(AmazonSales[[#This Row],[Delivery Time]]>2),"Slow")} | W30: =IF(AmazonSales[[#This Row],[Delivery performance]]="Fast",1,0) -> 0
A31: 1 | B31: ORD0030 | C31: 44971 | F31: CUST008 | G31: PROD008 | H31: =_xlfn.XLOOKUP(AmazonSales[[#This Row],[Product ID]],Product_table[Product ID],Product_table[Category]) -> Books | I31: =_xlfn.XLOOKUP(AmazonSales[[#This Row],[Product ID]],Product_table[Product ID],Product_table[Product Name]) -> Textbook | J31: North | K31: 69 | L31: 5 | M31: 345 | N31: Amazon Pay | O31: In Transit | P31: Amazon Logistics | Q31: =IF(AND(E31<>"", O31="Cancelled"), "Cancelled", "Active") -> Active | S31: =IF(AmazonSales[[#This Row],[Order Status]]="Cancelled",1,0) -> 0 | T31: =IF(AmazonSales[[#This Row],[Delivery Status]]="Delivered",1,0) -> 0 | U31: =IF(AmazonSales[[#This Row],[Delivery Status]]="Delivered",AmazonSales[[#This Row],[Total Amount]],0) -> 0 | V31: {=_xlfn.IFS(AND(AmazonSales[[#This Row],[Delivery Time]]=""),"",AND(AmazonSales[[#This Row],[Delivery Time]]<=2),"Fast",AND(AmazonSales[[#This Row],[Delivery Time]]>2),"Slow")} | W31: =IF(AmazonSales[[#This Row],[Delivery performance]]="Fast",1,0) -> 0
A32: 1 | B32: ORD0031 | C32: 45011 | F32: CUST014 | G32: PROD002 | H32: =_xlfn.XLOOKUP(AmazonSales[[#This Row],[Product ID]],Product_table[Product ID],Product_table[Category]) -> Toys | I32: =_xlfn.XLOOKUP(AmazonSales[[#This Row],[Product ID]],Product_table[Product ID],Product_table[Product Name]) -> Action Figure | J32: North | K32: 42 | L32: 5 | M32: 210 | N32: Amazon Pay | O32: In Transit | P32: UPS | Q32: =IF(AND(E32<>"", O32="Cancelled"), "Cancelled", "Active") -> Active | S32: =IF(AmazonSales[[#This Row],[Order Status]]="Cancelled",1,0) -> 0 | T32: =IF(AmazonSales[[#This Row],[Delivery Status]]="Delivered",1,0) -> 0 | U32: =IF(AmazonSales[[#This Row],[Delivery Status]]="Delivered",AmazonSales[[#This Row],[Total Amount]],0) -> 0 | V32: {=_xlfn.IFS(AND(AmazonSales[[#This Row],[Delivery Time]]=""),"",AND(AmazonSales[[#This Row],[Delivery Time]]<=2),"Fast",AND(AmazonSales[[#This Row],[Delivery Time]]>2),"Slow")} | W32: =IF(AmazonSales[[#This Row],[Delivery performance]]="Fast",1,0) -> 0
A33: 1 | B33: ORD0032 | C33: 45092 | E33: 45099 | F33: CUST037 | G33: PROD009 | H33: =_xlfn.XLOOKUP(AmazonSales[[#This Row],[Product ID]],Product_table[Product ID],Product_table[Category]) -> Books | I33: =_xlfn.XLOOKUP(AmazonSales[[#This Row],[Product ID]],Product_table[Product ID],Product_table[Product Name]) -> Magazine | J33: East | K33: 11 | L33: 5 | M33: 55 | N33: Debit Card | O33: Cancelled | P33: FedEx | Q33: =IF(AND(E33<>"", O33="Cancelled"), "Cancelled", "Active") -> Cancelled | S33: =IF(AmazonSales[[#This Row],[Order Status]]="Cancelled",1,0) -> 1 | T33: =IF(AmazonSales[[#This Row],[Delivery Status]]="Delivered",1,0) -> 0 | U33: =IF(AmazonSales[[#This Row],[Delivery Status]]="Delivered",AmazonSales[[#This Row],[Total Amount]],0) -> 0 | V33: {=_xlfn.IFS(AND(AmazonSales[[#This Row],[Delivery Time]]=""),"",AND(AmazonSales[[#This Row],[Delivery Time]]<=2),"Fast",AND(AmazonSales[[#This Row],[Delivery Time]]>2),"Slow")} | W33: =IF(AmazonSales[[#This Row],[Delivery performance]]="Fast",1,0) -> 0
A34: 1 | B34: ORD0033 | C34: 45068 | D34: 45069 | F34: CUST016 | G34: PROD005 | H34: =_xlfn.XLOOKUP(AmazonSales[[#This Row],[Product ID]],Product_table[Product ID],Product_table[Category]) -> Fashion | I34: =_xlfn.XLOOKUP(AmazonSales[[#This Row],[Product ID]],Product_table[Product ID],Product_table[Product Name]) -> T-Shirt | J34: South | K34: 27 | L34: 2 | M34: 54 | N34: Apple Pay | O34: Delivered | P34: USPS | Q34: =IF(AND(E34<>"", O34="Cancelled"), "Cancelled", "Active") -> Active | R34: =DATEDIF(AmazonSales[[#This Row],[Order Date]],AmazonSales[[#This Row],[Delivery Date]],"d") -> 1 | S34: =IF(AmazonSales[[#This Row],[Order Status]]="Cancelled",1,0) -> 0 | T34: =IF(AmazonSales[[#This Row],[Delivery Status]]="Delivered",1,0) -> 1 | U34: =IF(AmazonSales[[#This Row],[Delivery Status]]="Delivered",AmazonSales[[#This Row],[Total Amount]],0) -> 54 | V34: {=_xlfn.IFS(AND(AmazonSales[[#This Row],[Delivery Time]]=""),"",AND(AmazonSales[[#This Row],[Delivery Time]]<=2),"Fast",AND(AmazonSales[[#This Row],[Delivery Time]]>2),"Slow")} -> Fast | W34: =IF(AmazonSales[[#This Row],[Delivery performance]]="Fast",1,0) -> 1
A35: 1 | B35: ORD0034 | C35: 45250 | F35: CUST025 | G35: PROD015 | H35: =_xlfn.XLOOKUP(AmazonSales[[#This Row],[Product ID]],Product_table[Product ID],Product_table[Category]) -> Books | I35: =_xlfn.XLOOKUP(AmazonSales[[#This Row],[Product ID]],Product_table[Product ID],Product_table[Product Name]) -> Novel | J35: South | K35: 21 | L35: 1 | M35: 21 | N35: Amazon Pay | O35: In Transit | P35: DHL | Q35: =IF(AND(E35<>"", O35="Cancelled"), "Cancelled", "Active") -> Active | S35: =IF(AmazonSales[[#This Row],[Order Status]]="Cancelled",1,0) -> 0 | T35: =IF(AmazonSales[[#This Row],[Delivery Status]]="Delivered",1,0) -> 0 | U35: =IF(AmazonSales[[#This Row],[Delivery Status]]="Delivered",AmazonSales[[#This Row],[Total Amount]],0) -> 0 | V35: {=_xlfn.IFS(AND(AmazonSales[[#This Row],[Delivery Time]]=""),"",AND(AmazonSales[[#This Row],[Delivery Time]]<=2),"Fast",AND(AmazonSales[[#This Row],[Delivery Time]]>2),"Slow")} | W35: =IF(AmazonSales[[#This Row],[Delivery performance]]="Fast",1,0) -> 0
A36: 1 | B36: ORD0035 | C36: 45261 | D36: 45286 | F36: CUST032 | G36: PROD011 | H36: =_xlfn.XLOOKUP(AmazonSales[[#This Row],[Product ID]],Product_table[Product ID],Product_table[Category]) -> Electronics | I36: =_xlfn.XLOOKUP(AmazonSales[[#This Row],[Product ID]],Product_table[Product ID],Product_table[Product Name]) -> Headphones | J36: South | K36: 172 | L36: 1 | M36: 172 | N36: PayPal | O36: Delivered | P36: USPS | Q36: =IF(AND(E36<>"", O36="Cancelled"), "Cancelled", "Active") -> Active | R36: =DATEDIF(AmazonSales[[#This Row],[Order Date]],AmazonSales[[#This Row],[Delivery Date]],"d") -> 25 | S36: =IF(AmazonSales[[#This Row],[Order Status]]="Cancelled",1,0) -> 0 | T36: =IF(AmazonSales[[#This Row],[Delivery Status]]="Delivered",1,0) -> 1 | U36: =IF(AmazonSales[[#This Row],[Delivery Status]]="Delivered",AmazonSales[[#This Row],[Total Amount]],0) -> 172 | V36: {=_xlfn.IFS(AND(AmazonSales[[#This Row],[Delivery Time]]=""),"",AND(AmazonSales[[#This Row],[Delivery Time]]<=2),"Fast",AND(AmazonSales[[#This Row],[Delivery Time]]>2),"Slow")} -> Slow | W36: =IF(AmazonSales[[#This Row],[Delivery performance]]="Fast",1,0) -> 0
A37: 1 | B37: ORD0036 | C37: 45130 | F37: CUST014 | G37: PROD016 | H37: =_xlfn.XLOOKUP(AmazonSales[[#This Row],[Product ID]],Product_table[Product ID],Product_table[Category]) -> Home | I37: =_xlfn.XLOOKUP(AmazonSales[[#This Row],[Product ID]],Product_table[Product ID],Product_table[Product Name]) -> Cookware Set Pro | J37: North | K37: 212 | L37: 3 | M37: 636 | N37: Amazon Pay | O37: In Transit | P37: UPS | Q37: =IF(AND(E37<>"", O37="Cancelled"), "Cancelled", "Active") -> Active | S37: =IF(AmazonSales[[#This Row],[Order Status]]="Cancelled",1,0) -> 0 | T37: =IF(AmazonSales[[#This Row],[Delivery Status]]="Delivered",1,0) -> 0 | U37: =IF(AmazonSales[[#This Row],[Delivery Status]]="Delivered",AmazonSales[[#This Row],[Total Amount]],0) -> 0 | V37: {=_xlfn.IFS(AND(AmazonSales[[#This Row],[Delivery Time]]=""),"",AND(AmazonSales[[#This Row],[Delivery Time]]<=2),"Fast",AND(AmazonSales[[#This Row],[Delivery Time]]>2),"Slow")} | W37: =IF(AmazonSales[[#This Row],[Delivery performance]]="Fast",1,0) -> 0
A38: 1 | B38: ORD0037 | C38: 45216 | D38: 45221 | F38: CUST044 | G38: PROD002 | H38: =_xlfn.XLOOKUP(AmazonSales[[#This Row],[Product ID]],Product_table[Product ID],Product_table[Category]) -> Toys | I38: =_xlfn.XLOOKUP(AmazonSales[[#This Row],[Product ID]],Product_table[Product ID],Product_table[Product Name]) -> Action Figure | J38: East | K38: 41 | L38: 4 | M38: 164 | N38: Credit Card | O38: Delivered | P38: Amazon Logistics | Q38: =IF(AND(E38<>"", O38="Cancelled"), "Cancelled", "Active") -> Active | R38: =DATEDIF(AmazonSales[[#This Row],[Order Date]],AmazonSales[[#This Row],[Delivery Date]],"d") -> 5 | S38: =IF(AmazonSales[[#This Row],[Order Status]]="Cancelled",1,0) -> 0 | T38: =IF(AmazonSales[[#This Row],[Delivery Status]]="Delivered",1,0) -> 1 | U38: =IF(AmazonSales[[#This Row],[Delivery Status]]="Delivered",AmazonSales[[#This Row],[Total Amount]],0) -> 164 | V38: {=_xlfn.IFS(AND(AmazonSales[[#This Row],[Delivery Time]]=""),"",AND(AmazonSales[[#This Row],[Delivery Time]]<=2),"Fast",AND(AmazonSales[[#This Row],[Delivery Time]]>2),"Slow")} -> Slow | W38: =IF(AmazonSales[[#This Row],[Delivery performance]]="Fast",1,0) -> 0
A39: 1 | B39: ORD0038 | C39: 45160 | E39: 45162 | F39: CUST028 | G39: PROD007 | H39: =_xlfn.XLOOKUP(AmazonSales[[#This Row],[Product ID]],Product_table[Product ID],Product_table[Category]) -> Toys | I39: =_xlfn.XLOOKUP(AmazonSales[[#This Row],[Product ID]],Product_table[Product ID],Product_table[Product Name]) -> Puzzle | J39: North | K39: 32 | L39: 2 | M39: 64 | N39: Debit Card | O39: Cancelled | P39: FedEx | Q39: =IF(AND(E39<>"", O39="Cancelled"), "Cancelled", "Active") -> Cancelled | S39: =IF(AmazonSales[[#This Row],[Order Status]]="Cancelled",1,0) -> 1 | T39: =IF(AmazonSales[[#This Row],[Delivery Status]]="Delivered",1,0) -> 0 | U39: =IF(AmazonSales[[#This Row],[Delivery Status]]="Delivered",AmazonSales[[#This Row],[Total Amount]],0) -> 0 | V39: {=_xlfn.IFS(AND(AmazonSales[[#This Row],[Delivery Time]]=""),"",AND(AmazonSales[[#This Row],[Delivery Time]]<=2),"Fast",AND(AmazonSales[[#This Row],[Delivery Time]]>2),"Slow")} | W39: =IF(AmazonSales[[#This Row],[Delivery performance]]="Fast",1,0) -> 0
A40: 1 | B40: ORD0039 | C40: 44938 | F40: CUST024 | G40: PROD022 | H40: =_xlfn.XLOOKUP(AmazonSales[[#This Row],[Product ID]],Product_table[Product ID],Product_table[Category]) -> Fashion | I40: =_xlfn.XLOOKUP(AmazonSales[[#This Row],[Product ID]],Product_table[Product ID],Product_table[Product Name]) -> Backpack | J40: East | K40: 66 | L40: 2 | M40: 132 | N40: Apple Pay | O40: In Transit | P40: DHL | Q40: =IF(AND(E40<>"", O40="Cancelled"), "Cancelled", "Active") -> Active | S40: =IF(AmazonSales[[#This Row],[Order Status]]="Cancelled",1,0) -> 0 | T40: =IF(AmazonSales[[#This Row],[Delivery Status]]="Delivered",1,0) -> 0 | U40: =IF(AmazonSales[[#This Row],[Delivery Status]]="Delivered",AmazonSales[[#This Row],[Total Amount]],0) -> 0 | V40: {=_xlfn.IFS(AND(AmazonSales[[#This Row],[Delivery Time]]=""),"",AND(AmazonSales[[#This Row],[Delivery Time]]<=2),"Fast",AND(AmazonSales[[#This Row],[Delivery Time]]>2),"Slow")} | W40: =IF(AmazonSales[[#This Row],[Delivery performance]]="Fast",1,0) -> 0
A41: 1 | B41: ORD0040 | C41: 44938 | F41: CUST006 | G41: PROD004 | H41: =_xlfn.XLOOKUP(AmazonSales[[#This Row],[Product ID]],Product_table[Product ID],Product_table[Category]) -> Toys | I41: =_xlfn.XLOOKUP(AmazonSales[[#This Row],[Product ID]],Product_table[Product ID],Product_table[Product Name]) -> Leg Set | J41: East | K41: 62 | L41: 4 | M41: 248 | N41: Debit Card | O41: In Transit | P41: UPS | Q41: =IF(AND(E41<>"", O41="Cancelled"), "Cancelled", "Active") -> Active | S41: =IF(AmazonSales[[#This Row],[Order Status]]="Cancelled",1,0) -> 0 | T41: =IF(AmazonSales[[#This Row],[Delivery Status]]="Delivered",1,0) -> 0 | U41: =IF(AmazonSales[[#This Row],[Delivery Status]]="Delivered",AmazonSales[[#This Row],[Total Amount]],0) -> 0 | V41: {=_xlfn.IFS(AND(AmazonSales[[#This Row],[Delivery Time]]=""),"",AND(AmazonSales[[#This Row],[Delivery Time]]<=2),"Fast",AND(AmazonSales[[#This Row],[Delivery Time]]>2),"Slow")} | W41: =IF(AmazonSales[[#This Row],[Delivery performance]]="Fast",1,0) -> 0
A42: 1 | B42: ORD0041 | C42: 45192 | D42: 45199 | F42: CUST001 | G42: PROD011 | H42: =_xlfn.XLOOKUP(AmazonSales[[#This Row],[Product ID]],Product_table[Product ID],Product_table[Category]) -> Electronics | I42: =_xlfn.XLOOKUP(AmazonSales[[#This Row],[Product ID]],Product_table[Product ID],Product_table[Product Name]) -> Headphones | J42: West | K42: 173 | L42: 4 | M42: 692 | N42: Apple Pay | O42: Delivered | P42: UPS | Q42: =IF(AND(E42<>"", O42="Cancelled"), "Cancelled", "Active") -> Active | R42: =DATEDIF(AmazonSales[[#This Row],[Order Date]],AmazonSales[[#This Row],[Delivery Date]],"d") -> 7 | S42: =IF(AmazonSales[[#This Row],[Order Status]]="Cancelled",1,0) -> 0 | T42: =IF(AmazonSales[[#This Row],[Delivery Status]]="Delivered",1,0) -> 1 | U42: =IF(AmazonSales[[#This Row],[Delivery Status]]="Delivered",AmazonSales[[#This Row],[Total Amount]],0) -> 692 | V42: {=_xlfn.IFS(AND(AmazonSales[[#This Row],[Delivery Time]]=""),"",AND(AmazonSales[[#This Row],[Delivery Time]]<=2),"Fast",AND(AmazonSales[[#This Row],[Delivery Time]]>2),"Slow")} -> Slow | W42: =IF(AmazonSales[[#This Row],[Delivery performance]]="Fast",1,0) -> 0
A43: 1 | B43: ORD0042 | C43: 45123 | D43: 45125 | F43: CUST007 | G43: PROD004 | H43: =_xlfn.XLOOKUP(AmazonSales[[#This Row],[Product ID]],Product_table[Product ID],Product_table[Category]) -> Toys | I43: =_xlfn.XLOOKUP(AmazonSales[[#This Row],[Product ID]],Product_table[Product ID],Product_table[Product Name]) -> Leg Set | J43: West | K43: 63 | L43: 3 | M43: 189 | N43: Apple Pay | O43: Delivered | P43: UPS | Q43: =IF(AND(E43<>"", O43="Cancelled"), "Cancelled", "Active") -> Active | R43: =DATEDIF(AmazonSales[[#This Row],[Order Date]],AmazonSales[[#This Row],[Delivery Date]],"d") -> 2 | S43: =IF(AmazonSales[[#This Row],[Order Status]]="Cancelled",1,0) -> 0 | T43: =IF(AmazonSales[[#This Row],[Delivery Status]]="Delivered",1,0) -> 1 | U43: =IF(AmazonSales[[#This Row],[Delivery Status]]="Delivered",AmazonSales[[#This Row],[Total Amount]],0) -> 189 | V43: {=_xlfn.IFS(AND(AmazonSales[[#This Row],[Delivery Time]]=""),"",AND(AmazonSales[[#This Row],[Delivery Time]]<=2),"Fast",AND(AmazonSales[[#This Row],[Delivery Time]]>2),"Slow")} -> Fast | W43: =IF(AmazonSales[[#This Row],[Delivery performance]]="Fast",1,0) -> 1
A44: 1 | B44: ORD0043 | C44: 44962 | E44: 44968 | F44: CUST040 | G44: PROD021 | H44: =_xlfn.XLOOKUP(AmazonSales[[#This Row],[Product ID]],Product_table[Product ID],Product_table[Category]) -> Home | I44: =_xlfn.XLOOKUP(AmazonSales[[#This Row],[Product ID]],Product_table[Product ID],Product_table[Product Name]) -> Wall Clock | J44: West | K44: 36 | L44: 3 | M44: 108 | N44: Debit Card | O44: Cancelled | P44: USPS | Q44: =IF(AND(E44<>"", O44="Cancelled"), "Cancelled", "Active") -> Cancelled | S44: =IF(AmazonSales[[#This Row],[Order Status]]="Cancelled",1,0) -> 1 | T44: =IF(AmazonSales[[#This Row],[Delivery Status]]="Delivered",1,0) -> 0 | U44: =IF(AmazonSales[[#This Row],[Delivery Status]]="Delivered",AmazonSales[[#This Row],[Total Amount]],0) -> 0 | V44: {=_xlfn.IFS(AND(AmazonSales[[#This Row],[Delivery Time]]=""),"",AND(AmazonSales[[#This Row],[Delivery Time]]<=2),"Fast",AND(AmazonSales[[#This Row],[Delivery Time]]>2),"Slow")} | W44: =IF(AmazonSales[[#This Row],[Delivery performance]]="Fast",1,0) -> 0
A45: 1 | B45: ORD0044 | C45: 45278 | E45: 45283 | F45: CUST006 | G45: PROD004 | H45: =_xlfn.XLOOKUP(AmazonSales[[#This Row],[Product ID]],Product_table[Product ID],Product_table[Category]) -> Toys | I45: =_xlfn.XLOOKUP(AmazonSales[[#This Row],[Product ID]],Product_table[Product ID],Product_table[Product Name]) -> Leg Set | J45: Central | K45: 62 | L45: 1 | M45: 62 | N45: Apple Pay | O45: Cancelled | P45: Amazon Logistics | Q45: =IF(AND(E45<>"", O45="Cancelled"), "Cancelled", "Active") -> Cancelled | S45: =IF(AmazonSales[[#This Row],[Order Status]]="Cancelled",1,0) -> 1 | T45: =IF(AmazonSales[[#This Row],[Delivery Status]]="Delivered",1,0) -> 0 | U45: =IF(AmazonSales[[#This Row],[Delivery Status]]="Delivered",AmazonSales[[#This Row],[Total Amount]],0) -> 0 | V45: {=_xlfn.IFS(AND(AmazonSales[[#This Row],[Delivery Time]]=""),"",AND(AmazonSales[[#This Row],[Delivery Time]]<=2),"Fast",AND(AmazonSales[[#This Row],[Delivery Time]]>2),"Slow")} | W45: =IF(AmazonSales[[#This Row],[Delivery performance]]="Fast",1,0) -> 0
A46: 1 | B46: ORD0045 | C46: 45088 | E46: 45091 | F46: CUST042 | G46: PROD003 | H46: =_xlfn.XLOOKUP(AmazonSales[[#This Row],[Product ID]],Product_table[Product ID],Product_table[Category]) -> Home | I46: =_xlfn.XLOOKUP(AmazonSales[[#This Row],[Product ID]],Product_table[Product ID],Product_table[Product Name]) -> Cookware Set | J46: Central | K46: 137 | L46: 5 | M46: 685 | N46: Amazon Pay | O46: Cancelled | P46: FedEx | Q46: =IF(AND(E46<>"", O46="Cancelled"), "Cancelled", "Active") -> Cancelled | S46: =IF(AmazonSales[[#This Row],[Order Status]]="Cancelled",1,0) -> 1 | T46: =IF(AmazonSales[[#This Row],[Delivery Status]]="Delivered",1,0) -> 0 | U46: =IF(AmazonSales[[#This Row],[Delivery Status]]="Delivered",AmazonSales[[#This Row],[Total Amount]],0) -> 0 | V46: {=_xlfn.IFS(AND(AmazonSales[[#This Row],[Delivery Time]]=""),"",AND(AmazonSales[[#This Row],[Delivery Time]]<=2),"Fast",AND(AmazonSales[[#This Row],[Delivery Time]]>2),"Slow")} | W46: =IF(AmazonSales[[#This Row],[Delivery performance]]="Fast",1,0) -> 0
A47: 1 | B47: ORD0046 | C47: 45264 | D47: 45268 | F47: CUST039 | G47: PROD017 | H47: =_xlfn.XLOOKUP(AmazonSales[[#This Row],[Product ID]],Product_table[Product ID],Product_table[Category]) -> Electronics | I47: =_xlfn.XLOOKUP(AmazonSales[[#This Row],[Product ID]],Product_table[Product ID],Product_table[Product Name]) -> Gaming Mouse | J47: North | K47: 73 | L47: 4 | M47: 292 | N47: Credit Card | O47: Delivered | P47: Amazon Logistics | Q47: =IF(AND(E47<>"", O47="Cancelled"), "Cancelled", "Active") -> Active | R47: =DATEDIF(AmazonSales[[#This Row],[Order Date]],AmazonSales[[#This Row],[Delivery Date]],"d") -> 4 | S47: =IF(AmazonSales[[#This Row],[Order Status]]="Cancelled",1,0) -> 0 | T47: =IF(AmazonSales[[#This Row],[Delivery Status]]="Delivered",1,0) -> 1 | U47: =IF(AmazonSales[[#This Row],[Delivery Status]]="Delivered",AmazonSales[[#This Row],[Total Amount]],0) -> 292 | V47: {=_xlfn.IFS(AND(AmazonSales[[#This Row],[Delivery Time]]=""),"",AND(AmazonSales[[#This Row],[Delivery Time]]<=2),"Fast",AND(AmazonSales[[#This Row],[Delivery Time]]>2),"Slow")} -> Slow | W47: =IF(AmazonSales[[#This Row],[Delivery performance]]="Fast",1,0) -> 0
A48: 1 | B48: ORD0047 | C48: 45124 | D48: 45126 | F48: CUST041 | G48: PROD020 | H48: =_xlfn.XLOOKUP(AmazonSales[[#This Row],[Product ID]],Product_table[Product ID],Product_table[Category]) -> Electronics | I48: =_xlfn.XLOOKUP(AmazonSales[[#This Row],[Product ID]],Product_table[Product ID],Product_table[Product Name]) -> Bluetooth Speaker | J48: North | K48: 104 | L48: 1 | M48: 104 | N48: PayPal | O48: Delivered | P48: Amazon Logistics | Q48: =IF(AND(E48<>"", O48="Cancelled"), "Cancelled", "Active") -> Active | R48: =DATEDIF(AmazonSales[[#This Row],[Order Date]],AmazonSales[[#This Row],[Delivery Date]],"d") -> 2 | S48: =IF(AmazonSales[[#This Row],[Order Status]]="Cancelled",1,0) -> 0 | T48: =IF(AmazonSales[[#This Row],[Delivery Status]]="Delivered",1,0) -> 1 | U48: =IF(AmazonSales[[#This Row],[Delivery Status]]="Delivered",AmazonSales[[#This Row],[Total Amount]],0) -> 104 | V48: {=_xlfn.IFS(AND(AmazonSales[[#This Row],[Delivery Time]]=""),"",AND(AmazonSales[[#This Row],[Delivery Time]]<=2),"Fast",AND(AmazonSales[[#This Row],[Delivery Time]]>2),"Slow")} -> Fast | W48: =IF(AmazonSales[[#This Row],[Delivery performance]]="Fast",1,0) -> 1
A49: 1 | B49: ORD0048 | C49: 45218 | D49: 45223 | F49: CUST044 | G49: PROD006 | H49: =_xlfn.XLOOKUP(AmazonSales[[#This Row],[Product ID]],Product_table[Product ID],Product_table[Category]) -> Fashion | I49: =_xlfn.XLOOKUP(AmazonSales[[#This Row],[Product ID]],Product_table[Product ID],Product_table[Product Name]) -> Shoes | J49: East | K49: 97 | L49: 1 | M49: 97 | N49: Amazon Pay | O49: Delivered | P49: FedEx | Q49: =IF(AND(E49<>"", O49="Cancelled"), "Cancelled", "Active") -> Active | R49: =DATEDIF(AmazonSales[[#This Row],[Order Date]],AmazonSales[[#This Row],[Delivery Date]],"d") -> 5 | S49: =IF(AmazonSales[[#This Row],[Order Status]]="Cancelled",1,0) -> 0 | T49: =IF(AmazonSales[[#This Row],[Delivery Status]]="Delivered",1,0) -> 1 | U49: =IF(AmazonSales[[#This Row],[Delivery Status]]="Delivered",AmazonSales[[#This Row],[Total Amount]],0) -> 97 | V49: {=_xlfn.IFS(AND(AmazonSales[[#This Row],[Delivery Time]]=""),"",AND(AmazonSales[[#This Row],[Delivery Time]]<=2),"Fast",AND(AmazonSales[[#This Row],[Delivery Time]]>2),"Slow")} -> Slow | W49: =IF(AmazonSales[[#This Row],[Delivery performance]]="Fast",1,0) -> 0
A50: 1 | B50: ORD0049 | C50: 45061 | F50: CUST026 | G50: PROD017 | H50: =_xlfn.XLOOKUP(AmazonSales[[#This Row],[Product ID]],Product_table[Product ID],Product_table[Category]) -> Electronics | I50: =_xlfn.XLOOKUP(AmazonSales[[#This Row],[Product ID]],Product_table[Product ID],Product_table[Product Name]) -> Gaming Mouse | J50: South | K50: 73 | L50: 5 | M50: 365 | N50: Apple Pay | O50: In Transit | P50: Amazon Logistics | Q50: =IF(AND(E50<>"", O50="Cancelled"), "Cancelled", "Active") -> Active | S50: =IF(AmazonSales[[#This Row],[Order Status]]="Cancelled",1,0) -> 0 | T50: =IF(AmazonSales[[#This Row],[Delivery Status]]="Delivered",1,0) -> 0 | U50: =IF(AmazonSales[[#This Row],[Delivery Status]]="Delivered",AmazonSales[[#This Row],[Total Amount]],0) -> 0 | V50: {=_xlfn.IFS(AND(AmazonSales[[#This Row],[Delivery Time]]=""),"",AND(AmazonSales[[#This Row],[Delivery Time]]<=2),"Fast",AND(AmazonSales[[#This Row],[Delivery Time]]>2),"Slow")} | W50: =IF(AmazonSales[[#This Row],[Delivery performance]]="Fast",1,0) -> 0
A51: 1 | B51: ORD0050 | C51: 44938 | D51: 44976 | F51: CUST040 | G51: PROD005 | H51: =_xlfn.XLOOKUP(AmazonSales[[#This Row],[Product ID]],Product_table[Product ID],Product_table[Category]) -> Fashion | I51: =_xlfn.XLOOKUP(AmazonSales[[#This Row],[Product ID]],Product_table[Product ID],Product_table[Product Name]) -> T-Shirt | J51: East | K51: 27 | L51: 3 | M51: 81 | N51: Amazon Pay | O51: Delivered | P51: UPS | Q51: =IF(AND(E51<>"", O51="Cancelled"), "Cancelled", "Active") -> Active | R51: =DATEDIF(AmazonSales[[#This Row],[Order Date]],AmazonSales[[#This Row],[Delivery Date]],"d") -> 38 | S51: =IF(AmazonSales[[#This Row],[Order Status]]="Cancelled",1,0) -> 0 | T51: =IF(AmazonSales[[#This Row],[Delivery Status]]="Delivered",1,0) -> 1 | U51: =IF(AmazonSales[[#This Row],[Delivery Status]]="Delivered",AmazonSales[[#This Row],[Total Amount]],0) -> 81 | V51: {=_xlfn.IFS(AND(AmazonSales[[#This Row],[Delivery Time]]=""),"",AND(AmazonSales[[#This Row],[Delivery Time]]<=2),"Fast",AND(AmazonSales[[#This Row],[Delivery Time]]>2),"Slow")} -> Slow | W51: =IF(AmazonSales[[#This Row],[Delivery performance]]="Fast",1,0) -> 0
A52: 1 | B52: ORD0051 | C52: 44967 | F52: CUST041 | G52: PROD021 | H52: =_xlfn.XLOOKUP(AmazonSales[[#This Row],[Product ID]],Product_table[Product ID],Product_table[Category]) -> Home | I52: =_xlfn.XLOOKUP(AmazonSales[[#This Row],[Product ID]],Product_table[Product ID],Product_table[Product Name]) -> Wall Clock | J52: North | K52: 37 | L52: 1 | M52: 37 | N52: Apple Pay | O52: In Transit | P52: UPS | Q52: =IF(AND(E52<>"", O52="Cancelled"), "Cancelled", "Active") -> Active | S52: =IF(AmazonSales[[#This Row],[Order Status]]="Cancelled",1,0) -> 0 | T52: =IF(AmazonSales[[#This Row],[Delivery Status]]="Delivered",1,0) -> 0 | U52: =IF(AmazonSales[[#This Row],[Delivery Status]]="Delivered",AmazonSales[[#This Row],[Total Amount]],0) -> 0 | V52: {=_xlfn.IFS(AND(AmazonSales[[#This Row],[Delivery Time]]=""),"",AND(AmazonSales[[#This Row],[Delivery Time]]<=2),"Fast",AND(AmazonSales[[#This Row],[Delivery Time]]>2),"Slow")} | W52: =IF(AmazonSales[[#This Row],[Delivery performance]]="Fast",1,0) -> 0
A53: 1 | B53: ORD0052 | C53: 44956 | D53: 44958 | F53: CUST008 | G53: PROD015 | H53: =_xlfn.XLOOKUP(AmazonSales[[#This Row],[Product ID]],Product_table[Product ID],Product_table[Category]) -> Books | I53: =_xlfn.XLOOKUP(AmazonSales[[#This Row],[Product ID]],Product_table[Product ID],Product_table[Product Name]) -> Novel | J53: North | K53: 22 | L53: 1 | M53: 22 | N53: Debit Card | O53: Delivered | P53: FedEx | Q53: =IF(AND(E53<>"", O53="Cancelled"), "Cancelled", "Active") -> Active | R53: =DATEDIF(AmazonSales[[#This Row],[Order Date]],AmazonSales[[#This Row],[Delivery Date]],"d") -> 2 | S53: =IF(AmazonSales[[#This Row],[Order Status]]="Cancelled",1,0) -> 0 | T53: =IF(AmazonSales[[#This Row],[Delivery Status]]="Delivered",1,0) -> 1 | U53: =IF(AmazonSales[[#This Row],[Delivery Status]]="Delivered",AmazonSales[[#This Row],[Total Amount]],0) -> 22 | V53: {=_xlfn.IFS(AND(AmazonSales[[#This Row],[Delivery Time]]=""),"",AND(AmazonSales[[#This Row],[Delivery Time]]<=2),"Fast",AND(AmazonSales[[#This Row],[Delivery Time]]>2),"Slow")} -> Fast | W53: =IF(AmazonSales[[#This Row],[Delivery performance]]="Fast",1,0) -> 1
A54: 1 | B54: ORD0053 | C54: 45289 | D54: 45292 | F54: CUST011 | G54: PROD016 | H54: =_xlfn.XLOOKUP(AmazonSales[[#This Row],[Product ID]],Product_table[Product ID],Product_table[Category]) -> Home | I54: =_xlfn.XLOOKUP(AmazonSales[[#This Row],[Product ID]],Product_table[Product ID],Product_table[Product Name]) -> Cookware Set Pro | J54: Central | K54: 218 | L54: 5 | M54: 1090 | N54: PayPal | O54: Delivered | P54: DHL | Q54: =IF(AND(E54<>"", O54="Cancelled"), "Cancelled", "Active") -> Active | R54: =DATEDIF(AmazonSales[[#This Row],[Order Date]],AmazonSales[[#This Row],[Delivery Date]],"d") -> 3 | S54: =IF(AmazonSales[[#This Row],[Order Status]]="Cancelled",1,0) -> 0 | T54: =IF(AmazonSales[[#This Row],[Delivery Status]]="Delivered",1,0) -> 1 | U54: =IF(AmazonSales[[#This Row],[Delivery Status]]="Delivered",AmazonSales[[#This Row],[Total Amount]],0) -> 1090 | V54: {=_xlfn.IFS(AND(AmazonSales[[#This Row],[Delivery Time]]=""),"",AND(AmazonSales[[#This Row],[Delivery Time]]<=2),"Fast",AND(AmazonSales[[#This Row],[Delivery Time]]>2),"Slow")} -> Slow | W54: =IF(AmazonSales[[#This Row],[Delivery performance]]="Fast",1,0) -> 0
A55: 1 | B55: ORD0054 | C55: 44991 | E55: 44998 | F55: CUST018 | G55: PROD004 | H55: =_xlfn.XLOOKUP(AmazonSales[[#This Row],[Product ID]],Product_table[Product ID],Product_table[Category]) -> Toys | I55: =_xlfn.XLOOKUP(AmazonSales[[#This Row],[Product ID]],Product_table[Product ID],Product_table[Product Name]) -> Leg Set | J55: North | K55: 64 | L55: 1 | M55: 64 | N55: Apple Pay | O55: Cancelled | P55: USPS | Q55: =IF(AND(E55<>"", O55="Cancelled"), "Cancelled", "Active") -> Cancelled | S55: =IF(AmazonSales[[#This Row],[Order Status]]="Cancelled",1,0) -> 1 | T55: =IF(AmazonSales[[#This Row],[Delivery Status]]="Delivered",1,0) -> 0 | U55: =IF(AmazonSales[[#This Row],[Delivery Status]]="Delivered",AmazonSales[[#This Row],[Total Amount]],0) -> 0 | V55: {=_xlfn.IFS(AND(AmazonSales[[#This Row],[Delivery Time]]=""),"",AND(AmazonSales[[#This Row],[Delivery Time]]<=2),"Fast",AND(AmazonSales[[#This Row],[Delivery Time]]>2),"Slow")} | W55: =IF(AmazonSales[[#This Row],[Delivery performance]]="Fast",1,0) -> 0
A56: 1 | B56: ORD0055 | C56: 44959 | D56: 44963 | F56: CUST037 | G56: PROD021 | H56: =_xlfn.XLOOKUP(AmazonSales[[#This Row],[Product ID]],Product_table[Product ID],Product_table[Category]) -> Home | I56: =_xlfn.XLOOKUP(AmazonSales[[#This Row],[Product ID]],Product_table[Product ID],Product_table[Product Name]) -> Wall Clock | J56: Central | K56: 36 | L56: 4 | M56: 144 | N56: PayPal | O56: Delivered | P56: Amazon Logistics | Q56: =IF(AND(E56<>"", O56="Cancelled"), "Cancelled", "Active") -> Active | R56: =DATEDIF(AmazonSales[[#This Row],[Order Date]],AmazonSales[[#This Row],[Delivery Date]],"d") -> 4 | S56: =IF(AmazonSales[[#This Row],[Order Status]]="Cancelled",1,0) -> 0 | T56: =IF(AmazonSales[[#This Row],[Delivery Status]]="Delivered",1,0) -> 1 | U56: =IF(AmazonSales[[#This Row],[Delivery Status]]="Delivered",AmazonSales[[#This Row],[Total Amount]],0) -> 144 | V56: {=_xlfn.IFS(AND(AmazonSales[[#This Row],[Delivery Time]]=""),"",AND(AmazonSales[[#This Row],[Delivery Time]]<=2),"Fast",AND(AmazonSales[[#This Row],[Delivery Time]]>2),"Slow")} -> Slow | W56: =IF(AmazonSales[[#This Row],[Delivery performance]]="Fast",1,0) -> 0
A57: 1 | B57: ORD0056 | C57: 45217 | D57: 45220 | F57: CUST017 | G57: PROD004 | H57: =_xlfn.XLOOKUP(AmazonSales[[#This Row],[Product ID]],Product_table[Product ID],Product_table[Category]) -> Toys | I57: =_xlfn.XLOOKUP(AmazonSales[[#This Row],[Product ID]],Product_table[Product ID],Product_table[Product Name]) -> Leg Set | J57: West | K57: 65 | L57: 1 | M57: 65 | N57: Amazon Pay | O57: Delivered | P57: FedEx | Q57: =IF(AND(E57<>"", O57="Cancelled"), "Cancelled", "Active") -> Active | R57: =DATEDIF(AmazonSales[[#This Row],[Order Date]],AmazonSales[[#This Row],[Delivery Date]],"d") -> 3 | S57: =IF(AmazonSales[[#This Row],[Order Status]]="Cancelled",1,0) -> 0 | T57: =IF(AmazonSales[[#This Row],[Delivery Status]]="Delivered",1,0) -> 1 | U57: =IF(AmazonSales[[#This Row],[Delivery Status]]="Delivered",AmazonSales[[#This Row],[Total Amount]],0) -> 65 | V57: {=_xlfn.IFS(AND(AmazonSales[[#This Row],[Delivery Time]]=""),"",AND(AmazonSales[[#This Row],[Delivery Time]]<=2),"Fast",AND(AmazonSales[[#This Row],[Delivery Time]]>2),"Slow")} -> Slow | W57: =IF(AmazonSales[[#This Row],[Delivery performance]]="Fast",1,0) -> 0
A58: 1 | B58: ORD0057 | C58: 44933 | D58: 44935 | F58: CUST025 | G58: PROD005 | H58: =_xlfn.XLOOKUP(AmazonSales[[#This Row],[Product ID]],Product_table[Product ID],Product_table[Category]) -> Fashion | I58: =_xlfn.XLOOKUP(AmazonSales[[#This Row],[Product ID]],Product_table[Product ID],Product_table[Product Name]) -> T-Shirt | J58: Central | K58: 26 | L58: 1 | M58: 26 | N58: Apple Pay | O58: Delivered | P58: DHL | Q58: =IF(AND(E58<>"", O58="Cancelled"), "Cancelled", "Active") -> Active | R58: =DATEDIF(AmazonSales[[#This Row],[Order Date]],AmazonSales[[#This Row],[Delivery Date]],"d") -> 2 | S58: =IF(AmazonSales[[#This Row],[Order Status]]="Cancelled",1,0) -> 0 | T58: =IF(AmazonSales[[#This Row],[Delivery Status]]="Delivered",1,0) -> 1 | U58: =IF(AmazonSales[[#This Row],[Delivery Status]]="Delivered",AmazonSales[[#This Row],[Total Amount]],0) -> 26 | V58: {=_xlfn.IFS(AND(AmazonSales[[#This Row],[Delivery Time]]=""),"",AND(AmazonSales[[#This Row],[Delivery Time]]<=2),"Fast",AND(AmazonSales[[#This Row],[Delivery Time]]>2),"Slow")} -> Fast | W58: =IF(AmazonSales[[#This Row],[Delivery performance]]="Fast",1,0) -> 1
A59: 1 | B59: ORD0058 | C59: 45143 | F59: CUST021 | G59: PROD009 | H59: =_xlfn.XLOOKUP(AmazonSales[[#This Row],[Product ID]],Product_table[Product ID],Product_table[Category]) -> Books | I59: =_xlfn.XLOOKUP(AmazonSales[[#This Row],[Product ID]],Product_table[Product ID],Product_table[Product Name]) -> Magazine | J59: North | K59: 11 | L59: 5 | M59: 55 | N59: Credit Card | O59: In Transit | P59: FedEx | Q59: =IF(AND(E59<>"", O59="Cancelled"), "Cancelled", "Active") -> Active | S59: =IF(AmazonSales[[#This Row],[Order Status]]="Cancelled",1,0) -> 0 | T59: =IF(AmazonSales[[#This Row],[Delivery Status]]="Delivered",1,0) -> 0 | U59: =IF(AmazonSales[[#This Row],[Delivery Status]]="Delivered",AmazonSales[[#This Row],[Total Amount]],0) -> 0 | V59: {=_xlfn.IFS(AND(AmazonSales[[#This Row],[Delivery Time]]=""),"",AND(AmazonSales[[#This Row],[Delivery Time]]<=2),"Fast",AND(AmazonSales[[#This Row],[Delivery Time]]>2),"Slow")} | W59: =IF(AmazonSales[[#This Row],[Delivery performance]]="Fast",1,0) -> 0
A60: 1 | B60: ORD0059 | C60: 44961 | E60: 45050 | F60: CUST003 | G60: PROD013 | H60: =_xlfn.XLOOKUP(AmazonSales[[#This Row],[Product ID]],Product_table[Product ID],Product_table[Category]) -> Home | I60: =_xlfn.XLOOKUP(AmazonSales[[#This Row],[Product ID]],Product_table[Product ID],Product_table[Product Name]) -> Vacuum Cleaner | J60: North | K60: 195 | L60: 4 | M60: 780 | N60: PayPal | O60: Cancelled | P60: FedEx | Q60: =IF(AND(E60<>"", O60="Cancelled"), "Cancelled", "Active") -> Cancelled | S60: =IF(AmazonSales[[#This Row],[Order Status]]="Cancelled",1,0) -> 1 | T60: =IF(AmazonSales[[#This Row],[Delivery Status]]="Delivered",1,0) -> 0 | U60: =IF(AmazonSales[[#This Row],[Delivery Status]]="Delivered",AmazonSales[[#This Row],[Total Amount]],0) -> 0 | V60: {=_xlfn.IFS(AND(AmazonSales[[#This Row],[Delivery Time]]=""),"",AND(AmazonSales[[#This Row],[Delivery Time]]<=2),"Fast",AND(AmazonSales[[#This Row],[Delivery Time]]>2),"Slow")} | W60: =IF(AmazonSales[[#This Row],[Delivery performance]]="Fast",1,0) -> 0
A61: 1 | B61: ORD0060 | C61: 45240 | E61: 45270 | F61: CUST019 | G61: PROD019 | H61: =_xlfn.XLOOKUP(AmazonSales[[#This Row],[Product ID]],Product_table[Product ID],Product_table[Category]) -> Fashion | I61: =_xlfn.XLOOKUP(AmazonSales[[#This Row],[Product ID]],Product_table[Product ID],Product_table[Product Name]) -> Formal Shirt | J61: West | K61: 44 | L61: 5 | M61: 220 | N61: Apple Pay | O61: Cancelled | P61: USPS | Q61: =IF(AND(E61<>"", O61="Cancelled"), "Cancelled", "Active") -> Cancelled | S61: =IF(AmazonSales[[#This Row],[Order Status]]="Cancelled",1,0) -> 1 | T61: =IF(AmazonSales[[#This Row],[Delivery Status]]="Delivered",1,0) -> 0 | U61: =IF(AmazonSales[[#This Row],[Delivery Status]]="Delivered",AmazonSales[[#This Row],[Total Amount]],0) -> 0 | V61: {=_xlfn.IFS(AND(AmazonSales[[#This Row],[Delivery Time]]=""),"",AND(AmazonSales[[#This Row],[Delivery Time]]<=2),"Fast",AND(AmazonSales[[#This Row],[Delivery Time]]>2),"Slow")} | W61: =IF(AmazonSales[[#This Row],[Delivery performance]]="Fast",1,0) -> 0
A62: 1 | B62: ORD0061 | C62: 45208 | F62: CUST035 | G62: PROD008 | H62: =_xlfn.XLOOKUP(AmazonSales[[#This Row],[Product ID]],Product_table[Product ID],Product_table[Category]) -> Books | I62: =_xlfn.XLOOKUP(AmazonSales[[#This Row],[Product ID]],Product_table[Product ID],Product_table[Product Name]) -> Textbook | J62: East | K62: 69 | L62: 4 | M62: 276 | N62: Debit Card | O62: In Transit | P62: DHL | Q62: =IF(AND(E62<>"", O62="Cancelled"), "Cancelled", "Active") -> Active | S62: =IF(AmazonSales[[#This Row],[Order Status]]="Cancelled",1,0) -> 0 | T62: =IF(AmazonSales[[#This Row],[Delivery Status]]="Delivered",1,0) -> 0 | U62: =IF(AmazonSales[[#This Row],[Delivery Status]]="Delivered",AmazonSales[[#This Row],[Total Amount]],0) -> 0 | V62: {=_xlfn.IFS(AND(AmazonSales[[#This Row],[Delivery Time]]=""),"",AND(AmazonSales[[#This Row],[Delivery Time]]<=2),"Fast",AND(AmazonSales[[#This Row],[Delivery Time]]>2),"Slow")} | W62: =IF(AmazonSales[[#This Row],[Delivery performance]]="Fast",1,0) -> 0
A63: 1 | B63: ORD0062 | C63: 45252 | D63: 45259 | F63: CUST022 | G63: PROD001 | H63: =_xlfn.XLOOKUP(AmazonSales[[#This Row],[Product ID]],Product_table[Product ID],Product_table[Category]) -> Electronics | I63: =_xlfn.XLOOKUP(AmazonSales[[#This Row],[Product ID]],Product_table[Product ID],Product_table[Product Name]) -> Smartphone | J63: North | K63: 815 | L63: 4 | M63: 3260 | N63: Credit Card | O63: Delivered | P63: USPS | Q63: =IF(AND(E63<>"", O63="Cancelled"), "Cancelled", "Active") -> Active | R63: =DATEDIF(AmazonSales[[#This Row],[Order Date]],AmazonSales[[#This Row],[Delivery Date]],"d") -> 7 | S63: =IF(AmazonSales[[#This Row],[Order Status]]="Cancelled",1,0) -> 0 | T63: =IF(AmazonSales[[#This Row],[Delivery Status]]="Delivered",1,0) -> 1 | U63: =IF(AmazonSales[[#This Row],[Delivery Status]]="Delivered",AmazonSales[[#This Row],[Total Amount]],0) -> 3260 | V63: {=_xlfn.IFS(AND(AmazonSales[[#This Row],[Delivery Time]]=""),"",AND(AmazonSales[[#This Row],[Delivery Time]]<=2),"Fast",AND(AmazonSales[[#This Row],[Delivery Time]]>2),"Slow")} -> Slow | W63: =IF(AmazonSales[[#This Row],[Delivery performance]]="Fast",1,0) -> 0
A64: 1 | B64: ORD0063 | C64: 44962 | F64: CUST004 | G64: PROD005 | H64: =_xlfn.XLOOKUP(AmazonSales[[#This Row],[Product ID]],Product_table[Product ID],Product_table[Category]) -> Fashion | I64: =_xlfn.XLOOKUP(AmazonSales[[#This Row],[Product ID]],Product_table[Product ID],Product_table[Product Name]) -> T-Shirt | J64: East | K64: 27 | L64: 1 | M64: 27 | N64: Debit Card | O64: In Transit | P64: Amazon Logistics | Q64: =IF(AND(E64<>"", O64="Cancelled"), "Cancelled", "Active") -> Active | S64: =IF(AmazonSales[[#This Row],[Order Status]]="Cancelled",1,0) -> 0 | T64: =IF(AmazonSales[[#This Row],[Delivery Status]]="Delivered",1,0) -> 0 | U64: =IF(AmazonSales[[#This Row],[Delivery Status]]="Delivered",AmazonSales[[#This Row],[Total Amount]],0) -> 0 | V64: {=_xlfn.IFS(AND(AmazonSales[[#This Row],[Delivery Time]]=""),"",AND(AmazonSales[[#This Row],[Delivery Time]]<=2),"Fast",AND(AmazonSales[[#This Row],[Delivery Time]]>2),"Slow")} | W64: =IF(AmazonSales[[#This Row],[Delivery performance]]="Fast",1,0) -> 0
A65: 1 | B65: ORD0064 | C65: 45261 | D65: 45289 | F65: CUST048 | G65: PROD003 | H65: =_xlfn.XLOOKUP(AmazonSales[[#This Row],[Product ID]],Product_table[Product ID],Product_table[Category]) -> Home | I65: =_xlfn.XLOOKUP(AmazonSales[[#This Row],[Product ID]],Product_table[Product ID],Product_table[Product Name]) -> Cookware Set | J65: West | K65: 139 | L65: 5 | M65: 695 | N65: Apple Pay | O65: Delivered | P65: USPS | Q65: =IF(AND(E65<>"", O65="Cancelled"), "Cancelled", "Active") -> Active | R65: =DATEDIF(AmazonSales[[#This Row],[Order Date]],AmazonSales[[#This Row],[Delivery Date]],"d") -> 28 | S65: =IF(AmazonSales[[#This Row],[Order Status]]="Cancelled",1,0) -> 0 | T65: =IF(AmazonSales[[#This Row],[Delivery Status]]="Delivered",1,0) -> 1 | U65: =IF(AmazonSales[[#This Row],[Delivery Status]]="Delivered",AmazonSales[[#This Row],[Total Amount]],0) -> 695 | V65: {=_xlfn.IFS(AND(AmazonSales[[#This Row],[Delivery Time]]=""),"",AND(AmazonSales[[#This Row],[Delivery Time]]<=2),"Fast",AND(AmazonSales[[#This Row],[Delivery Time]]>2),"Slow")} -> Slow | W65: =IF(AmazonSales[[#This Row],[Delivery performance]]="Fast",1,0) -> 0
A66: 1 | B66: ORD0065 | C66: 45217 | E66: 45219 | F66: CUST009 | G66: PROD008 | H66: =_xlfn.XLOOKUP(AmazonSales[[#This Row],[Product ID]],Product_table[Product ID],Product_table[Category]) -> Books | I66: =_xlfn.XLOOKUP(AmazonSales[[#This Row],[Product ID]],Product_table[Product ID],Product_table[Product Name]) -> Textbook | J66: South | K66: 69 | L66: 3 | M66: 207 | N66: PayPal | O66: Cancelled | P66: Amazon Logistics | Q66: =IF(AND(E66<>"", O66="Cancelled"), "Cancelled", "Active") -> Cancelled | S66: =IF(AmazonSales[[#This Row],[Order Status]]="Cancelled",1,0) -> 1 | T66: =IF(AmazonSales[[#This Row],[Delivery Status]]="Delivered",1,0) -> 0 | U66: =IF(AmazonSales[[#This Row],[Delivery Status]]="Delivered",AmazonSales[[#This Row],[Total Amount]],0) -> 0 | V66: {=_xlfn.IFS(AND(AmazonSales[[#This Row],[Delivery Time]]=""),"",AND(AmazonSales[[#This Row],[Delivery Time]]<=2),"Fast",AND(AmazonSales[[#This Row],[Delivery Time]]>2),"Slow")} | W66: =IF(AmazonSales[[#This Row],[Delivery performance]]="Fast",1,0) -> 0
A67: 1 | B67: ORD0066 | C67: 45066 | E67: 45067 | F67: CUST009 | G67: PROD019 | H67: =_xlfn.XLOOKUP(AmazonSales[[#This Row],[Product ID]],Product_table[Product ID],Product_table[Category]) -> Fashion | I67: =_xlfn.XLOOKUP(AmazonSales[[#This Row],[Product ID]],Product_table[Product ID],Product_table[Product Name]) -> Formal Shirt | J67: West | K67: 42 | L67: 1 | M67: 42 | N67: Apple Pay | O67: Cancelled | P67: DHL | Q67: =IF(AND(E67<>"", O67="Cancelled"), "Cancelled", "Active") -> Cancelled | S67: =IF(AmazonSales[[#This Row],[Order Status]]="Cancelled",1,0) -> 1 | T67: =IF(AmazonSales[[#This Row],[Delivery Status]]="Delivered",1,0) -> 0 | U67: =IF(AmazonSales[[#This Row],[Delivery Status]]="Delivered",AmazonSales[[#This Row],[Total Amount]],0) -> 0 | V67: {=_xlfn.IFS(AND(AmazonSales[[#This Row],[Delivery Time]]=""),"",AND(AmazonSales[[#This Row],[Delivery Time]]<=2),"Fast",AND(AmazonSales[[#This Row],[Delivery Time]]>2),"Slow")} | W67: =IF(AmazonSales[[#This Row],[Delivery performance]]="Fast",1,0) -> 0
A68: 1 | B68: ORD0067 | C68: 45135 | D68: 45137 | F68: CUST050 | G68: PROD007 | H68: =_xlfn.XLOOKUP(AmazonSales[[#This Row],[Product ID]],Product_table[Product ID],Product_table[Category]) -> Toys | I68: =_xlfn.XLOOKUP(AmazonSales[[#This Row],[Product ID]],Product_table[Product ID],Product_table[Product Name]) -> Puzzle | J68: North | K68: 31 | L68: 4 | M68: 124 | N68: Credit Card | O68: Delivered | P68: UPS | Q68: =IF(AND(E68<>"", O68="Cancelled"), "Cancelled", "Active") -> Active | R68: =DATEDIF(AmazonSales[[#This Row],[Order Date]],AmazonSales[[#This Row],[Delivery Date]],"d") -> 2 | S68: =IF(AmazonSales[[#This Row],[Order Status]]="Cancelled",1,0) -> 0 | T68: =IF(AmazonSales[[#This Row],[Delivery Status]]="Delivered",1,0) -> 1 | U68: =IF(AmazonSales[[#This Row],[Delivery Status]]="Delivered",AmazonSales[[#This Row],[Total Amount]],0) -> 124 | V68: {=_xlfn.IFS(AND(AmazonSales[[#This Row],[Delivery Time]]=""),"",AND(AmazonSales[[#This Row],[Delivery Time]]<=2),"Fast",AND(AmazonSales[[#This Row],[Delivery Time]]>2),"Slow")} -> Fast | W68: =IF(AmazonSales[[#This Row],[Delivery performance]]="Fast",1,0) -> 1
A69: 1 | B69: ORD0068 | C69: 45278 | F69: CUST045 | G69: PROD020 | H69: =_xlfn.XLOOKUP(AmazonSales[[#This Row],[Product ID]],Product_table[Product ID],Product_table[Category]) -> Electronics | I69: =_xlfn.XLOOKUP(AmazonSales[[#This Row],[Product ID]],Product_table[Product ID],Product_table[Product Name]) -> Bluetooth Speaker | J69: West | K69: 104 | L69: 3 | M69: 312 | N69: Credit Card | O69: In Transit | P69: UPS | Q69: =IF(AND(E69<>"", O69="Cancelled"), "Cancelled", "Active") -> Active | S69: =IF(AmazonSales[[#This Row],[Order Status]]="Cancelled",1,0) -> 0 | T69: =IF(AmazonSales[[#This Row],[Delivery Status]]="Delivered",1,0) -> 0 | U69: =IF(AmazonSales[[#This Row],[Delivery Status]]="Delivered",AmazonSales[[#This Row],[Total Amount]],0) -> 0 | V69: {=_xlfn.IFS(AND(AmazonSales[[#This Row],[Delivery Time]]=""),"",AND(AmazonSales[[#This Row],[Delivery Time]]<=2),"Fast",AND(AmazonSales[[#This Row],[Delivery Time]]>2),"Slow")} | W69: =IF(AmazonSales[[#This Row],[Delivery performance]]="Fast",1,0) -> 0
A70: 1 | B70: ORD0069 | C70: 44964 | E70: 45114 | F70: CUST044 | G70: PROD010 | H70: =_xlfn.XLOOKUP(AmazonSales[[#This Row],[Product ID]],Product_table[Product ID],Product_table[Category]) -> Fashion | I70: =_xlfn.XLOOKUP(AmazonSales[[#This Row],[Product ID]],Product_table[Product ID],Product_table[Product Name]) -> Jeans | J70: East | K70: 58 | L70: 2 | M70: 116 | N70: Apple Pay | O70: Cancelled | P70: USPS | Q70: =IF(AND(E70<>"", O70="Cancelled"), "Cancelled", "Active") -> Cancelled | S70: =IF(AmazonSales[[#This Row],[Order Status]]="Cancelled",1,0) -> 1 | T70: =IF(AmazonSales[[#This Row],[Delivery Status]]="Delivered",1,0) -> 0 | U70: =IF(AmazonSales[[#This Row],[Delivery Status]]="Delivered",AmazonSales[[#This Row],[Total Amount]],0) -> 0 | V70: {=_xlfn.IFS(AND(AmazonSales[[#This Row],[Delivery Time]]=""),"",AND(AmazonSales[[#This Row],[Delivery Time]]<=2),"Fast",AND(AmazonSales[[#This Row],[Delivery Time]]>2),"Slow")} | W70: =IF(AmazonSales[[#This Row],[Delivery performance]]="Fast",1,0) -> 0
A71: 1 | B71: ORD0070 | C71: 45179 | E71: 45209 | F71: CUST009 | G71: PROD004 | H71: =_xlfn.XLOOKUP(AmazonSales[[#This Row],[Product ID]],Product_table[Product ID],Product_table[Category]) -> Toys | I71: =_xlfn.XLOOKUP(AmazonSales[[#This Row],[Product ID]],Product_table[Product ID],Product_table[Product Name]) -> Leg Set | J71: West | K71: 62 | L71: 2 | M71: 124 | N71: Debit Card | O71: Cancelled | P71: DHL | Q71: =IF(AND(E71<>"", O71="Cancelled"), "Cancelled", "Active") -> Cancelled | S71: =IF(AmazonSales[[#This Row],[Order Status]]="Cancelled",1,0) -> 1 | T71: =IF(AmazonSales[[#This Row],[Delivery Status]]="Delivered",1,0) -> 0 | U71: =IF(AmazonSales[[#This Row],[Delivery Status]]="Delivered",AmazonSales[[#This Row],[Total Amount]],0) -> 0 | V71: {=_xlfn.IFS(AND(AmazonSales[[#This Row],[Delivery Time]]=""),"",AND(AmazonSales[[#This Row],[Delivery Time]]<=2),"Fast",AND(AmazonSales[[#This Row],[Delivery Time]]>2),"Slow")} | W71: =IF(AmazonSales[[#This Row],[Delivery performance]]="Fast",1,0) -> 0
A72: 1 | B72: ORD0071 | C72: 45278 | D72: 45285 | F72: CUST006 | G72: PROD019 | H72: =_xlfn.XLOOKUP(AmazonSales[[#This Row],[Product ID]],Product_table[Product ID],Product_table[Category]) -> Fashion | I72: =_xlfn.XLOOKUP(AmazonSales[[#This Row],[Product ID]],Product_table[Product ID],Product_table[Product Name]) -> Formal Shirt | J72: East | K72: 43 | L72: 1 | M72: 43 | N72: Credit Card | O72: Delivered | P72: Amazon Logistics | Q72: =IF(AND(E72<>"", O72="Cancelled"), "Cancelled", "Active") -> Active | R72: =DATEDIF(AmazonSales[[#This Row],[Order Date]],AmazonSales[[#This Row],[Delivery Date]],"d") -> 7 | S72: =IF(AmazonSales[[#This Row],[Order Status]]="Cancelled",1,0) -> 0 | T72: =IF(AmazonSales[[#This Row],[Delivery Status]]="Delivered",1,0) -> 1 | U72: =IF(AmazonSales[[#This Row],[Delivery Status]]="Delivered",AmazonSales[[#This Row],[Total Amount]],0) -> 43 | V72: {=_xlfn.IFS(AND(AmazonSales[[#This Row],[Delivery Time]]=""),"",AND(AmazonSales[[#This Row],[Delivery Time]]<=2),"Fast",AND(AmazonSales[[#This Row],[Delivery Time]]>2),"Slow")} -> Slow | W72: =IF(AmazonSales[[#This Row],[Delivery performance]]="Fast",1,0) -> 0
A73: 1 | B73: ORD0072 | C73: 45110 | F73: CUST022 | G73: PROD004 | H73: =_xlfn.XLOOKUP(AmazonSales[[#This Row],[Product ID]],Product_table[Product ID],Product_table[Category]) -> Toys | I73: =_xlfn.XLOOKUP(AmazonSales[[#This Row],[Product ID]],Product_table[Product ID],Product_table[Product Name]) -> Leg Set | J73: East | K73: 62 | L73: 4 | M73: 248 | N73: Debit Card | O73: In Transit | P73: Amazon Logistics | Q73: =IF(AND(E73<>"", O73="Cancelled"), "Cancelled", "Active") -> Active | S73: =IF(AmazonSales[[#This Row],[Order Status]]="Cancelled",1,0) -> 0 | T73: =IF(AmazonSales[[#This Row],[Delivery Status]]="Delivered",1,0) -> 0 | U73: =IF(AmazonSales[[#This Row],[Delivery Status]]="Delivered",AmazonSales[[#This Row],[Total Amount]],0) -> 0 | V73: {=_xlfn.IFS(AND(AmazonSales[[#This Row],[Delivery Time]]=""),"",AND(AmazonSales[[#This Row],[Delivery Time]]<=2),"Fast",AND(AmazonSales[[#This Row],[Delivery Time]]>2),"Slow")} | W73: =IF(AmazonSales[[#This Row],[Delivery performance]]="Fast",1,0) -> 0
A74: 1 | B74: ORD0073 | C74: 45129 | E74: 45132 | F74: CUST028 | G74: PROD006 | H74: =_xlfn.XLOOKUP(AmazonSales[[#This Row],[Product ID]],Product_table[Product ID],Product_table[Category]) -> Fashion | I74: =_xlfn.XLOOKUP(AmazonSales[[#This Row],[Product ID]],Product_table[Product ID],Product_table[Product Name]) -> Shoes | J74: North | K74: 95 | L74: 2 | M74: 190 | N74: PayPal | O74: Cancelled | P74: UPS | Q74: =IF(AND(E74<>"", O74="Cancelled"), "Cancelled", "Active") -> Cancelled | S74: =IF(AmazonSales[[#This Row],[Order Status]]="Cancelled",1,0) -> 1 | T74: =IF(AmazonSales[[#This Row],[Delivery Status]]="Delivered",1,0) -> 0 | U74: =IF(AmazonSales[[#This Row],[Delivery Status]]="Delivered",AmazonSales[[#This Row],[Total Amount]],0) -> 0 | V74: {=_xlfn.IFS(AND(AmazonSales[[#This Row],[Delivery Time]]=""),"",AND(AmazonSales[[#This Row],[Delivery Time]]<=2),"Fast",AND(AmazonSales[[#This Row],[Delivery Time]]>2),"Slow")} | W74: =IF(AmazonSales[[#This Row],[Delivery performance]]="Fast",1,0) -> 0
A75: 1 | B75: ORD0074 | C75: 44944 | D75: 44950 | F75: CUST016 | G75: PROD021 | H75: =_xlfn.XLOOKUP(AmazonSales[[#This Row],[Product ID]],Product_table[Product ID],Product_table[Category]) -> Home | I75: =_xlfn.XLOOKUP(AmazonSales[[#This Row],[Product ID]],Product_table[Product ID],Product_table[Product Name]) -> Wall Clock | J75: Central | K75: 36 | L75: 4 | M75: 144 | N75: Apple Pay | O75: Delivered | P75: FedEx | Q75: =IF(AND(E75<>"", O75="Cancelled"), "Cancelled", "Active") -> Active | R75: =DATEDIF(AmazonSales[[#This Row],[Order Date]],AmazonSales[[#This Row],[Delivery Date]],"d") -> 6 | S75: =IF(AmazonSales[[#This Row],[Order Status]]="Cancelled",1,0) -> 0 | T75: =IF(AmazonSales[[#This Row],[Delivery Status]]="Delivered",1,0) -> 1 | U75: =IF(AmazonSales[[#This Row],[Delivery Status]]="Delivered",AmazonSales[[#This Row],[Total Amount]],0) -> 144 | V75: {=_xlfn.IFS(AND(AmazonSales[[#This Row],[Delivery Time]]=""),"",AND(AmazonSales[[#This Row],[Delivery Time]]<=2),"Fast",AND(AmazonSales[[#This Row],[Delivery Time]]>2),"Slow")} -> Slow | W75: =IF(AmazonSales[[#This Row],[Delivery performance]]="Fast",1,0) -> 0
A76: 1 | B76: ORD0075 | C76: 45070 | F76: CUST042 | G76: PROD017 | H76: =_xlfn.XLOOKUP(AmazonSales[[#This Row],[Product ID]],Product_table[Product ID],Product_table[Category]) -> Electronics | I76: =_xlfn.XLOOKUP(AmazonSales[[#This Row],[Product ID]],Product_table[Product ID],Product_table[Product Name]) -> Gaming Mouse | J76: East | K76: 73 | L76: 5 | M76: 365 | N76: Apple Pay | O76: In Transit | P76: DHL | Q76: =IF(AND(E76<>"", O76="Cancelled"), "Cancelled", "Active") -> Active | S76: =IF(AmazonSales[[#This Row],[Order Status]]="Cancelled",1,0) -> 0 | T76: =IF(AmazonSales[[#This Row],[Delivery Status]]="Delivered",1,0) -> 0 | U76: =IF(AmazonSales[[#This Row],[Delivery Status]]="Delivered",AmazonSales[[#This Row],[Total Amount]],0) -> 0 | V76: {=_xlfn.IFS(AND(AmazonSales[[#This Row],[Delivery Time]]=""),"",AND(AmazonSales[[#This Row],[Delivery Time]]<=2),"Fast",AND(AmazonSales[[#This Row],[Delivery Time]]>2),"Slow")} | W76: =IF(AmazonSales[[#This Row],[Delivery performance]]="Fast",1,0) -> 0
A77: 1 | B77: ORD0076 | C77: 45172 | D77: 45178 | F77: CUST023 | G77: PROD019 | H77: =_xlfn.XLOOKUP(AmazonSales[[#This Row],[Product ID]],Product_table[Product ID],Product_table[Category]) -> Fashion | I77: =_xlfn.XLOOKUP(AmazonSales[[#This Row],[Product ID]],Product_table[Product ID],Product_table[Product Name]) -> Formal Shirt | J77: North | K77: 43 | L77: 4 | M77: 172 | N77: Debit Card | O77: Delivered | P77: DHL | Q77: =IF(AND(E77<>"", O77="Cancelled"), "Cancelled", "Active") -> Active | R77: =DATEDIF(AmazonSales[[#This Row],[Order Date]],AmazonSales[[#This Row],[Delivery Date]],"d") -> 6 | S77: =IF(AmazonSales[[#This Row],[Order Status]]="Cancelled",1,0) -> 0 | T77: =IF(AmazonSales[[#This Row],[Delivery Status]]="Delivered",1,0) -> 1 | U77: =IF(AmazonSales[[#This Row],[Delivery Status]]="Delivered",AmazonSales[[#This Row],[Total Amount]],0) -> 172 | V77: {=_xlfn.IFS(AND(AmazonSales[[#This Row],[Delivery Time]]=""),"",AND(AmazonSales[[#This Row],[Delivery Time]]<=2),"Fast",AND(AmazonSales[[#This Row],[Delivery Time]]>2),"Slow")} -> Slow | W77: =IF(AmazonSales[[#This Row],[Delivery performance]]="Fast",1,0) -> 0
A78: 1 | B78: ORD0077 | C78: 45232 | D78: 45234 | F78: CUST004 | G78: PROD016 | H78: =_xlfn.XLOOKUP(AmazonSales[[#This Row],[Product ID]],Product_table[Product ID],Product_table[Category]) -> Home | I78: =_xlfn.XLOOKUP(AmazonSales[[#This Row],[Product ID]],Product_table[Product ID],Product_table[Product Name]) -> Cookware Set Pro | J78: West | K78: 214 | L78: 5 | M78: 1070 | N78: Debit Card | O78: Delivered | P78: UPS | Q78: =IF(AND(E78<>"", O78="Cancelled"), "Cancelled", "Active") -> Active | R78: =DATEDIF(AmazonSales[[#This Row],[Order Date]],AmazonSales[[#This Row],[Delivery Date]],"d") -> 2 | S78: =IF(AmazonSales[[#This Row],[Order Status]]="Cancelled",1,0) -> 0 | T78: =IF(AmazonSales[[#This Row],[Delivery Status]]="Delivered",1,0) -> 1 | U78: =IF(AmazonSales[[#This Row],[Delivery Status]]="Delivered",AmazonSales[[#This Row],[Total Amount]],0) -> 1070 | V78: {=_xlfn.IFS(AND(AmazonSales[[#This Row],[Delivery Time]]=""),"",AND(AmazonSales[[#This Row],[Delivery Time]]<=2),"Fast",AND(AmazonSales[[#This Row],[Delivery Time]]>2),"Slow")} -> Fast | W78: =IF(AmazonSales[[#This Row],[Delivery performance]]="Fast",1,0) -> 1
A79: 1 | B79: ORD0078 | C79: 44997 | E79: 45089 | F79: CUST048 | G79: PROD002 | H79: =_xlfn.XLOOKUP(AmazonSales[[#This Row],[Product ID]],Product_table[Product ID],Product_table[Category]) -> Toys | I79: =_xlfn.XLOOKUP(AmazonSales[[#This Row],[Product ID]],Product_table[Product ID],Product_table[Product Name]) -> Action Figure | J79: Central | K79: 42 | L79: 2 | M79: 84 | N79: Apple Pay | O79: Cancelled | P79: UPS | Q79: =IF(AND(E79<>"", O79="Cancelled"), "Cancelled", "Active") -> Cancelled | S79: =IF(AmazonSales[[#This Row],[Order Status]]="Cancelled",1,0) -> 1 | T79: =IF(AmazonSales[[#This Row],[Delivery Status]]="Delivered",1,0) -> 0 | U79: =IF(AmazonSales[[#This Row],[Delivery Status]]="Delivered",AmazonSales[[#This Row],[Total Amount]],0) -> 0 | V79: {=_xlfn.IFS(AND(AmazonSales[[#This Row],[Delivery Time]]=""),"",AND(AmazonSales[[#This Row],[Delivery Time]]<=2),"Fast",AND(AmazonSales[[#This Row],[Delivery Time]]>2),"Slow")} | W79: =IF(AmazonSales[[#This Row],[Delivery performance]]="Fast",1,0) -> 0
A80: 1 | B80: ORD0079 | C80: 44930 | F80: CUST048 | G80: PROD012 | H80: =_xlfn.XLOOKUP(AmazonSales[[#This Row],[Product ID]],Product_table[Product ID],Product_table[Category]) -> Home | I80: =_xlfn.XLOOKUP(AmazonSales[[#This Row],[Product ID]],Product_table[Product ID],Product_table[Product Name]) -> Lamp | J80: North | K80: 46 | L80: 1 | M80: 46 | N80: Amazon Pay | O80: In Transit | P80: UPS | Q80: =IF(AND(E80<>"", O80="Cancelled"), "Cancelled", "Active") -> Active | S80: =IF(AmazonSales[[#This Row],[Order Status]]="Cancelled",1,0) -> 0 | T80: =IF(AmazonSales[[#This Row],[Delivery Status]]="Delivered",1,0) -> 0 | U80: =IF(AmazonSales[[#This Row],[Delivery Status]]="Delivered",AmazonSales[[#This Row],[Total Amount]],0) -> 0 | V80: {=_xlfn.IFS(AND(AmazonSales[[#This Row],[Delivery Time]]=""),"",AND(AmazonSales[[#This Row],[Delivery Time]]<=2),"Fast",AND(AmazonSales[[#This Row],[Delivery Time]]>2),"Slow")} | W80: =IF(AmazonSales[[#This Row],[Delivery performance]]="Fast",1,0) -> 0
A81: 1 | B81: ORD0080 | C81: 45215 | D81: 45218 | F81: CUST032 | G81: PROD018 | H81: =_xlfn.XLOOKUP(AmazonSales[[#This Row],[Product ID]],Product_table[Product ID],Product_table[Category]) -> Toys | I81: =_xlfn.XLOOKUP(AmazonSales[[#This Row],[Product ID]],Product_table[Product ID],Product_table[Product Name]) -> Doll House | J81: East | K81: 95 | L81: 4 | M81: 380 | N81: Credit Card | O81: Delivered | P81: UPS | Q81: =IF(AND(E81<>"", O81="Cancelled"), "Cancelled", "Active") -> Active | R81: =DATEDIF(AmazonSales[[#This Row],[Order Date]],AmazonSales[[#This Row],[Delivery Date]],"d") -> 3 | S81: =IF(AmazonSales[[#This Row],[Order Status]]="Cancelled",1,0) -> 0 | T81: =IF(AmazonSales[[#This Row],[Delivery Status]]="Delivered",1,0) -> 1 | U81: =IF(AmazonSales[[#This Row],[Delivery Status]]="Delivered",AmazonSales[[#This Row],[Total Amount]],0) -> 380 | V81: {=_xlfn.IFS(AND(AmazonSales[[#This Row],[Delivery Time]]=""),"",AND(AmazonSales[[#This Row],[Delivery Time]]<=2),"Fast",AND(AmazonSales[[#This Row],[Delivery Time]]>2),"Slow")} -> Slow | W81: =IF(AmazonSales[[#This Row],[Delivery performance]]="Fast",1,0) -> 0
A82: 1 | B82: ORD0081 | C82: 45057 | F82: CUST001 | G82: PROD011 | H82: =_xlfn.XLOOKUP(AmazonSales[[#This Row],[Product ID]],Product_table[Product ID],Product_table[Category]) -> Electronics | I82: =_xlfn.XLOOKUP(AmazonSales[[#This Row],[Product ID]],Product_table[Product ID],Product_table[Product Name]) -> Headphones | J82: West | K82: 174 | L82: 2 | M82: 348 | N82: PayPal | O82: In Transit | P82: UPS | Q82: =IF(AND(E82<>"", O82="Cancelled"), "Cancelled", "Active") -> Active | S82: =IF(AmazonSales[[#This Row],[Order Status]]="Cancelled",1,0) -> 0 | T82: =IF(AmazonSales[[#This Row],[Delivery Status]]="Delivered",1,0) -> 0 | U82: =IF(AmazonSales[[#This Row],[Delivery Status]]="Delivered",AmazonSales[[#This Row],[Total Amount]],0) -> 0 | V82: {=_xlfn.IFS(AND(AmazonSales[[#This Row],[Delivery Time]]=""),"",AND(AmazonSales[[#This Row],[Delivery Time]]<=2),"Fast",AND(AmazonSales[[#This Row],[Delivery Time]]>2),"Slow")} | W82: =IF(AmazonSales[[#This Row],[Delivery performance]]="Fast",1,0) -> 0
A83: 1 | B83: ORD0082 | C83: 45092 | E83: 45095 | F83: CUST046 | G83: PROD005 | H83: =_xlfn.XLOOKUP(AmazonSales[[#This Row],[Product ID]],Product_table[Product ID],Product_table[Category]) -> Fashion | I83: =_xlfn.XLOOKUP(AmazonSales[[#This Row],[Product ID]],Product_table[Product ID],Product_table[Product Name]) -> T-Shirt | J83: North | K83: 27 | L83: 5 | M83: 135 | N83: Credit Card | O83: Cancelled | P83: Amazon Logistics | Q83: =IF(AND(E83<>"", O83="Cancelled"), "Cancelled", "Active") -> Cancelled | S83: =IF(AmazonSales[[#This Row],[Order Status]]="Cancelled",1,0) -> 1 | T83: =IF(AmazonSales[[#This Row],[Delivery Status]]="Delivered",1,0) -> 0 | U83: =IF(AmazonSales[[#This Row],[Delivery Status]]="Delivered",AmazonSales[[#This Row],[Total Amount]],0) -> 0 | V83: {=_xlfn.IFS(AND(AmazonSales[[#This Row],[Delivery Time]]=""),"",AND(AmazonSales[[#This Row],[Delivery Time]]<=2),"Fast",AND(AmazonSales[[#This Row],[Delivery Time]]>2),"Slow")} | W83: =IF(AmazonSales[[#This Row],[Delivery performance]]="Fast",1,0) -> 0
A84: 1 | B84: ORD0083 | C84: 45227 | D84: 45229 | F84: CUST021 | G84: PROD005 | H84: =_xlfn.XLOOKUP(AmazonSales[[#This Row],[Product ID]],Product_table[Product ID],Product_table[Category]) -> Fashion | I84: =_xlfn.XLOOKUP(AmazonSales[[#This Row],[Product ID]],Product_table[Product ID],Product_table[Product Name]) -> T-Shirt | J84: South | K84: 27 | L84: 4 | M84: 108 | N84: PayPal | O84: Delivered | P84: USPS | Q84: =IF(AND(E84<>"", O84="Cancelled"), "Cancelled", "Active") -> Active | R84: =DATEDIF(AmazonSales[[#This Row],[Order Date]],AmazonSales[[#This Row],[Delivery Date]],"d") -> 2 | S84: =IF(AmazonSales[[#This Row],[Order Status]]="Cancelled",1,0) -> 0 | T84: =IF(AmazonSales[[#This Row],[Delivery Status]]="Delivered",1,0) -> 1 | U84: =IF(AmazonSales[[#This Row],[Delivery Status]]="Delivered",AmazonSales[[#This Row],[Total Amount]],0) -> 108 | V84: {=_xlfn.IFS(AND(AmazonSales[[#This Row],[Delivery Time]]=""),"",AND(AmazonSales[[#This Row],[Delivery Time]]<=2),"Fast",AND(AmazonSales[[#This Row],[Delivery Time]]>2),"Slow")} -> Fast | W84: =IF(AmazonSales[[#This Row],[Delivery performance]]="Fast",1,0) -> 1
A85: 1 | B85: ORD0084 | C85: 44938 | F85: CUST015 | G85: PROD022 | H85: =_xlfn.XLOOKUP(AmazonSales[[#This Row],[Product ID]],Product_table[Product ID],Product_table[Category]) -> Fashion | I85: =_xlfn.XLOOKUP(AmazonSales[[#This Row],[Product ID]],Product_table[Product ID],Product_table[Product Name]) -> Backpack | J85: South | K85: 65 | L85: 2 | M85: 130 | N85: PayPal | O85: In Transit | P85: DHL | Q85: =IF(AND(E85<>"", O85="Cancelled"), "Cancelled", "Active") -> Active | S85: =IF(AmazonSales[[#This Row],[Order Status]]="Cancelled",1,0) -> 0 | T85: =IF(AmazonSales[[#This Row],[Delivery Status]]="Delivered",1,0) -> 0 | U85: =IF(AmazonSales[[#This Row],[Delivery Status]]="Delivered",AmazonSales[[#This Row],[Total Amount]],0) -> 0 | V85: {=_xlfn.IFS(AND(AmazonSales[[#This Row],[Delivery Time]]=""),"",AND(AmazonSales[[#This Row],[Delivery Time]]<=2),"Fast",AND(AmazonSales[[#This Row],[Delivery Time]]>2),"Slow")} | W85: =IF(AmazonSales[[#This Row],[Delivery performance]]="Fast",1,0) -> 0
A86: 1 | B86: ORD0085 | C86: 45110 | F86: CUST045 | G86: PROD019 | H86: =_xlfn.XLOOKUP(AmazonSales[[#This Row],[Product ID]],Product_table[Product ID],Product_table[Category]) -> Fashion | I86: =_xlfn.XLOOKUP(AmazonSales[[#This Row],[Product ID]],Product_table[Product ID],Product_table[Product Name]) -> Formal Shirt | J86: East | K86: 43 | L86: 5 | M86: 215 | N86: Debit Card | O86: In Transit | P86: DHL | Q86: =IF(AND(E86<>"", O86="Cancelled"), "Cancelled", "Active") -> Active | S86: =IF(AmazonSales[[#This Row],[Order Status]]="Cancelled",1,0) -> 0 | T86: =IF(AmazonSales[[#This Row],[Delivery Status]]="Delivered",1,0) -> 0 | U86: =IF(AmazonSales[[#This Row],[Delivery Status]]="Delivered",AmazonSales[[#This Row],[Total Amount]],0) -> 0 | V86: {=_xlfn.IFS(AND(AmazonSales[[#This Row],[Delivery Time]]=""),"",AND(AmazonSales[[#This Row],[Delivery Time]]<=2),"Fast",AND(AmazonSales[[#This Row],[Delivery Time]]>2),"Slow")} | W86: =IF(AmazonSales[[#This Row],[Delivery performance]]="Fast",1,0) -> 0
A87: 1 | B87: ORD0086 | C87: 45210 | F87: CUST007 | G87: PROD016 | H87: =_xlfn.XLOOKUP(AmazonSales[[#This Row],[Product ID]],Product_table[Product ID],Product_table[Category]) -> Home | I87: =_xlfn.XLOOKUP(AmazonSales[[#This Row],[Product ID]],Product_table[Product ID],Product_table[Product Name]) -> Cookware Set Pro | J87: West | K87: 210 | L87: 1 | M87: 210 | N87: PayPal | O87: In Transit | P87: UPS | Q87: =IF(AND(E87<>"", O87="Cancelled"), "Cancelled", "Active") -> Active | S87: =IF(AmazonSales[[#This Row],[Order Status]]="Cancelled",1,0) -> 0 | T87: =IF(AmazonSales[[#This Row],[Delivery Status]]="Delivered",1,0) -> 0 | U87: =IF(AmazonSales[[#This Row],[Delivery Status]]="Delivered",AmazonSales[[#This Row],[Total Amount]],0) -> 0 | V87: {=_xlfn.IFS(AND(AmazonSales[[#This Row],[Delivery Time]]=""),"",AND(AmazonSales[[#This Row],[Delivery Time]]<=2),"Fast",AND(AmazonSales[[#This Row],[Delivery Time]]>2),"Slow")} | W87: =IF(AmazonSales[[#This Row],[Delivery performance]]="Fast",1,0) -> 0
A88: 1 | B88: ORD0087 | C88: 45252 | F88: CUST043 | G88: PROD021 | H88: =_xlfn.XLOOKUP(AmazonSales[[#This Row],[Product ID]],Product_table[Product ID],Product_table[Category]) -> Home | I88: =_xlfn.XLOOKUP(AmazonSales[[#This Row],[Product ID]],Product_table[Product ID],Product_table[Product Name]) -> Wall Clock | J88: South | K88: 37 | L88: 3 | M88: 111 | N88: Credit Card | O88: In Transit | P88: UPS | Q88: =IF(AND(E88<>"", O88="Cancelled"), "Cancelled", "Active") -> Active | S88: =IF(AmazonSales[[#This Row],[Order Status]]="Cancelled",1,0) -> 0 | T88: =IF(AmazonSales[[#This Row],[Delivery Status]]="Delivered",1,0) -> 0 | U88: =IF(AmazonSales[[#This Row],[Delivery Status]]="Delivered",AmazonSales[[#This Row],[Total Amount]],0) -> 0 | V88: {=_xlfn.IFS(AND(AmazonSales[[#This Row],[Delivery Time]]=""),"",AND(AmazonSales[[#This Row],[Delivery Time]]<=2),"Fast",AND(AmazonSales[[#This Row],[Delivery Time]]>2),"Slow")} | W88: =IF(AmazonSales[[#This Row],[Delivery performance]]="Fast",1,0) -> 0
A89: 1 | B89: ORD0088 | C89: 45143 | F89: CUST007 | G89: PROD001 | H89: =_xlfn.XLOOKUP(AmazonSales[[#This Row],[Product ID]],Product_table[Product ID],Product_table[Category]) -> Electronics | I89: =_xlfn.XLOOKUP(AmazonSales[[#This Row],[Product ID]],Product_table[Product ID],Product_table[Product Name]) -> Smartphone | J89: South | K89: 788 | L89: 4 | M89: 3152 | N89: Debit Card | O89: In Transit | P89: Amazon Logistics | Q89: =IF(AND(E89<>"", O89="Cancelled"), "Cancelled", "Active") -> Active | S89: =IF(AmazonSales[[#This Row],[Order Status]]="Cancelled",1,0) -> 0 | T89: =IF(AmazonSales[[#This Row],[Delivery Status]]="Delivered",1,0) -> 0 | U89: =IF(AmazonSales[[#This Row],[Delivery Status]]="Delivered",AmazonSales[[#This Row],[Total Amount]],0) -> 0 | V89: {=_xlfn.IFS(AND(AmazonSales[[#This Row],[Delivery Time]]=""),"",AND(AmazonSales[[#This Row],[Delivery Time]]<=2),"Fast",AND(AmazonSales[[#This Row],[Delivery Time]]>2),"Slow")} | W89: =IF(AmazonSales[[#This Row],[Delivery performance]]="Fast",1,0) -> 0
A90: 1 | B90: ORD0089 | C90: 45120 | F90: CUST007 | G90: PROD016 | H90: =_xlfn.XLOOKUP(AmazonSales[[#This Row],[Product ID]],Product_table[Product ID],Product_table[Category]) -> Home | I90: =_xlfn.XLOOKUP(AmazonSales[[#This Row],[Product ID]],Product_table[Product ID],Product_table[Product Name]) -> Cookware Set Pro | J90: West | K90: 217 | L90: 5 | M90: 1085 | N90: Debit Card | O90: In Transit | P90: FedEx | Q90: =IF(AND(E90<>"", O90="Cancelled"), "Cancelled", "Active") -> Active | S90: =IF(AmazonSales[[#This Row],[Order Status]]="Cancelled",1,0) -> 0 | T90: =IF(AmazonSales[[#This Row],[Delivery Status]]="Delivered",1,0) -> 0 | U90: =IF(AmazonSales[[#This Row],[Delivery Status]]="Delivered",AmazonSales[[#This Row],[Total Amount]],0) -> 0 | V90: {=_xlfn.IFS(AND(AmazonSales[[#This Row],[Delivery Time]]=""),"",AND(AmazonSales[[#This Row],[Delivery Time]]<=2),"Fast",AND(AmazonSales[[#This Row],[Delivery Time]]>2),"Slow")} | W90: =IF(AmazonSales[[#This Row],[Delivery performance]]="Fast",1,0) -> 0
A91: 1 | B91: ORD0090 | C91: 44944 | F91: CUST007 | G91: PROD003 | H91: =_xlfn.XLOOKUP(AmazonSales[[#This Row],[Product ID]],Product_table[Product ID],Product_table[Category]) -> Home | I91: =_xlfn.XLOOKUP(AmazonSales[[#This Row],[Product ID]],Product_table[Product ID],Product_table[Product Name]) -> Cookware Set | J91: West | K91: 138 | L91: 4 | M91: 552 | N91: Credit Card | O91: In Transit | P91: FedEx | Q91: =IF(AND(E91<>"", O91="Cancelled"), "Cancelled", "Active") -> Active | S91: =IF(AmazonSales[[#This Row],[Order Status]]="Cancelled",1,0) -> 0 | T91: =IF(AmazonSales[[#This Row],[Delivery Status]]="Delivered",1,0) -> 0 | U91: =IF(AmazonSales[[#This Row],[Delivery Status]]="Delivered",AmazonSales[[#This Row],[Total Amount]],0) -> 0 | V91: {=_xlfn.IFS(AND(AmazonSales[[#This Row],[Delivery Time]]=""),"",AND(AmazonSales[[#This Row],[Delivery Time]]<=2),"Fast",AND(AmazonSales[[#This Row],[Delivery Time]]>2),"Slow")} | W91: =IF(AmazonSales[[#This Row],[Delivery performance]]="Fast",1,0) -> 0
A92: 1 | B92: ORD0091 | C92: 45100 | D92: 45106 | F92: CUST031 | G92: PROD001 | H92: =_xlfn.XLOOKUP(AmazonSales[[#This Row],[Product ID]],Product_table[Product ID],Product_table[Category]) -> Electronics | I92: =_xlfn.XLOOKUP(AmazonSales[[#This Row],[Product ID]],Product_table[Product ID],Product_table[Product Name]) -> Smartphone | J92: Central | K92: 803 | L92: 2 | M92: 1606 | N92: Apple Pay | O92: Delivered | P92: FedEx | Q92: =IF(AND(E92<>"", O92="Cancelled"), "Cancelled", "Active") -> Active | R92: =DATEDIF(AmazonSales[[#This Row],[Order Date]],AmazonSales[[#This Row],[Delivery Date]],"d") -> 6 | S92: =IF(AmazonSales[[#This Row],[Order Status]]="Cancelled",1,0) -> 0 | T92: =IF(AmazonSales[[#This Row],[Delivery Status]]="Delivered",1,0) -> 1 | U92: =IF(AmazonSales[[#This Row],[Delivery Status]]="Delivered",AmazonSales[[#This Row],[Total Amount]],0) -> 1606 | V92: {=_xlfn.IFS(AND(AmazonSales[[#This Row],[Delivery Time]]=""),"",AND(AmazonSales[[#This Row],[Delivery Time]]<=2),"Fast",AND(AmazonSales[[#This Row],[Delivery Time]]>2),"Slow")} -> Slow | W92: =IF(AmazonSales[[#This Row],[Delivery performance]]="Fast",1,0) -> 0
A93: 1 | B93: ORD0092 | C93: 44978 | E93: 44982 | F93: CUST013 | G93: PROD014 | H93: =_xlfn.XLOOKUP(AmazonSales[[#This Row],[Product ID]],Product_table[Product ID],Product_table[Category]) -> Electronics | I93: =_xlfn.XLOOKUP(AmazonSales[[#This Row],[Product ID]],Product_table[Product ID],Product_table[Product Name]) -> Smartwatch | J93: North | K93: 248 | L93: 5 | M93: 1240 | N93: PayPal | O93: Cancelled | P93: UPS | Q93: =IF(AND(E93<>"", O93="Cancelled"), "Cancelled", "Active") -> Cancelled | S93: =IF(AmazonSales[[#This Row],[Order Status]]="Cancelled",1,0) -> 1 | T93: =IF(AmazonSales[[#This Row],[Delivery Status]]="Delivered",1,0) -> 0 | U93: =IF(AmazonSales[[#This Row],[Delivery Status]]="Delivered",AmazonSales[[#This Row],[Total Amount]],0) -> 0 | V93: {=_xlfn.IFS(AND(AmazonSales[[#This Row],[Delivery Time]]=""),"",AND(AmazonSales[[#This Row],[Delivery Time]]<=2),"Fast",AND(AmazonSales[[#This Row],[Delivery Time]]>2),"Slow")} | W93: =IF(AmazonSales[[#This Row],[Delivery performance]]="Fast",1,0) -> 0
A94: 1 | B94: ORD0093 | C94: 44976 | D94: 44978 | F94: CUST036 | G94: PROD016 | H94: =_xlfn.XLOOKUP(AmazonSales[[#This Row],[Product ID]],Product_table[Product ID],Product_table[Category]) -> Home | I94: =_xlfn.XLOOKUP(AmazonSales[[#This Row],[Product ID]],Product_table[Product ID],Product_table[Product Name]) -> Cookware Set Pro | J94: East | K94: 210 | L94: 3 | M94: 630 | N94: Apple Pay | O94: Delivered | P94: DHL | Q94: =IF(AND(E94<>"", O94="Cancelled"), "Cancelled", "Active") -> Active | R94: =DATEDIF(AmazonSales[[#This Row],[Order Date]],AmazonSales[[#This Row],[Delivery Date]],"d") -> 2 | S94: =IF(AmazonSales[[#This Row],[Order Status]]="Cancelled",1,0) -> 0 | T94: =IF(AmazonSales[[#This Row],[Delivery Status]]="Delivered",1,0) -> 1 | U94: =IF(AmazonSales[[#This Row],[Delivery Status]]="Delivered",AmazonSales[[#This Row],[Total Amount]],0) -> 630 | V94: {=_xlfn.IFS(AND(AmazonSales[[#This Row],[Delivery Time]]=""),"",AND(AmazonSales[[#This Row],[Delivery Time]]<=2),"Fast",AND(AmazonSales[[#This Row],[Delivery Time]]>2),"Slow")} -> Fast | W94: =IF(AmazonSales[[#This Row],[Delivery performance]]="Fast",1,0) -> 1
A95: 1 | B95: ORD0094 | C95: 45201 | E95: 45272 | F95: CUST013 | G95: PROD004 | H95: =_xlfn.XLOOKUP(AmazonSales[[#This Row],[Product ID]],Product_table[Product ID],Product_table[Category]) -> Toys | I95: =_xlfn.XLOOKUP(AmazonSales[[#This Row],[Product ID]],Product_table[Product ID],Product_table[Product Name]) -> Leg Set | J95: North | K95: 62 | L95: 2 | M95: 124 | N95: Credit Card | O95: Cancelled | P95: FedEx | Q95: =IF(AND(E95<>"", O95="Cancelled"), "Cancelled", "Active") -> Cancelled | S95: =IF(AmazonSales[[#This Row],[Order Status]]="Cancelled",1,0) -> 1 | T95: =IF(AmazonSales[[#This Row],[Delivery Status]]="Delivered",1,0) -> 0 | U95: =IF(AmazonSales[[#This Row],[Delivery Status]]="Delivered",AmazonSales[[#This Row],[Total Amount]],0) -> 0 | V95: {=_xlfn.IFS(AND(AmazonSales[[#This Row],[Delivery Time]]=""),"",AND(AmazonSales[[#This Row],[Delivery Time]]<=2),"Fast",AND(AmazonSales[[#This Row],[Delivery Time]]>2),"Slow")} | W95: =IF(AmazonSales[[#This Row],[Delivery performance]]="Fast",1,0) -> 0
A96: 1 | B96: ORD0095 | C96: 45084 | E96: 45089 | F96: CUST043 | G96: PROD009 | H96: =_xlfn.XLOOKUP(AmazonSales[[#This Row],[Product ID]],Product_table[Product ID],Product_table[Category]) -> Books | I96: =_xlfn.XLOOKUP(AmazonSales[[#This Row],[Product ID]],Product_table[Product ID],Product_table[Product Name]) -> Magazine | J96: South | K96: 11 | L96: 5 | M96: 55 | N96: Debit Card | O96: Cancelled | P96: Amazon Logistics | Q96: =IF(AND(E96<>"", O96="Cancelled"), "Cancelled", "Active") -> Cancelled | S96: =IF(AmazonSales[[#This Row],[Order Status]]="Cancelled",1,0) -> 1 | T96: =IF(AmazonSales[[#This Row],[Delivery Status]]="Delivered",1,0) -> 0 | U96: =IF(AmazonSales[[#This Row],[Delivery Status]]="Delivered",AmazonSales[[#This Row],[Total Amount]],0) -> 0 | V96: {=_xlfn.IFS(AND(AmazonSales[[#This Row],[Delivery Time]]=""),"",AND(AmazonSales[[#This Row],[Delivery Time]]<=2),"Fast",AND(AmazonSales[[#This Row],[Delivery Time]]>2),"Slow")} | W96: =IF(AmazonSales[[#This Row],[Delivery performance]]="Fast",1,0) -> 0
A97: 1 | B97: ORD0096 | C97: 45116 | D97: 45119 | F97: CUST017 | G97: PROD015 | H97: =_xlfn.XLOOKUP(AmazonSales[[#This Row],[Product ID]],Product_table[Product ID],Product_table[Category]) -> Books | I97: =_xlfn.XLOOKUP(AmazonSales[[#This Row],[Product ID]],Product_table[Product ID],Product_table[Product Name]) -> Novel | J97: North | K97: 21 | L97: 2 | M97: 42 | N97: Amazon Pay | O97: Delivered | P97: UPS | Q97: =IF(AND(E97<>"", O97="Cancelled"), "Cancelled", "Active") -> Active | R97: =DATEDIF(AmazonSales[[#This Row],[Order Date]],AmazonSales[[#This Row],[Delivery Date]],"d") -> 3 | S97: =IF(AmazonSales[[#This Row],[Order Status]]="Cancelled",1,0) -> 0 | T97: =IF(AmazonSales[[#This Row],[Delivery Status]]="Delivered",1,0) -> 1 | U97: =IF(AmazonSales[[#This Row],[Delivery Status]]="Delivered",AmazonSales[[#This Row],[Total Amount]],0) -> 42 | V97: {=_xlfn.IFS(AND(AmazonSales[[#This Row],[Delivery Time]]=""),"",AND(AmazonSales[[#This Row],[Delivery Time]]<=2),"Fast",AND(AmazonSales[[#This Row],[Delivery Time]]>2),"Slow")} -> Slow | W97: =IF(AmazonSales[[#This Row],[Delivery performance]]="Fast",1,0) -> 0
A98: 1 | B98: ORD0097 | C98: 45283 | D98: 45286 | F98: CUST023 | G98: PROD018 | H98: =_xlfn.XLOOKUP(AmazonSales[[#This Row],[Product ID]],Product_table[Product ID],Product_table[Category]) -> Toys | I98: =_xlfn.XLOOKUP(AmazonSales[[#This Row],[Product ID]],Product_table[Product ID],Product_table[Product Name]) -> Doll House | J98: West | K98: 95 | L98: 5 | M98: 475 | N98: Amazon Pay | O98: Delivered | P98: Amazon Logistics | Q98: =IF(AND(E98<>"", O98="Cancelled"), "Cancelled", "Active") -> Active | R98: =DATEDIF(AmazonSales[[#This Row],[Order Date]],AmazonSales[[#This Row],[Delivery Date]],"d") -> 3 | S98: =IF(AmazonSales[[#This Row],[Order Status]]="Cancelled",1,0) -> 0 | T98: =IF(AmazonSales[[#This Row],[Delivery Status]]="Delivered",1,0) -> 1 | U98: =IF(AmazonSales[[#This Row],[Delivery Status]]="Delivered",AmazonSales[[#This Row],[Total Amount]],0) -> 475 | V98: {=_xlfn.IFS(AND(AmazonSales[[#This Row],[Delivery Time]]=""),"",AND(AmazonSales[[#This Row],[Delivery Time]]<=2),"Fast",AND(AmazonSales[[#This Row],[Delivery Time]]>2),"Slow")} -> Slow | W98: =IF(AmazonSales[[#This Row],[Delivery performance]]="Fast",1,0) -> 0
A99: 1 | B99: ORD0098 | C99: 45194 | D99: 45199 | F99: CUST044 | G99: PROD016 | H99: =_xlfn.XLOOKUP(AmazonSales[[#This Row],[Product ID]],Product_table[Product ID],Product_table[Category]) -> Home | I99: =_xlfn.XLOOKUP(AmazonSales[[#This Row],[Product ID]],Product_table[Product ID],Product_table[Product Name]) -> Cookware Set Pro | J99: South | K99: 215 | L99: 2 | M99: 430 | N99: PayPal | O99: Delivered | P99: Amazon Logistics | Q99: =IF(AND(E99<>"", O99="Cancelled"), "Cancelled", "Active") -> Active | R99: =DATEDIF(AmazonSales[[#This Row],[Order Date]],AmazonSales[[#This Row],[Delivery Date]],"d") -> 5 | S99: =IF(AmazonSales[[#This Row],[Order Status]]="Cancelled",1,0) -> 0 | T99: =IF(AmazonSales[[#This Row],[Delivery Status]]="Delivered",1,0) -> 1 | U99: =IF(AmazonSales[[#This Row],[Delivery Status]]="Delivered",AmazonSales[[#This Row],[Total Amount]],0) -> 430 | V99: {=_xlfn.IFS(AND(AmazonSales[[#This Row],[Delivery Time]]=""),"",AND(AmazonSales[[#This Row],[Delivery Time]]<=2),"Fast",AND(AmazonSales[[#This Row],[Delivery Time]]>2),"Slow")} -> Slow | W99: =IF(AmazonSales[[#This Row],[Delivery performance]]="Fast",1,0) -> 0
A100: 1 | B100: ORD0099 | C100: 44944 | E100: 44950 | F100: CUST034 | G100: PROD019 | H100: =_xlfn.XLOOKUP(AmazonSales[[#This Row],[Product ID]],Product_table[Product ID],Product_table[Category]) -> Fashion | I100: =_xlfn.XLOOKUP(AmazonSales[[#This Row],[Product ID]],Product_table[Product ID],Product_table[Product Name]) -> Formal Shirt | J100: West | K100: 43 | L100: 5 | M100: 215 | N100: Credit Card | O100: Cancelled | P100: UPS | Q100: =IF(AND(E100<>"", O100="Cancelled"), "Cancelled", "Active") -> Cancelled | S100: =IF(AmazonSales[[#This Row],[Order Status]]="Cancelled",1,0) -> 1 | T100: =IF(AmazonSales[[#This Row],[Delivery Status]]="Delivered",1,0) -> 0 | U100: =IF(AmazonSales[[#This Row],[Delivery Status]]="Delivered",AmazonSales[[#This Row],[Total Amount]],0) -> 0 | V100: {=_xlfn.IFS(AND(AmazonSales[[#This Row],[Delivery Time]]=""),"",AND(AmazonSales[[#This Row],[Delivery Time]]<=2),"Fast",AND(AmazonSales[[#This Row],[Delivery Time]]>2),"Slow")} | W100: =IF(AmazonSales[[#This Row],[Delivery performance]]="Fast",1,0) -> 0
...

Sheet Task2
A1: Creating Pivot Tables
A2: ● Show Total Sales Amount by Region and Product Category
A3: ● Count of Orders by Delivery Status
A4: ● Average Delivery Time = Delivery Date – Order Date
A5: ● Add filter for Payment Method and Product Category
B7: Payment Method | C7: (All)
B8: Delivery Status | C8: (All)
B9: Product Category | C9: (All)
C11: Total sales amount | D11: Count of Orders | E11: Average of Delivery Time
B12: Central | C12: 5456 | D12: 14 | E12: 4.2
B13: East | C13: 3635 | D13: 18 | E13: 8.125
B14: North | C14: 10491 | D14: 25 | E14: 3.625
B15: South | C15: 7317 | D15: 20 | E15: 6.8333333
B16: West | C16: 8359 | D16: 23 | E16: 6.8571429
B17: Grand Total | C17: 35258 | D17: 100 | E17: 6

Sheet Task3
A1: Order ID | B1: Order Date | C1: Delivery Date | D1: Cancel Date | E1: Customer ID | F1: Customer Name | G1: Product ID | H1: Region | I1: Sale Price/Unit | J1: Quantity | K1: Total Amount | L1: Payment Method | M1: Delivery Status | N1: Fulfillment Partner | O1: Delivery Performance
A2: ORD0001 | B2: 45291 | D2: 45323 | E2: CUST021 | F2: =_xlfn.XLOOKUP(AmazonSales5[[#This Row],[Customer ID]],customerdata[Customer ID],customerdata[Customer Name],"Not Found") -> Zoe Mitchell | G2: PROD012 | H2: North | I2: 44 | J2: 1 | K2: 44 | L2: Apple Pay | M2: Cancelled | N2: DHL | O2: =IFERROR(IF(AmazonSales5[[#This Row],[Delivery Date]]="", "", IF(AmazonSales5[[#This Row],[Delivery Date]]-AmazonSales5[[#This Row],[Order Date]]<=2,"Fast","Slow")),"")
A3: ORD0002 | B3: 44979 | C3: 44981 | E3: CUST029 | F3: =_xlfn.XLOOKUP(AmazonSales5[[#This Row],[Customer ID]],customerdata[Customer ID],customerdata[Customer Name],"Not Found") -> Ava White | G3: PROD018 | H3: East | I3: 96 | J3: 4 | K3: 384 | L3: Credit Card | M3: Delivered | N3: DHL | O3: =IFERROR(IF(AmazonSales5[[#This Row],[Delivery Date]]="", "", IF(AmazonSales5[[#This Row],[Delivery Date]]-AmazonSales5[[#This Row],[Order Date]]<=2,"Fast","Slow")),"") -> Fast
A4: ORD0003 | B4: 45240 | E4: CUST021 | F4: =_xlfn.XLOOKUP(AmazonSales5[[#This Row],[Customer ID]],customerdata[Customer ID],customerdata[Customer Name],"Not Found") -> Zoe Mitchell | G4: PROD013 | H4: South | I4: 194 | J4: 4 | K4: 776 | L4: Credit Card | M4: In Transit | N4: USPS | O4: =IFERROR(IF(AmazonSales5[[#This Row],[Delivery Date]]="", "", IF(AmazonSales5[[#This Row],[Delivery Date]]-AmazonSales5[[#This Row],[Order Date]]<=2,"Fast","Slow")),"")
A5: ORD0004 | B5: 45051 | D5: 45235 | E5: CUST044 | F5: =_xlfn.XLOOKUP(AmazonSales5[[#This Row],[Customer ID]],customerdata[Customer ID],customerdata[Customer Name],"Not Found") -> Grace Ward | G5: PROD013 | H5: North | I5: 196 | J5: 3 | K5: 588 | L5: PayPal | M5: Cancelled | N5: UPS | O5: =IFERROR(IF(AmazonSales5[[#This Row],[Delivery Date]]="", "", IF(AmazonSales5[[#This Row],[Delivery Date]]-AmazonSales5[[#This Row],[Order Date]]<=2,"Fast","Slow")),"")
A6: ORD0005 | B6: 44959 | C6: 45048 | E6: CUST027 | F6: =_xlfn.XLOOKUP(AmazonSales5[[#This Row],[Customer ID]],customerdata[Customer ID],customerdata[Customer Name],"Not Found") -> Hazel Brooks | G6: PROD010 | H6: North | I6: 59 | J6: 1 | K6: 59 | L6: PayPal | M6: Delivered | N6: Amazon Logistics | O6: =IFERROR(IF(AmazonSales5[[#This Row],[Delivery Date]]="", "", IF(AmazonSales5[[#This Row],[Delivery Date]]-AmazonSales5[[#This Row],[Order Date]]<=2,"Fast","Slow")),"") -> Slow
A7: ORD0006 | B7: 44937 | D7: 44968 | E7: CUST009 | F7: =_xlfn.XLOOKUP(AmazonSales5[[#This Row],[Customer ID]],customerdata[Customer ID],customerdata[Customer Name],"Not Found") -> Jackson Allen | G7: PROD010 | H7: North | I7: 58 | J7: 4 | K7: 232 | L7: Amazon Pay | M7: Cancelled | N7: DHL | O7: =IFERROR(IF(AmazonSales5[[#This Row],[Delivery Date]]="", "", IF(AmazonSales5[[#This Row],[Delivery Date]]-AmazonSales5[[#This Row],[Order Date]]<=2,"Fast","Slow")),"")
A8: ORD0007 | B8: 45152 | D8: 45156 | E8: CUST042 | F8: =_xlfn.XLOOKUP(AmazonSales5[[#This Row],[Customer ID]],customerdata[Customer ID],customerdata[Customer Name],"Not Found") -> Noah Wilson | G8: PROD020 | H8: Central | I8: 105 | J8: 3 | K8: 315 | L8: Debit Card | M8: Cancelled | N8: DHL | O8: =IFERROR(IF(AmazonSales5[[#This Row],[Delivery Date]]="", "", IF(AmazonSales5[[#This Row],[Delivery Date]]-AmazonSales5[[#This Row],[Order Date]]<=2,"Fast","Slow")),"")
A9: ORD0008 | B9: 44930 | D9: 45081 | E9: CUST019 | F9: =_xlfn.XLOOKUP(AmazonSales5[[#This Row],[Customer ID]],customerdata[Customer ID],customerdata[Customer Name],"Not Found") -> Ava Robinson | G9: PROD021 | H9: West | I9: 37 | J9: 5 | K9: 185 | L9: PayPal | M9: Cancelled | N9: DHL | O9: =IFERROR(IF(AmazonSales5[[#This Row],[Delivery Date]]="", "", IF(AmazonSales5[[#This Row],[Delivery Date]]-AmazonSales5[[#This Row],[Order Date]]<=2,"Fast","Slow")),"")
A10: ORD0009 | B10: 45128 | E10: CUST013 | F10: =_xlfn.XLOOKUP(AmazonSales5[[#This Row],[Customer ID]],customerdata[Customer ID],customerdata[Customer Name],"Not Found") -> Olivia Martinez | G10: PROD019 | H10: Central | I10: 44 | J10: 2 | K10: 88 | L10: Credit Card | M10: In Transit | N10: Amazon Logistics | O10: =IFERROR(IF(AmazonSales5[[#This Row],[Delivery Date]]="", "", IF(AmazonSales5[[#This Row],[Delivery Date]]-AmazonSales5[[#This Row],[Order Date]]<=2,"Fast","Slow")),"")
A11: ORD0010 | B11: 45289 | E11: CUST019 | F11: =_xlfn.XLOOKUP(AmazonSales5[[#This Row],[Customer ID]],customerdata[Customer ID],customerdata[Customer Name],"Not Found") -> Ava Robinson | G11: PROD003 | H11: South | I11: 141 | J11: 4 | K11: 564 | L11: Debit Card | M11: In Transit | N11: DHL | O11: =IFERROR(IF(AmazonSales5[[#This Row],[Delivery Date]]="", "", IF(AmazonSales5[[#This Row],[Delivery Date]]-AmazonSales5[[#This Row],[Order Date]]<=2,"Fast","Slow")),"")
A12: ORD0011 | B12: 45021 | D12: 45143 | E12: CUST046 | F12: =_xlfn.XLOOKUP(AmazonSales5[[#This Row],[Customer ID]],customerdata[Customer ID],customerdata[Customer Name],"Not Found") -> Emily Johnson | G12: PROD014 | H12: South | I12: 249 | J12: 1 | K12: 249 | L12: Amazon Pay | M12: Cancelled | N12: USPS | O12: =IFERROR(IF(AmazonSales5[[#This Row],[Delivery Date]]="", "", IF(AmazonSales5[[#This Row],[Delivery Date]]-AmazonSales5[[#This Row],[Order Date]]<=2,"Fast","Slow")),"")
A13: ORD0012 | B13: 45132 | E13: CUST045 | F13: =_xlfn.XLOOKUP(AmazonSales5[[#This Row],[Customer ID]],customerdata[Customer ID],customerdata[Customer Name],"Not Found") -> Emily Johnson | G13: PROD014 | H13: Central | I13: 247 | J13: 3 | K13: 741 | L13: Amazon Pay | M13: In Transit | N13: FedEx | O13: =IFERROR(IF(AmazonSales5[[#This Row],[Delivery Date]]="", "", IF(AmazonSales5[[#This Row],[Delivery Date]]-AmazonSales5[[#This Row],[Order Date]]<=2,"Fast","Slow")),"")
A14: ORD0013 | B14: 44982 | D14: 44985 | E14: CUST023 | F14: =_xlfn.XLOOKUP(AmazonSales5[[#This Row],[Customer ID]],customerdata[Customer ID],customerdata[Customer Name],"Not Found") -> Charlotte Reed | G14: PROD006 | H14: Central | I14: 96 | J14: 1 | K14: 96 | L14: Apple Pay | M14: Cancelled | N14: Amazon Logistics | O14: =IFERROR(IF(AmazonSales5[[#This Row],[Delivery Date]]="", "", IF(AmazonSales5[[#This Row],[Delivery Date]]-AmazonSales5[[#This Row],[Order Date]]<=2,"Fast","Slow")),"")
A15: ORD0014 | B15: 44981 | D15: 44982 | E15: CUST033 | F15: =_xlfn.XLOOKUP(AmazonSales5[[#This Row],[Customer ID]],customerdata[Customer ID],customerdata[Customer Name],"Not Found") -> Hazel Rivera | G15: PROD017 | H15: West | I15: 74 | J15: 5 | K15: 370 | L15: Apple Pay | M15: Cancelled | N15: Amazon Logistics | O15: =IFERROR(IF(AmazonSales5[[#This Row],[Delivery Date]]="", "", IF(AmazonSales5[[#This Row],[Delivery Date]]-AmazonSales5[[#This Row],[Order Date]]<=2,"Fast","Slow")),"")
A16: ORD0015 | B16: 45164 | D16: 45171 | E16: CUST033 | F16: =_xlfn.XLOOKUP(AmazonSales5[[#This Row],[Customer ID]],customerdata[Customer ID],customerdata[Customer Name],"Not Found") -> Hazel Rivera | G16: PROD005 | H16: South | I16: 27 | J16: 1 | K16: 27 | L16: Credit Card | M16: Cancelled | N16: Amazon Logistics | O16: =IFERROR(IF(AmazonSales5[[#This Row],[Delivery Date]]="", "", IF(AmazonSales5[[#This Row],[Delivery Date]]-AmazonSales5[[#This Row],[Order Date]]<=2,"Fast","Slow")),"")
A17: ORD0016 | B17: 44970 | E17: CUST047 | F17: =_xlfn.XLOOKUP(AmazonSales5[[#This Row],[Customer ID]],customerdata[Customer ID],customerdata[Customer Name],"Not Found") -> Scarlett Murphy | G17: PROD005 | H17: South | I17: 27 | J17: 3 | K17: 81 | L17: Debit Card | M17: In Transit | N17: Amazon Logistics | O17: =IFERROR(IF(AmazonSales5[[#This Row],[Delivery Date]]="", "", IF(AmazonSales5[[#This Row],[Delivery Date]]-AmazonSales5[[#This Row],[Order Date]]<=2,"Fast","Slow")),"")
A18: ORD0017 | B18: 45105 | C18: 44933 | E18: CUST045 | F18: =_xlfn.XLOOKUP(AmazonSales5[[#This Row],[Customer ID]],customerdata[Customer ID],customerdata[Customer Name],"Not Found") -> Emily Johnson | G18: PROD015 | H18: East | I18: 21 | J18: 3 | K18: 63 | L18: Credit Card | M18: Delivered | N18: DHL | O18: =IFERROR(IF(AmazonSales5[[#This Row],[Delivery Date]]="", "", IF(AmazonSales5[[#This Row],[Delivery Date]]-AmazonSales5[[#This Row],[Order Date]]<=2,"Fast","Slow")),"") -> Fast
A19: ORD0018 | B19: 45258 | E19: CUST011 | F19: =_xlfn.XLOOKUP(AmazonSales5[[#This Row],[Customer ID]],customerdata[Customer ID],customerdata[Customer Name],"Not Found") -> Mason Hall | G19: PROD008 | H19: West | I19: 70 | J19: 5 | K19: 350 | L19: PayPal | M19: In Transit | N19: Amazon Logistics | O19: =IFERROR(IF(AmazonSales5[[#This Row],[Delivery Date]]="", "", IF(AmazonSales5[[#This Row],[Delivery Date]]-AmazonSales5[[#This Row],[Order Date]]<=2,"Fast","Slow")),"")
A20: ORD0019 | B20: 45163 | E20: CUST041 | F20: =_xlfn.XLOOKUP(AmazonSales5[[#This Row],[Customer ID]],customerdata[Customer ID],customerdata[Customer Name],"Not Found") -> Jacob Price | G20: PROD006 | H20: South | I20: 94 | J20: 4 | K20: 376 | L20: Credit Card | M20: In Transit | N20: USPS | O20: =IFERROR(IF(AmazonSales5[[#This Row],[Delivery Date]]="", "", IF(AmazonSales5[[#This Row],[Delivery Date]]-AmazonSales5[[#This Row],[Order Date]]<=2,"Fast","Slow")),"")
A21: ORD0020 | B21: 45264 | E21: CUST025 | F21: =_xlfn.XLOOKUP(AmazonSales5[[#This Row],[Customer ID]],customerdata[Customer ID],customerdata[Customer Name],"Not Found") -> Emma King | G21: PROD001 | H21: North | I21: 813 | J21: 2 | K21: 1626 | L21: Credit Card | M21: In Transit | N21: FedEx | O21: =IFERROR(IF(AmazonSales5[[#This Row],[Delivery Date]]="", "", IF(AmazonSales5[[#This Row],[Delivery Date]]-AmazonSales5[[#This Row],[Order Date]]<=2,"Fast","Slow")),"")
A22: ORD0021 | B22: 44967 | E22: CUST013 | F22: =_xlfn.XLOOKUP(AmazonSales5[[#This Row],[Customer ID]],customerdata[Customer ID],customerdata[Customer Name],"Not Found") -> Olivia Martinez | G22: PROD015 | H22: Central | I22: 21 | J22: 4 | K22: 84 | L22: PayPal | M22: In Transit | N22: Amazon Logistics | O22: =IFERROR(IF(AmazonSales5[[#This Row],[Delivery Date]]="", "", IF(AmazonSales5[[#This Row],[Delivery Date]]-AmazonSales5[[#This Row],[Order Date]]<=2,"Fast","Slow")),"")
A23: ORD0022 | B23: 45180 | E23: CUST023 | F23: =_xlfn.XLOOKUP(AmazonSales5[[#This Row],[Customer ID]],customerdata[Customer ID],customerdata[Customer Name],"Not Found") -> Charlotte Reed | G23: PROD012 | H23: West | I23: 46 | J23: 5 | K23: 230 | L23: PayPal | M23: In Transit | N23: USPS | O23: =IFERROR(IF(AmazonSales5[[#This Row],[Delivery Date]]="", "", IF(AmazonSales5[[#This Row],[Delivery Date]]-AmazonSales5[[#This Row],[Order Date]]<=2,"Fast","Slow")),"")
A24: ORD0023 | B24: 44970 | D24: 44971 | E24: CUST016 | F24: =_xlfn.XLOOKUP(AmazonSales5[[#This Row],[Customer ID]],customerdata[Customer ID],customerdata[Customer Name],"Not Found") -> Elijah Lewis | G24: PROD010 | H24: West | I24: 58 | J24: 3 | K24: 174 | L24: Amazon Pay | M24: Cancelled | N24: Amazon Logistics | O24: =IFERROR(IF(AmazonSales5[[#This Row],[Delivery Date]]="", "", IF(AmazonSales5[[#This Row],[Delivery Date]]-AmazonSales5[[#This Row],[Order Date]]<=2,"Fast","Slow")),"")
A25: ORD0024 | B25: 45232 | C25: 45057 | E25: CUST028 | F25: =_xlfn.XLOOKUP(AmazonSales5[[#This Row],[Customer ID]],customerdata[Customer ID],customerdata[Customer Name],"Not Found") -> Lily Bennett | G25: PROD006 | H25: West | I25: 96 | J25: 5 | K25: 480 | L25: Amazon Pay | M25: Delivered | N25: Amazon Logistics | O25: =IFERROR(IF(AmazonSales5[[#This Row],[Delivery Date]]="", "", IF(AmazonSales5[[#This Row],[Delivery Date]]-AmazonSales5[[#This Row],[Order Date]]<=2,"Fast","Slow")),"") -> Fast
A26: ORD0025 | B26: 45074 | C26: 45076 | E26: CUST040 | F26: =_xlfn.XLOOKUP(AmazonSales5[[#This Row],[Customer ID]],customerdata[Customer ID],customerdata[Customer Name],"Not Found") -> Benjamin Clark | G26: PROD002 | H26: South | I26: 43 | J26: 1 | K26: 43 | L26: Debit Card | M26: Delivered | N26: Amazon Logistics | O26: =IFERROR(IF(AmazonSales5[[#This Row],[Delivery Date]]="", "", IF(AmazonSales5[[#This Row],[Delivery Date]]-AmazonSales5[[#This Row],[Order Date]]<=2,"Fast","Slow")),"") -> Fast
A27: ORD0026 | B27: 45214 | C27: 45220 | E27: CUST027 | F27: =_xlfn.XLOOKUP(AmazonSales5[[#This Row],[Customer ID]],customerdata[Customer ID],customerdata[Customer Name],"Not Found") -> Hazel Brooks | G27: PROD022 | H27: South | I27: 64 | J27: 4 | K27: 256 | L27: Debit Card | M27: Delivered | N27: USPS | O27: =IFERROR(IF(AmazonSales5[[#This Row],[Delivery Date]]="", "", IF(AmazonSales5[[#This Row],[Delivery Date]]-AmazonSales5[[#This Row],[Order Date]]<=2,"Fast","Slow")),"") -> Slow
A28: ORD0027 | B28: 44942 | E28: CUST018 | F28: =_xlfn.XLOOKUP(AmazonSales5[[#This Row],[Customer ID]],customerdata[Customer ID],customerdata[Customer Name],"Not Found") -> Grace Scott | G28: PROD008 | H28: South | I28: 70 | J28: 2 | K28: 140 | L28: Amazon Pay | M28: In Transit | N28: Amazon Logistics | O28: =IFERROR(IF(AmazonSales5[[#This Row],[Delivery Date]]="", "", IF(AmazonSales5[[#This Row],[Delivery Date]]-AmazonSales5[[#This Row],[Order Date]]<=2,"Fast","Slow")),"")
A29: ORD0028 | B29: 45179 | E29: CUST018 | F29: =_xlfn.XLOOKUP(AmazonSales5[[#This Row],[Customer ID]],customerdata[Customer ID],customerdata[Customer Name],"Not Found") -> Grace Scott | G29: PROD018 | H29: Central | I29: 97 | J29: 3 | K29: 291 | L29: Credit Card | M29: In Transit | N29: Amazon Logistics | O29: =IFERROR(IF(AmazonSales5[[#This Row],[Delivery Date]]="", "", IF(AmazonSales5[[#This Row],[Delivery Date]]-AmazonSales5[[#This Row],[Order Date]]<=2,"Fast","Slow")),"")
A30: ORD0029 | B30: 45117 | D30: 45209 | E30: CUST007 | F30: =_xlfn.XLOOKUP(AmazonSales5[[#This Row],[Customer ID]],customerdata[Customer ID],customerdata[Customer Name],"Not Found") -> Liam Walker | G30: PROD021 | H30: East | I30: 37 | J30: 3 | K30: 111 | L30: Apple Pay | M30: Cancelled | N30: DHL | O30: =IFERROR(IF(AmazonSales5[[#This Row],[Delivery Date]]="", "", IF(AmazonSales5[[#This Row],[Delivery Date]]-AmazonSales5[[#This Row],[Order Date]]<=2,"Fast","Slow")),"")
A31: ORD0030 | B31: 44971 | E31: CUST008 | F31: =_xlfn.XLOOKUP(AmazonSales5[[#This Row],[Customer ID]],customerdata[Customer ID],customerdata[Customer Name],"Not Found") -> Harper Young | G31: PROD008 | H31: North | I31: 69 | J31: 5 | K31: 345 | L31: Amazon Pay | M31: In Transit | N31: Amazon Logistics | O31: =IFERROR(IF(AmazonSales5[[#This Row],[Delivery Date]]="", "", IF(AmazonSales5[[#This Row],[Delivery Date]]-AmazonSales5[[#This Row],[Order Date]]<=2,"Fast","Slow")),"")
A32: ORD0031 | B32: 45011 | E32: CUST014 | F32: =_xlfn.XLOOKUP(AmazonSales5[[#This Row],[Customer ID]],customerdata[Customer ID],customerdata[Customer Name],"Not Found") -> Harper Young | G32: PROD002 | H32: North | I32: 42 | J32: 5 | K32: 210 | L32: Amazon Pay | M32: In Transit | N32: UPS | O32: =IFERROR(IF(AmazonSales5[[#This Row],[Delivery Date]]="", "", IF(AmazonSales5[[#This Row],[Delivery Date]]-AmazonSales5[[#This Row],[Order Date]]<=2,"Fast","Slow")),"")
A33: ORD0032 | B33: 45092 | D33: 45099 | E33: CUST037 | F33: =_xlfn.XLOOKUP(AmazonSales5[[#This Row],[Customer ID]],customerdata[Customer ID],customerdata[Customer Name],"Not Found") -> Emily Johnson | G33: PROD009 | H33: East | I33: 11 | J33: 5 | K33: 55 | L33: Debit Card | M33: Cancelled | N33: FedEx | O33: =IFERROR(IF(AmazonSales5[[#This Row],[Delivery Date]]="", "", IF(AmazonSales5[[#This Row],[Delivery Date]]-AmazonSales5[[#This Row],[Order Date]]<=2,"Fast","Slow")),"")
A34: ORD0033 | B34: 45068 | C34: 45069 | E34: CUST016 | F34: =_xlfn.XLOOKUP(AmazonSales5[[#This Row],[Customer ID]],customerdata[Customer ID],customerdata[Customer Name],"Not Found") -> Elijah Lewis | G34: PROD005 | H34: South | I34: 27 | J34: 2 | K34: 54 | L34: Apple Pay | M34: Delivered | N34: USPS | O34: =IFERROR(IF(AmazonSales5[[#This Row],[Delivery Date]]="", "", IF(AmazonSales5[[#This Row],[Delivery Date]]-AmazonSales5[[#This Row],[Order Date]]<=2,"Fast","Slow")),"") -> Fast
A35: ORD0034 | B35: 45250 | E35: CUST025 | F35: =_xlfn.XLOOKUP(AmazonSales5[[#This Row],[Customer ID]],customerdata[Customer ID],customerdata[Customer Name],"Not Found") -> Emma King | G35: PROD015 | H35: South | I35: 21 | J35: 1 | K35: 21 | L35: Amazon Pay | M35: In Transit | N35: DHL | O35: =IFERROR(IF(AmazonSales5[[#This Row],[Delivery Date]]="", "", IF(AmazonSales5[[#This Row],[Delivery Date]]-AmazonSales5[[#This Row],[Order Date]]<=2,"Fast","Slow")),"")
A36: ORD0035 | B36: 44938 | C36: 45286 | E36: CUST032 | F36: =_xlfn.XLOOKUP(AmazonSales5[[#This Row],[Customer ID]],customerdata[Customer ID],customerdata[Customer Name],"Not Found") -> Luke Gray | G36: PROD011 | H36: South | I36: 172 | J36: 1 | K36: 172 | L36: PayPal | M36: Delivered | N36: USPS | O36: =IFERROR(IF(AmazonSales5[[#This Row],[Delivery Date]]="", "", IF(AmazonSales5[[#This Row],[Delivery Date]]-AmazonSales5[[#This Row],[Order Date]]<=2,"Fast","Slow")),"") -> Slow
A37: ORD0036 | B37: 45130 | E37: CUST014 | F37: =_xlfn.XLOOKUP(AmazonSales5[[#This Row],[Customer ID]],customerdata[Customer ID],customerdata[Customer Name],"Not Found") -> Harper Young | G37: PROD016 | H37: North | I37: 212 | J37: 3 | K37: 636 | L37: Amazon Pay | M37: In Transit | N37: UPS | O37: =IFERROR(IF(AmazonSales5[[#This Row],[Delivery Date]]="", "", IF(AmazonSales5[[#This Row],[Delivery Date]]-AmazonSales5[[#This Row],[Order Date]]<=2,"Fast","Slow")),"")
A38: ORD0037 | B38: 45216 | C38: 45221 | E38: CUST044 | F38: =_xlfn.XLOOKUP(AmazonSales5[[#This Row],[Customer ID]],customerdata[Customer ID],customerdata[Customer Name],"Not Found") -> Grace Ward | G38: PROD002 | H38: East | I38: 41 | J38: 4 | K38: 164 | L38: Credit Card | M38: Delivered | N38: Amazon Logistics | O38: =IFERROR(IF(AmazonSales5[[#This Row],[Delivery Date]]="", "", IF(AmazonSales5[[#This Row],[Delivery Date]]-AmazonSales5[[#This Row],[Order Date]]<=2,"Fast","Slow")),"") -> Slow
A39: ORD0038 | B39: 45160 | D39: 45162 | E39: CUST028 | F39: =_xlfn.XLOOKUP(AmazonSales5[[#This Row],[Customer ID]],customerdata[Customer ID],customerdata[Customer Name],"Not Found") -> Lily Bennett | G39: PROD007 | H39: North | I39: 32 | J39: 2 | K39: 64 | L39: Debit Card | M39: Cancelled | N39: FedEx | O39: =IFERROR(IF(AmazonSales5[[#This Row],[Delivery Date]]="", "", IF(AmazonSales5[[#This Row],[Delivery Date]]-AmazonSales5[[#This Row],[Order Date]]<=2,"Fast","Slow")),"")
A40: ORD0039 | B40: 44938 | E40: CUST024 | F40: =_xlfn.XLOOKUP(AmazonSales5[[#This Row],[Customer ID]],customerdata[Customer ID],customerdata[Customer Name],"Not Found") -> Scarlett Murphy | G40: PROD022 | H40: East | I40: 66 | J40: 2 | K40: 132 | L40: Apple Pay | M40: In Transit | N40: DHL | O40: =IFERROR(IF(AmazonSales5[[#This Row],[Delivery Date]]="", "", IF(AmazonSales5[[#This Row],[Delivery Date]]-AmazonSales5[[#This Row],[Order Date]]<=2,"Fast","Slow")),"")
A41: ORD0040 | B41: 44938 | E41: CUST006 | F41: =_xlfn.XLOOKUP(AmazonSales5[[#This Row],[Customer ID]],customerdata[Customer ID],customerdata[Customer Name],"Not Found") -> Ava Robinson | G41: PROD004 | H41: East | I41: 62 | J41: 4 | K41: 248 | L41: Debit Card | M41: In Transit | N41: UPS | O41: =IFERROR(IF(AmazonSales5[[#This Row],[Delivery Date]]="", "", IF(AmazonSales5[[#This Row],[Delivery Date]]-AmazonSales5[[#This Row],[Order Date]]<=2,"Fast","Slow")),"")
A42: ORD0041 | B42: 45192 | C42: 45199 | E42: CUST001 | F42: =_xlfn.XLOOKUP(AmazonSales5[[#This Row],[Customer ID]],customerdata[Customer ID],customerdata[Customer Name],"Not Found") -> James Miller | G42: PROD011 | H42: West | I42: 173 | J42: 4 | K42: 692 | L42: Apple Pay | M42: Delivered | N42: UPS | O42: =IFERROR(IF(AmazonSales5[[#This Row],[Delivery Date]]="", "", IF(AmazonSales5[[#This Row],[Delivery Date]]-AmazonSales5[[#This Row],[Order Date]]<=2,"Fast","Slow")),"") -> Slow
A43: ORD0042 | B43: 45123 | C43: 45125 | E43: CUST007 | F43: =_xlfn.XLOOKUP(AmazonSales5[[#This Row],[Customer ID]],customerdata[Customer ID],customerdata[Customer Name],"Not Found") -> Liam Walker | G43: PROD004 | H43: West | I43: 63 | J43: 3 | K43: 189 | L43: Apple Pay | M43: Delivered | N43: UPS | O43: =IFERROR(IF(AmazonSales5[[#This Row],[Delivery Date]]="", "", IF(AmazonSales5[[#This Row],[Delivery Date]]-AmazonSales5[[#This Row],[Order Date]]<=2,"Fast","Slow")),"") -> Fast
A44: ORD0043 | B44: 44962 | D44: 44968 | E44: CUST040 | F44: =_xlfn.XLOOKUP(AmazonSales5[[#This Row],[Customer ID]],customerdata[Customer ID],customerdata[Customer Name],"Not Found") -> Benjamin Clark | G44: PROD021 | H44: West | I44: 36 | J44: 3 | K44: 108 | L44: Debit Card | M44: Cancelled | N44: USPS | O44: =IFERROR(IF(AmazonSales5[[#This Row],[Delivery Date]]="", "", IF(AmazonSales5[[#This Row],[Delivery Date]]-AmazonSales5[[#This Row],[Order Date]]<=2,"Fast","Slow")),"")
A45: ORD0044 | B45: 45278 | D45: 45283 | E45: CUST006 | F45: =_xlfn.XLOOKUP(AmazonSales5[[#This Row],[Customer ID]],customerdata[Customer ID],customerdata[Customer Name],"Not Found") -> Ava Robinson | G45: PROD004 | H45: Central | I45: 62 | J45: 1 | K45: 62 | L45: Apple Pay | M45: Cancelled | N45: Amazon Logistics | O45: =IFERROR(IF(AmazonSales5[[#This Row],[Delivery Date]]="", "", IF(AmazonSales5[[#This Row],[Delivery Date]]-AmazonSales5[[#This Row],[Order Date]]<=2,"Fast","Slow")),"")
A46: ORD0045 | B46: 45088 | D46: 45091 | E46: CUST042 | F46: =_xlfn.XLOOKUP(AmazonSales5[[#This Row],[Customer ID]],customerdata[Customer ID],customerdata[Customer Name],"Not Found") -> Noah Wilson | G46: PROD003 | H46: Central | I46: 137 | J46: 5 | K46: 685 | L46: Amazon Pay | M46: Cancelled | N46: FedEx | O46: =IFERROR(IF(AmazonSales5[[#This Row],[Delivery Date]]="", "", IF(AmazonSales5[[#This Row],[Delivery Date]]-AmazonSales5[[#This Row],[Order Date]]<=2,"Fast","Slow")),"")
A47: ORD0046 | B47: 45264 | C47: 45268 | E47: CUST039 | F47: =_xlfn.XLOOKUP(AmazonSales5[[#This Row],[Customer ID]],customerdata[Customer ID],customerdata[Customer Name],"Not Found") -> Logan Ramirez | G47: PROD017 | H47: North | I47: 73 | J47: 4 | K47: 292 | L47: Credit Card | M47: Delivered | N47: Amazon Logistics | O47: =IFERROR(IF(AmazonSales5[[#This Row],[Delivery Date]]="", "", IF(AmazonSales5[[#This Row],[Delivery Date]]-AmazonSales5[[#This Row],[Order Date]]<=2,"Fast","Slow")),"") -> Slow
A48: ORD0047 | B48: 45124 | C48: 45126 | E48: CUST041 | F48: =_xlfn.XLOOKUP(AmazonSales5[[#This Row],[Customer ID]],customerdata[Customer ID],customerdata[Customer Name],"Not Found") -> Jacob Price | G48: PROD020 | H48: North | I48: 104 | J48: 1 | K48: 104 | L48: PayPal | M48: Delivered | N48: Amazon Logistics | O48: =IFERROR(IF(AmazonSales5[[#This Row],[Delivery Date]]="", "", IF(AmazonSales5[[#This Row],[Delivery Date]]-AmazonSales5[[#This Row],[Order Date]]<=2,"Fast","Slow")),"") -> Fast
A49: ORD0048 | B49: 45218 | C49: 45223 | E49: CUST044 | F49: =_xlfn.XLOOKUP(AmazonSales5[[#This Row],[Customer ID]],customerdata[Customer ID],customerdata[Customer Name],"Not Found") -> Grace Ward | G49: PROD006 | H49: East | I49: 97 | J49: 1 | K49: 97 | L49: Amazon Pay | M49: Delivered | N49: FedEx | O49: =IFERROR(IF(AmazonSales5[[#This Row],[Delivery Date]]="", "", IF(AmazonSales5[[#This Row],[Delivery Date]]-AmazonSales5[[#This Row],[Order Date]]<=2,"Fast","Slow")),"") -> Slow
A50: ORD0049 | B50: 45061 | E50: CUST026 | F50: =_xlfn.XLOOKUP(AmazonSales5[[#This Row],[Customer ID]],customerdata[Customer ID],customerdata[Customer Name],"Not Found") -> Zoe Mitchell | G50: PROD017 | H50: South | I50: 73 | J50: 5 | K50: 365 | L50: Apple Pay | M50: In Transit | N50: Amazon Logistics | O50: =IFERROR(IF(AmazonSales5[[#This Row],[Delivery Date]]="", "", IF(AmazonSales5[[#This Row],[Delivery Date]]-AmazonSales5[[#This Row],[Order Date]]<=2,"Fast","Slow")),"")
A51: ORD0050 | B51: 44938 | C51: 44976 | E51: CUST040 | F51: =_xlfn.XLOOKUP(AmazonSales5[[#This Row],[Customer ID]],customerdata[Customer ID],customerdata[Customer Name],"Not Found") -> Benjamin Clark | G51: PROD005 | H51: East | I51: 27 | J51: 3 | K51: 81 | L51: Amazon Pay | M51: Delivered | N51: UPS | O51: =IFERROR(IF(AmazonSales5[[#This Row],[Delivery Date]]="", "", IF(AmazonSales5[[#This Row],[Delivery Date]]-AmazonSales5[[#This Row],[Order Date]]<=2,"Fast","Slow")),"") -> Slow
A52: ORD0051 | B52: 44967 | E52: CUST041 | F52: =_xlfn.XLOOKUP(AmazonSales5[[#This Row],[Customer ID]],customerdata[Customer ID],customerdata[Customer Name],"Not Found") -> Jacob Price | G52: PROD021 | H52: North | I52: 37 | J52: 1 | K52: 37 | L52: Apple Pay | M52: In Transit | N52: UPS | O52: =IFERROR(IF(AmazonSales5[[#This Row],[Delivery Date]]="", "", IF(AmazonSales5[[#This Row],[Delivery Date]]-AmazonSales5[[#This Row],[Order Date]]<=2,"Fast","Slow")),"")
A53: ORD0052 | B53: 44956 | C53: 44928 | E53: CUST008 | F53: =_xlfn.XLOOKUP(AmazonSales5[[#This Row],[Customer ID]],customerdata[Customer ID],customerdata[Customer Name],"Not Found") -> Harper Young | G53: PROD015 | H53: North | I53: 22 | J53: 1 | K53: 22 | L53: Debit Card | M53: Delivered | N53: FedEx | O53: =IFERROR(IF(AmazonSales5[[#This Row],[Delivery Date]]="", "", IF(AmazonSales5[[#This Row],[Delivery Date]]-AmazonSales5[[#This Row],[Order Date]]<=2,"Fast","Slow")),"") -> Fast
A54: ORD0053 | B54: 45289 | C54: 45292 | E54: CUST011 | F54: =_xlfn.XLOOKUP(AmazonSales5[[#This Row],[Customer ID]],customerdata[Customer ID],customerdata[Customer Name],"Not Found") -> Mason Hall | G54: PROD016 | H54: Central | I54: 218 | J54: 5 | K54: 1090 | L54: PayPal | M54: Delivered | N54: DHL | O54: =IFERROR(IF(AmazonSales5[[#This Row],[Delivery Date]]="", "", IF(AmazonSales5[[#This Row],[Delivery Date]]-AmazonSales5[[#This Row],[Order Date]]<=2,"Fast","Slow")),"") -> Slow
A55: ORD0054 | B55: 44991 | D55: 44998 | E55: CUST018 | F55: =_xlfn.XLOOKUP(AmazonSales5[[#This Row],[Customer ID]],customerdata[Customer ID],customerdata[Customer Name],"Not Found") -> Grace Scott | G55: PROD004 | H55: North | I55: 64 | J55: 1 | K55: 64 | L55: Apple Pay | M55: Cancelled | N55: USPS | O55: =IFERROR(IF(AmazonSales5[[#This Row],[Delivery Date]]="", "", IF(AmazonSales5[[#This Row],[Delivery Date]]-AmazonSales5[[#This Row],[Order Date]]<=2,"Fast","Slow")),"")
A56: ORD0055 | B56: 44959 | C56: 45079 | E56: CUST037 | F56: =_xlfn.XLOOKUP(AmazonSales5[[#This Row],[Customer ID]],customerdata[Customer ID],customerdata[Customer Name],"Not Found") -> Emily Johnson | G56: PROD021 | H56: Central | I56: 36 | J56: 4 | K56: 144 | L56: PayPal | M56: Delivered | N56: Amazon Logistics | O56: =IFERROR(IF(AmazonSales5[[#This Row],[Delivery Date]]="", "", IF(AmazonSales5[[#This Row],[Delivery Date]]-AmazonSales5[[#This Row],[Order Date]]<=2,"Fast","Slow")),"") -> Slow
A57: ORD0056 | B57: 45217 | C57: 45220 | E57: CUST017 | F57: =_xlfn.XLOOKUP(AmazonSales5[[#This Row],[Customer ID]],customerdata[Customer ID],customerdata[Customer Name],"Not Found") -> Emma King | G57: PROD004 | H57: West | I57: 65 | J57: 1 | K57: 65 | L57: Amazon Pay | M57: Delivered | N57: FedEx | O57: =IFERROR(IF(AmazonSales5[[#This Row],[Delivery Date]]="", "", IF(AmazonSales5[[#This Row],[Delivery Date]]-AmazonSales5[[#This Row],[Order Date]]<=2,"Fast","Slow")),"") -> Slow
A58: ORD0057 | B58: 45108 | C58: 45170 | E58: CUST025 | F58: =_xlfn.XLOOKUP(AmazonSales5[[#This Row],[Customer ID]],customerdata[Customer ID],customerdata[Customer Name],"Not Found") -> Emma King | G58: PROD005 | H58: Central | I58: 26 | J58: 1 | K58: 26 | L58: Apple Pay | M58: Delivered | N58: DHL | O58: =IFERROR(IF(AmazonSales5[[#This Row],[Delivery Date]]="", "", IF(AmazonSales5[[#This Row],[Delivery Date]]-AmazonSales5[[#This Row],[Order Date]]<=2,"Fast","Slow")),"") -> Slow
A59: ORD0058 | B59: 45143 | E59: CUST021 | F59: =_xlfn.XLOOKUP(AmazonSales5[[#This Row],[Customer ID]],customerdata[Customer ID],customerdata[Customer Name],"Not Found") -> Zoe Mitchell | G59: PROD009 | H59: North | I59: 11 | J59: 5 | K59: 55 | L59: Credit Card | M59: In Transit | N59: FedEx | O59: =IFERROR(IF(AmazonSales5[[#This Row],[Delivery Date]]="", "", IF(AmazonSales5[[#This Row],[Delivery Date]]-AmazonSales5[[#This Row],[Order Date]]<=2,"Fast","Slow")),"")
A60: ORD0059 | B60: 44961 | D60: 45050 | E60: CUST003 | F60: =_xlfn.XLOOKUP(AmazonSales5[[#This Row],[Customer ID]],customerdata[Customer ID],customerdata[Customer Name],"Not Found") -> Ethan Davis | G60: PROD013 | H60: North | I60: 195 | J60: 4 | K60: 780 | L60: PayPal | M60: Cancelled | N60: FedEx | O60: =IFERROR(IF(AmazonSales5[[#This Row],[Delivery Date]]="", "", IF(AmazonSales5[[#This Row],[Delivery Date]]-AmazonSales5[[#This Row],[Order Date]]<=2,"Fast","Slow")),"")
A61: ORD0060 | B61: 45240 | D61: 45270 | E61: CUST019 | F61: =_xlfn.XLOOKUP(AmazonSales5[[#This Row],[Customer ID]],customerdata[Customer ID],customerdata[Customer Name],"Not Found") -> Ava Robinson | G61: PROD019 | H61: West | I61: 44 | J61: 5 | K61: 220 | L61: Apple Pay | M61: Cancelled | N61: USPS | O61: =IFERROR(IF(AmazonSales5[[#This Row],[Delivery Date]]="", "", IF(AmazonSales5[[#This Row],[Delivery Date]]-AmazonSales5[[#This Row],[Order Date]]<=2,"Fast","Slow")),"")
A62: ORD0061 | B62: 45208 | E62: CUST035 | F62: =_xlfn.XLOOKUP(AmazonSales5[[#This Row],[Customer ID]],customerdata[Customer ID],customerdata[Customer Name],"Not Found") -> Scarlett Adams | G62: PROD008 | H62: East | I62: 69 | J62: 4 | K62: 276 | L62: Debit Card | M62: In Transit | N62: DHL | O62: =IFERROR(IF(AmazonSales5[[#This Row],[Delivery Date]]="", "", IF(AmazonSales5[[#This Row],[Delivery Date]]-AmazonSales5[[#This Row],[Order Date]]<=2,"Fast","Slow")),"")
A63: ORD0062 | B63: 45252 | C63: 45259 | E63: CUST022 | F63: =_xlfn.XLOOKUP(AmazonSales5[[#This Row],[Customer ID]],customerdata[Customer ID],customerdata[Customer Name],"Not Found") -> Elijah Lewis | G63: PROD001 | H63: North | I63: 815 | J63: 4 | K63: 3260 | L63: Credit Card | M63: Delivered | N63: USPS | O63: =IFERROR(IF(AmazonSales5[[#This Row],[Delivery Date]]="", "", IF(AmazonSales5[[#This Row],[Delivery Date]]-AmazonSales5[[#This Row],[Order Date]]<=2,"Fast","Slow")),"") -> Slow
A64: ORD0063 | B64: 44962 | E64: CUST004 | F64: =_xlfn.XLOOKUP(AmazonSales5[[#This Row],[Customer ID]],customerdata[Customer ID],customerdata[Customer Name],"Not Found") -> Noah Wilson | G64: PROD005 | H64: East | I64: 27 | J64: 1 | K64: 27 | L64: Debit Card | M64: In Transit | N64: Amazon Logistics | O64: =IFERROR(IF(AmazonSales5[[#This Row],[Delivery Date]]="", "", IF(AmazonSales5[[#This Row],[Delivery Date]]-AmazonSales5[[#This Row],[Order Date]]<=2,"Fast","Slow")),"")
A65: ORD0064 | B65: 44938 | C65: 45289 | E65: CUST048 | F65: =_xlfn.XLOOKUP(AmazonSales5[[#This Row],[Customer ID]],customerdata[Customer ID],customerdata[Customer Name],"Not Found") -> Noah Wilson | G65: PROD003 | H65: West | I65: 139 | J65: 5 | K65: 695 | L65: Apple Pay | M65: Delivered | N65: USPS | O65: =IFERROR(IF(AmazonSales5[[#This Row],[Delivery Date]]="", "", IF(AmazonSales5[[#This Row],[Delivery Date]]-AmazonSales5[[#This Row],[Order Date]]<=2,"Fast","Slow")),"") -> Slow
A66: ORD0065 | B66: 45217 | D66: 45219 | E66: CUST009 | F66: =_xlfn.XLOOKUP(AmazonSales5[[#This Row],[Customer ID]],customerdata[Customer ID],customerdata[Customer Name],"Not Found") -> Jackson Allen | G66: PROD008 | H66: South | I66: 69 | J66: 3 | K66: 207 | L66: PayPal | M66: Cancelled | N66: Amazon Logistics | O66: =IFERROR(IF(AmazonSales5[[#This Row],[Delivery Date]]="", "", IF(AmazonSales5[[#This Row],[Delivery Date]]-AmazonSales5[[#This Row],[Order Date]]<=2,"Fast","Slow")),"")
A67: ORD0066 | B67: 45066 | D67: 45067 | E67: CUST009 | F67: =_xlfn.XLOOKUP(AmazonSales5[[#This Row],[Customer ID]],customerdata[Customer ID],customerdata[Customer Name],"Not Found") -> Jackson Allen | G67: PROD019 | H67: West | I67: 42 | J67: 1 | K67: 42 | L67: Apple Pay | M67: Cancelled | N67: DHL | O67: =IFERROR(IF(AmazonSales5[[#This Row],[Delivery Date]]="", "", IF(AmazonSales5[[#This Row],[Delivery Date]]-AmazonSales5[[#This Row],[Order Date]]<=2,"Fast","Slow")),"")
A68: ORD0067 | B68: 45135 | C68: 45137 | E68: CUST050 | F68: =_xlfn.XLOOKUP(AmazonSales5[[#This Row],[Customer ID]],customerdata[Customer ID],customerdata[Customer Name],"Not Found") -> Not Found | G68: PROD007 | H68: North | I68: 31 | J68: 4 | K68: 124 | L68: Credit Card | M68: Delivered | N68: UPS | O68: =IFERROR(IF(AmazonSales5[[#This Row],[Delivery Date]]="", "", IF(AmazonSales5[[#This Row],[Delivery Date]]-AmazonSales5[[#This Row],[Order Date]]<=2,"Fast","Slow")),"") -> Fast
A69: ORD0068 | B69: 45278 | E69: CUST045 | F69: =_xlfn.XLOOKUP(AmazonSales5[[#This Row],[Customer ID]],customerdata[Customer ID],customerdata[Customer Name],"Not Found") -> Emily Johnson | G69: PROD020 | H69: West | I69: 104 | J69: 3 | K69: 312 | L69: Credit Card | M69: In Transit | N69: UPS | O69: =IFERROR(IF(AmazonSales5[[#This Row],[Delivery Date]]="", "", IF(AmazonSales5[[#This Row],[Delivery Date]]-AmazonSales5[[#This Row],[Order Date]]<=2,"Fast","Slow")),"")
A70: ORD0069 | B70: 44964 | D70: 45114 | E70: CUST044 | F70: =_xlfn.XLOOKUP(AmazonSales5[[#This Row],[Customer ID]],customerdata[Customer ID],customerdata[Customer Name],"Not Found") -> Grace Ward | G70: PROD010 | H70: East | I70: 58 | J70: 2 | K70: 116 | L70: Apple Pay | M70: Cancelled | N70: USPS | O70: =IFERROR(IF(AmazonSales5[[#This Row],[Delivery Date]]="", "", IF(AmazonSales5[[#This Row],[Delivery Date]]-AmazonSales5[[#This Row],[Order Date]]<=2,"Fast","Slow")),"")
A71: ORD0070 | B71: 45179 | D71: 45209 | E71: CUST009 | F71: =_xlfn.XLOOKUP(AmazonSales5[[#This Row],[Customer ID]],customerdata[Customer ID],customerdata[Customer Name],"Not Found") -> Jackson Allen | G71: PROD004 | H71: West | I71: 62 | J71: 2 | K71: 124 | L71: Debit Card | M71: Cancelled | N71: DHL | O71: =IFERROR(IF(AmazonSales5[[#This Row],[Delivery Date]]="", "", IF(AmazonSales5[[#This Row],[Delivery Date]]-AmazonSales5[[#This Row],[Order Date]]<=2,"Fast","Slow")),"")
A72: ORD0071 | B72: 45278 | C72: 45285 | E72: CUST006 | F72: =_xlfn.XLOOKUP(AmazonSales5[[#This Row],[Customer ID]],customerdata[Customer ID],customerdata[Customer Name],"Not Found") -> Ava Robinson | G72: PROD019 | H72: East | I72: 43 | J72: 1 | K72: 43 | L72: Credit Card | M72: Delivered | N72: Amazon Logistics | O72: =IFERROR(IF(AmazonSales5[[#This Row],[Delivery Date]]="", "", IF(AmazonSales5[[#This Row],[Delivery Date]]-AmazonSales5[[#This Row],[Order Date]]<=2,"Fast","Slow")),"") -> Slow
A73: ORD0072 | B73: 45110 | E73: CUST022 | F73: =_xlfn.XLOOKUP(AmazonSales5[[#This Row],[Customer ID]],customerdata[Customer ID],customerdata[Customer Name],"Not Found") -> Elijah Lewis | G73: PROD004 | H73: East | I73: 62 | J73: 4 | K73: 248 | L73: Debit Card | M73: In Transit | N73: Amazon Logistics | O73: =IFERROR(IF(AmazonSales5[[#This Row],[Delivery Date]]="", "", IF(AmazonSales5[[#This Row],[Delivery Date]]-AmazonSales5[[#This Row],[Order Date]]<=2,"Fast","Slow")),"")
A74: ORD0073 | B74: 45129 | D74: 45132 | E74: CUST028 | F74: =_xlfn.XLOOKUP(AmazonSales5[[#This Row],[Customer ID]],customerdata[Customer ID],customerdata[Customer Name],"Not Found") -> Lily Bennett | G74: PROD006 | H74: North | I74: 95 | J74: 2 | K74: 190 | L74: PayPal | M74: Cancelled | N74: UPS | O74: =IFERROR(IF(AmazonSales5[[#This Row],[Delivery Date]]="", "", IF(AmazonSales5[[#This Row],[Delivery Date]]-AmazonSales5[[#This Row],[Order Date]]<=2,"Fast","Slow")),"")
A75: ORD0074 | B75: 44944 | C75: 44950 | E75: CUST016 | F75: =_xlfn.XLOOKUP(AmazonSales5[[#This Row],[Customer ID]],customerdata[Customer ID],customerdata[Customer Name],"Not Found") -> Elijah Lewis | G75: PROD021 | H75: Central | I75: 36 | J75: 4 | K75: 144 | L75: Apple Pay | M75: Delivered | N75: FedEx | O75: =IFERROR(IF(AmazonSales5[[#This Row],[Delivery Date]]="", "", IF(AmazonSales5[[#This Row],[Delivery Date]]-AmazonSales5[[#This Row],[Order Date]]<=2,"Fast","Slow")),"") -> Slow
A76: ORD0075 | B76: 45070 | E76: CUST042 | F76: =_xlfn.XLOOKUP(AmazonSales5[[#This Row],[Customer ID]],customerdata[Customer ID],customerdata[Customer Name],"Not Found") -> Noah Wilson | G76: PROD017 | H76: East | I76: 73 | J76: 5 | K76: 365 | L76: Apple Pay | M76: In Transit | N76: DHL | O76: =IFERROR(IF(AmazonSales5[[#This Row],[Delivery Date]]="", "", IF(AmazonSales5[[#This Row],[Delivery Date]]-AmazonSales5[[#This Row],[Order Date]]<=2,"Fast","Slow")),"")
A77: ORD0076 | B77: 44994 | C77: 45178 | E77: CUST023 | F77: =_xlfn.XLOOKUP(AmazonSales5[[#This Row],[Customer ID]],customerdata[Customer ID],customerdata[Customer Name],"Not Found") -> Charlotte Reed | G77: PROD019 | H77: North | I77: 43 | J77: 4 | K77: 172 | L77: Debit Card | M77: Delivered | N77: DHL | O77: =IFERROR(IF(AmazonSales5[[#This Row],[Delivery Date]]="", "", IF(AmazonSales5[[#This Row],[Delivery Date]]-AmazonSales5[[#This Row],[Order Date]]<=2,"Fast","Slow")),"") -> Slow
A78: ORD0077 | B78: 45232 | C78: 45234 | E78: CUST004 | F78: =_xlfn.XLOOKUP(AmazonSales5[[#This Row],[Customer ID]],customerdata[Customer ID],customerdata[Customer Name],"Not Found") -> Noah Wilson | G78: PROD016 | H78: West | I78: 214 | J78: 5 | K78: 1070 | L78: Debit Card | M78: Delivered | N78: UPS | O78: =IFERROR(IF(AmazonSales5[[#This Row],[Delivery Date]]="", "", IF(AmazonSales5[[#This Row],[Delivery Date]]-AmazonSales5[[#This Row],[Order Date]]<=2,"Fast","Slow")),"") -> Fast
A79: ORD0078 | B79: 44997 | D79: 45089 | E79: CUST048 | F79: =_xlfn.XLOOKUP(AmazonSales5[[#This Row],[Customer ID]],customerdata[Customer ID],customerdata[Customer Name],"Not Found") -> Noah Wilson | G79: PROD002 | H79: Central | I79: 42 | J79: 2 | K79: 84 | L79: Apple Pay | M79: Cancelled | N79: UPS | O79: =IFERROR(IF(AmazonSales5[[#This Row],[Delivery Date]]="", "", IF(AmazonSales5[[#This Row],[Delivery Date]]-AmazonSales5[[#This Row],[Order Date]]<=2,"Fast","Slow")),"")
A80: ORD0079 | B80: 44930 | E80: CUST048 | F80: =_xlfn.XLOOKUP(AmazonSales5[[#This Row],[Customer ID]],customerdata[Customer ID],customerdata[Customer Name],"Not Found") -> Noah Wilson | G80: PROD012 | H80: North | I80: 46 | J80: 1 | K80: 46 | L80: Amazon Pay | M80: In Transit | N80: UPS | O80: =IFERROR(IF(AmazonSales5[[#This Row],[Delivery Date]]="", "", IF(AmazonSales5[[#This Row],[Delivery Date]]-AmazonSales5[[#This Row],[Order Date]]<=2,"Fast","Slow")),"")
A81: ORD0080 | B81: 45215 | C81: 45218 | E81: CUST032 | F81: =_xlfn.XLOOKUP(AmazonSales5[[#This Row],[Customer ID]],customerdata[Customer ID],customerdata[Customer Name],"Not Found") -> Luke Gray | G81: PROD018 | H81: East | I81: 95 | J81: 4 | K81: 380 | L81: Credit Card | M81: Delivered | N81: UPS | O81: =IFERROR(IF(AmazonSales5[[#This Row],[Delivery Date]]="", "", IF(AmazonSales5[[#This Row],[Delivery Date]]-AmazonSales5[[#This Row],[Order Date]]<=2,"Fast","Slow")),"") -> Slow
A82: ORD0081 | B82: 45057 | E82: CUST001 | F82: =_xlfn.XLOOKUP(AmazonSales5[[#This Row],[Customer ID]],customerdata[Customer ID],customerdata[Customer Name],"Not Found") -> James Miller | G82: PROD011 | H82: West | I82: 174 | J82: 2 | K82: 348 | L82: PayPal | M82: In Transit | N82: UPS | O82: =IFERROR(IF(AmazonSales5[[#This Row],[Delivery Date]]="", "", IF(AmazonSales5[[#This Row],[Delivery Date]]-AmazonSales5[[#This Row],[Order Date]]<=2,"Fast","Slow")),"")
A83: ORD0082 | B83: 45092 | D83: 45095 | E83: CUST046 | F83: =_xlfn.XLOOKUP(AmazonSales5[[#This Row],[Customer ID]],customerdata[Customer ID],customerdata[Customer Name],"Not Found") -> Emily Johnson | G83: PROD005 | H83: North | I83: 27 | J83: 5 | K83: 135 | L83: Credit Card | M83: Cancelled | N83: Amazon Logistics | O83: =IFERROR(IF(AmazonSales5[[#This Row],[Delivery Date]]="", "", IF(AmazonSales5[[#This Row],[Delivery Date]]-AmazonSales5[[#This Row],[Order Date]]<=2,"Fast","Slow")),"")
A84: ORD0083 | B84: 45227 | C84: 45229 | E84: CUST021 | F84: =_xlfn.XLOOKUP(AmazonSales5[[#This Row],[Customer ID]],customerdata[Customer ID],customerdata[Customer Name],"Not Found") -> Zoe Mitchell | G84: PROD005 | H84: South | I84: 27 | J84: 4 | K84: 108 | L84: PayPal | M84: Delivered | N84: USPS | O84: =IFERROR(IF(AmazonSales5[[#This Row],[Delivery Date]]="", "", IF(AmazonSales5[[#This Row],[Delivery Date]]-AmazonSales5[[#This Row],[Order Date]]<=2,"Fast","Slow")),"") -> Fast
A85: ORD0084 | B85: 44938 | E85: CUST015 | F85: =_xlfn.XLOOKUP(AmazonSales5[[#This Row],[Customer ID]],customerdata[Customer ID],customerdata[Customer Name],"Not Found") -> Ava White | G85: PROD022 | H85: South | I85: 65 | J85: 2 | K85: 130 | L85: PayPal | M85: In Transit | N85: DHL | O85: =IFERROR(IF(AmazonSales5[[#This Row],[Delivery Date]]="", "", IF(AmazonSales5[[#This Row],[Delivery Date]]-AmazonSales5[[#This Row],[Order Date]]<=2,"Fast","Slow")),"")
A86: ORD0085 | B86: 45110 | E86: CUST045 | F86: =_xlfn.XLOOKUP(AmazonSales5[[#This Row],[Customer ID]],customerdata[Customer ID],customerdata[Customer Name],"Not Found") -> Emily Johnson | G86: PROD019 | H86: East | I86: 43 | J86: 5 | K86: 215 | L86: Debit Card | M86: In Transit | N86: DHL | O86: =IFERROR(IF(AmazonSales5[[#This Row],[Delivery Date]]="", "", IF(AmazonSales5[[#This Row],[Delivery Date]]-AmazonSales5[[#This Row],[Order Date]]<=2,"Fast","Slow")),"")
A87: ORD0086 | B87: 45210 | E87: CUST007 | F87: =_xlfn.XLOOKUP(AmazonSales5[[#This Row],[Customer ID]],customerdata[Customer ID],customerdata[Customer Name],"Not Found") -> Liam Walker | G87: PROD016 | H87: West | I87: 210 | J87: 1 | K87: 210 | L87: PayPal | M87: In Transit | N87: UPS | O87: =IFERROR(IF(AmazonSales5[[#This Row],[Delivery Date]]="", "", IF(AmazonSales5[[#This Row],[Delivery Date]]-AmazonSales5[[#This Row],[Order Date]]<=2,"Fast","Slow")),"")
A88: ORD0087 | B88: 45252 | E88: CUST043 | F88: =_xlfn.XLOOKUP(AmazonSales5[[#This Row],[Customer ID]],customerdata[Customer ID],customerdata[Customer Name],"Not Found") -> Lily Reed | G88: PROD021 | H88: South | I88: 37 | J88: 3 | K88: 111 | L88: Credit Card | M88: In Transit | N88: UPS | O88: =IFERROR(IF(AmazonSales5[[#This Row],[Delivery Date]]="", "", IF(AmazonSales5[[#This Row],[Delivery Date]]-AmazonSales5[[#This Row],[Order Date]]<=2,"Fast","Slow")),"")
A89: ORD0088 | B89: 45143 | E89: CUST007 | F89: =_xlfn.XLOOKUP(AmazonSales5[[#This Row],[Customer ID]],customerdata[Customer ID],customerdata[Customer Name],"Not Found") -> Liam Walker | G89: PROD001 | H89: South | I89: 788 | J89: 4 | K89: 3152 | L89: Debit Card | M89: In Transit | N89: Amazon Logistics | O89: =IFERROR(IF(AmazonSales5[[#This Row],[Delivery Date]]="", "", IF(AmazonSales5[[#This Row],[Delivery Date]]-AmazonSales5[[#This Row],[Order Date]]<=2,"Fast","Slow")),"")
A90: ORD0089 | B90: 45120 | E90: CUST007 | F90: =_xlfn.XLOOKUP(AmazonSales5[[#This Row],[Customer ID]],customerdata[Customer ID],customerdata[Customer Name],"Not Found") -> Liam Walker | G90: PROD016 | H90: West | I90: 217 | J90: 5 | K90: 1085 | L90: Debit Card | M90: In Transit | N90: FedEx | O90: =IFERROR(IF(AmazonSales5[[#This Row],[Delivery Date]]="", "", IF(AmazonSales5[[#This Row],[Delivery Date]]-AmazonSales5[[#This Row],[Order Date]]<=2,"Fast","Slow")),"")
A91: ORD0090 | B91: 44944 | E91: CUST007 | F91: =_xlfn.XLOOKUP(AmazonSales5[[#This Row],[Customer ID]],customerdata[Customer ID],customerdata[Customer Name],"Not Found") -> Liam Walker | G91: PROD003 | H91: West | I91: 138 | J91: 4 | K91: 552 | L91: Credit Card | M91: In Transit | N91: FedEx | O91: =IFERROR(IF(AmazonSales5[[#This Row],[Delivery Date]]="", "", IF(AmazonSales5[[#This Row],[Delivery Date]]-AmazonSales5[[#This Row],[Order Date]]<=2,"Fast","Slow")),"")
A92: ORD0091 | B92: 45100 | C92: 45106 | E92: CUST031 | F92: =_xlfn.XLOOKUP(AmazonSales5[[#This Row],[Customer ID]],customerdata[Customer ID],customerdata[Customer Name],"Not Found") -> Mason Collins | G92: PROD001 | H92: Central | I92: 803 | J92: 2 | K92: 1606 | L92: Apple Pay | M92: Delivered | N92: FedEx | O92: =IFERROR(IF(AmazonSales5[[#This Row],[Delivery Date]]="", "", IF(AmazonSales5[[#This Row],[Delivery Date]]-AmazonSales5[[#This Row],[Order Date]]<=2,"Fast","Slow")),"") -> Slow
A93: ORD0092 | B93: 44978 | D93: 44982 | E93: CUST013 | F93: =_xlfn.XLOOKUP(AmazonSales5[[#This Row],[Customer ID]],customerdata[Customer ID],customerdata[Customer Name],"Not Found") -> Olivia Martinez | G93: PROD014 | H93: North | I93: 248 | J93: 5 | K93: 1240 | L93: PayPal | M93: Cancelled | N93: UPS | O93: =IFERROR(IF(AmazonSales5[[#This Row],[Delivery Date]]="", "", IF(AmazonSales5[[#This Row],[Delivery Date]]-AmazonSales5[[#This Row],[Order Date]]<=2,"Fast","Slow")),"")
A94: ORD0093 | B94: 44976 | C94: 44978 | E94: CUST036 | F94: =_xlfn.XLOOKUP(AmazonSales5[[#This Row],[Customer ID]],customerdata[Customer ID],customerdata[Customer Name],"Not Found") -> Ethan Davis | G94: PROD016 | H94: East | I94: 210 | J94: 3 | K94: 630 | L94: Apple Pay | M94: Delivered | N94: DHL | O94: =IFERROR(IF(AmazonSales5[[#This Row],[Delivery Date]]="", "", IF(AmazonSales5[[#This Row],[Delivery Date]]-AmazonSales5[[#This Row],[Order Date]]<=2,"Fast","Slow")),"") -> Fast
A95: ORD0094 | B95: 45201 | D95: 45272 | E95: CUST013 | F95: =_xlfn.XLOOKUP(AmazonSales5[[#This Row],[Customer ID]],customerdata[Customer ID],customerdata[Customer Name],"Not Found") -> Olivia Martinez | G95: PROD004 | H95: North | I95: 62 | J95: 2 | K95: 124 | L95: Credit Card | M95: Cancelled | N95: FedEx | O95: =IFERROR(IF(AmazonSales5[[#This Row],[Delivery Date]]="", "", IF(AmazonSales5[[#This Row],[Delivery Date]]-AmazonSales5[[#This Row],[Order Date]]<=2,"Fast","Slow")),"")
A96: ORD0095 | B96: 45084 | D96: 45089 | E96: CUST043 | F96: =_xlfn.XLOOKUP(AmazonSales5[[#This Row],[Customer ID]],customerdata[Customer ID],customerdata[Customer Name],"Not Found") -> Lily Reed | G96: PROD009 | H96: South | I96: 11 | J96: 5 | K96: 55 | L96: Debit Card | M96: Cancelled | N96: Amazon Logistics | O96: =IFERROR(IF(AmazonSales5[[#This Row],[Delivery Date]]="", "", IF(AmazonSales5[[#This Row],[Delivery Date]]-AmazonSales5[[#This Row],[Order Date]]<=2,"Fast","Slow")),"")
A97: ORD0096 | B97: 45116 | C97: 45267 | E97: CUST017 | F97: =_xlfn.XLOOKUP(AmazonSales5[[#This Row],[Customer ID]],customerdata[Customer ID],customerdata[Customer Name],"Not Found") -> Emma King | G97: PROD015 | H97: North | I97: 21 | J97: 2 | K97: 42 | L97: Amazon Pay | M97: Delivered | N97: UPS | O97: =IFERROR(IF(AmazonSales5[[#This Row],[Delivery Date]]="", "", IF(AmazonSales5[[#This Row],[Delivery Date]]-AmazonSales5[[#This Row],[Order Date]]<=2,"Fast","Slow")),"") -> Slow
A98: ORD0097 | B98: 45283 | C98: 45286 | E98: CUST023 | F98: =_xlfn.XLOOKUP(AmazonSales5[[#This Row],[Customer ID]],customerdata[Customer ID],customerdata[Customer Name],"Not Found") -> Charlotte Reed | G98: PROD018 | H98: West | I98: 95 | J98: 5 | K98: 475 | L98: Amazon Pay | M98: Delivered | N98: Amazon Logistics | O98: =IFERROR(IF(AmazonSales5[[#This Row],[Delivery Date]]="", "", IF(AmazonSales5[[#This Row],[Delivery Date]]-AmazonSales5[[#This Row],[Order Date]]<=2,"Fast","Slow")),"") -> Slow
A99: ORD0098 | B99: 45194 | C99: 45199 | E99: CUST044 | F99: =_xlfn.XLOOKUP(AmazonSales5[[#This Row],[Customer ID]],customerdata[Customer ID],customerdata[Customer Name],"Not Found") -> Grace Ward | G99: PROD016 | H99: South | I99: 215 | J99: 2 | K99: 430 | L99: PayPal | M99: Delivered | N99: Amazon Logistics | O99: =IFERROR(IF(AmazonSales5[[#This Row],[Delivery Date]]="", "", IF(AmazonSales5[[#This Row],[Delivery Date]]-AmazonSales5[[#This Row],[Order Date]]<=2,"Fast","Slow")),"") -> Slow
A100: ORD0099 | B100: 44944 | D100: 44950 | E100: CUST034 | F100: =_xlfn.XLOOKUP(AmazonSales5[[#This Row],[Customer ID]],customerdata[Customer ID],customerdata[Customer Name],"Not Found") -> Lily Simmons | G100: PROD019 | H100: West | I100: 43 | J100: 5 | K100: 215 | L100: Credit Card | M100: Cancelled | N100: UPS | O100: =IFERROR(IF(AmazonSales5[[#This Row],[Delivery Date]]="", "", IF(AmazonSales5[[#This Row],[Delivery Date]]-AmazonSales5[[#This Row],[Order Date]]<=2,"Fast","Slow")),"")
...

Sheet Task4
A1: ● Create a field: Cancellation Rate by Region (Cancelled Orders / Total Orders)
A2: ● Add Calculated Field in Pivot: Effective Sales = Sales Amount for Delivered Orders only
A4: Regions | B4: Total Orders | C4: Cancelled Orders | D4: Delivered Orders | E4: Effective Sales | F4: Cancellation Rate | G4: Total Sales
A5: Central | B5: 14 | C5: 5 | D5: 5 | E5: 3010 | F5: 0.35714286 | G5: 5456
A6: East | B6: 18 | C6: 3 | D6: 8 | E6: 1842 | F6: 0.16666667 | G6: 3635
A7: North | B7: 25 | C7: 10 | D7: 8 | E7: 4075 | F7: 0.4 | G7: 10491
A8: South | B8: 20 | C8: 4 | D8: 6 | E8: 1063 | F8: 0.2 | G8: 7317
A9: West | B9: 23 | C9: 8 | D9: 7 | E9: 3666 | F9: 0.34782609 | G9: 8359
A10: Grand Total | B10: 100 | C10: 30 | D10: 34 | E10: 13656 | F10: 0.3 | G10: 35258
A13: KPI Cards for:
A14: ○ Total Revenue | C14: =GETPIVOTDATA("Total Revenue",$A$20) -> 35258 | I14: Total Sales | J14: Column Labels
A15: ○ % of Fast Deliveries | C15: =GETPIVOTDATA("Fast delivery %",$A$20) -> 0.32352941 | I15: Row Labels | J15: Central | K15: East | L15: North | M15: South | N15: West | O15: Grand Total
A16: ○ Top 3 Performing Regions | C16: North>West>South | I16: Smartphone | J16: 1606 | L16: 4886 | M16: 3152 | O16: 9644
A17: ○ Highest-selling Product | C17: Smartphone | I17: Cookware Set Pro | J17: 1090 | K17: 630 | L17: 636 | M17: 430 | N17: 2365 | O17: 5151
I18: Cookware Set | J18: 685 | M18: 564 | N18: 1247 | O18: 2496
I19: Smartwatch | J19: 741 | L19: 1240 | M19: 249 | O19: 2230
A20: Row Labels | B20: Fast delivery % | C20: Total Revenue | D20: Total orders | I20: Vacuum Cleaner | L20: 1368 | M20: 776 | O20: 2144
A21: Central | B21: 0.2 | C21: 5456 | D21: 14 | I21: Doll House | J21: 291 | K21: 764 | N21: 475 | O21: 1530
A22: East | B22: 0.25 | C22: 3635 | D22: 18 | I22: Gaming Mouse | K22: 365 | L22: 292 | M22: 365 | N22: 370 | O22: 1392
A23: North | B23: 0.375 | C23: 10491 | D23: 25 | I23: Textbook | K23: 276 | L23: 345 | M23: 347 | N23: 350 | O23: 1318
A24: South | B24: 0.5 | C24: 7317 | D24: 20 | I24: Shoes | J24: 96 | K24: 97 | L24: 190 | M24: 376 | N24: 480 | O24: 1239
A25: West | B25: 0.28571429 | C25: 8359 | D25: 23 | I25: Headphones | M25: 172 | N25: 1040 | O25: 1212
A26: Grand Total | B26: 0.32352941 | C26: 35258 | D26: 100 | I26: Leg Set | J26: 62 | K26: 496 | L26: 188 | N26: 378 | O26: 1124
I27: Formal Shirt | J27: 88 | K27: 258 | L27: 172 | N27: 477 | O27: 995
I28: Wall Clock | J28: 288 | K28: 111 | L28: 37 | M28: 111 | N28: 293 | O28: 840
I29: Bluetooth Speaker | J29: 315 | L29: 104 | N29: 312 | O29: 731
A30: Regionwise Sales | I30: Action Figure | J30: 84 | K30: 164 | L30: 210 | M30: 43 | N30: 168 | O30: 669
A31: Row Labels | B31: Central | C31: East | D31: North | E31: South | F31: West | G31: Grand Total | I31: Jeans | K31: 116 | L31: 291 | N31: 174 | O31: 581
A32: Qtr1 | B32: 578 | C32: 1618 | D32: 3035 | E32: 351 | F32: 1772 | G32: 7354 | I32: T-Shirt | J32: 26 | K32: 108 | L32: 135 | M32: 270 | O32: 539
A33: Jan | B33: 170 | C33: 461 | D33: 300 | E33: 270 | F33: 952 | G33: 2153 | I33: Backpack | K33: 132 | M33: 386 | O33: 518
A34: Feb | B34: 324 | C34: 1157 | D34: 2461 | E34: 81 | F34: 652 | G34: 4675 | I34: Lamp | L34: 90 | N34: 230 | O34: 320
A35: Mar | B35: 84 | D35: 274 | F35: 168 | G35: 526 | I35: Novel | J35: 84 | K35: 63 | L35: 64 | M35: 21 | O35: 232
A36: Qtr2 | B36: 2291 | C36: 483 | D36: 723 | E36: 766 | F36: 390 | G36: 4653 | I36: Puzzle | L36: 188 | O36: 188
A37: Apr | E37: 249 | G37: 249 | I37: Magazine | K37: 55 | L37: 55 | M37: 55 | O37: 165
A38: May | C38: 365 | D38: 588 | E38: 462 | F38: 390 | G38: 1805 | I38: Grand Total | J38: 5456 | K38: 3635 | L38: 10491 | M38: 7317 | N38: 8359 | O38: 35258
A39: Jun | B39: 2291 | C39: 118 | D39: 135 | E39: 55 | G39: 2599
A40: Qtr3 | B40: 1435 | C40: 574 | D40: 1387 | E40: 3985 | F40: 2320 | G40: 9701
A41: Jul | B41: 829 | C41: 574 | D41: 1096 | F41: 1274 | G41: 3773
A42: Aug | B42: 315 | D42: 119 | E42: 3555 | G42: 3989
A43: Sep | B43: 291 | D43: 172 | E43: 430 | F43: 1046 | G43: 1939
A44: Qtr4 | B44: 1152 | C44: 960 | D44: 5346 | E44: 2215 | F44: 3877 | G44: 13550
A45: Oct | C45: 917 | D45: 124 | E45: 571 | F45: 275 | G45: 1887
A46: Nov | D46: 3260 | E46: 908 | F46: 2120 | G46: 6288
A47: Dec | B47: 1152 | C47: 43 | D47: 1962 | E47: 736 | F47: 1482 | G47: 5375
A48: Grand Total | B48: 5456 | C48: 3635 | D48: 10491 | E48: 7317 | F48: 8359 | G48: 35258
A51: Count of Order count | B51: Column Labels
A52: Row Labels | B52: Cancelled | C52: Delivered | D52: In Transit | E52: Total Orders
A53: Books | B53: 3 | C53: 3 | D53: 7 | E53: 13
A54: Electronics | B54: 4 | C54: 6 | D54: 7 | E54: 17
A55: Fashion | B55: 10 | C55: 10 | D55: 7 | E55: 27
A56: Home | B56: 7 | C56: 7 | D56: 10 | E56: 24
A57: Toys | B57: 6 | C57: 8 | D57: 5 | E57: 19
A58: Total Orders | B58: 30 | C58: 34 | D58: 36 | E58: 100

Sheet Dashboard
A1: DASHBOARD- YEARLY STOCK DATA
L5: TOTAL SALES | N5: =SUM(AmazonSales5[Total Amount]) -> 35258
L11: TOTAL ORDERS | N11: =COUNT(AmazonSales5[Total Amount]) -> 100
L17: TOTAL PRODUCTS | N17: =COUNTA(Product_table[Product Name]) -> 22
L23: NO OF DELIVERED ORDERS | N23: =GETPIVOTDATA("Delivered Orders",Task4!$A$4) -> 34
L29: FAST DELIVERY % | N29: =GETPIVOTDATA("Fast delivery %",Task4!$A$20) -> 0.32352941
L35: NO OF CANCELLED ORDERS | N35: =GETPIVOTDATA("Order count",Task4!$A$51,"Delivery Status","Cancelled") -> 30
L41: HIGHEST SELLING PRODUCT | N41: =Task4!I16 -> Smartphone
L45: Select the Order ID below to get the delivery status and payment method of the order
L47: ORDER ID | N47: ORD0013
L50: PRODUCT NAME | N50: =_xlfn.XLOOKUP(N47,Task1!B2:B101,Task1!I2:I101) -> Shoes
L53: DELIVERY STATUS | N53: =_xlfn.XLOOKUP(N47,Task1!B2:B101,Task1!O2:O101) -> Cancelled
L56: PAYMENT METHOD | N56: =_xlfn.XLOOKUP(N47,Task1!B2:B101,Task1!N2:N101) -> Apple Pay

Sheet Brainstorm
A2: ●What is the most successful product category in terms of revenue? | H2: Electronics
A3: ●Which region has the highest order cancellation rate? | H3: North
A4: ●How many orders were delivered within 2 days? | H4: 11 orders
A5: ●How has the use of XLOOKUP simplified cross-sheet analysis?
A6: XLOOKUP has simplified the cross‑sheet analysis by allowing directly link values between all the sheets without any issue of the column position. It helped simplify the pivot table creation by just linking the values from one table to another, for example the product name and the product category in the AmazonSales table from the Producttable.
A10: ●What recommendations would you give to improve delivery performance?
A11: Delivery performance can be improved by focusing on low‑performing regions, aligning actuals with goals, monitoring employee achievement %, and addressing weak months.
